Workbook

Sheet Cover
A1: Birmarket.az — Bitirmə Layihəsi: Test Sənədləri
A2: UI (Web) + API test ssenariləri, test case-lər, avtomatlaşdırma strategiyası
A4: Layihə | B4: Birmarket.az (Umico) — onlayn marketplace
A5: Test obyekti (URL) | B5: https://birmarket.az/ (Production, public)
A6: Hazırlayan | B6: Zərifə Babayeva
A7: Kurs / Qrup | B7: ABB Tech Academy — QA
A8: Versiya | B8: 1.1
A9: Tarix | B9: 13.10.2026
A10: Mühit | B10: Windows 11 / macOS, Google Chrome (son stabil versiya), 1920×1080; dil AZ; şəhər Bakı
A11: Test perspektivi | B11: Black Box (UI) + Grey Box (API)
A12: Tətbiq olunan texnikalar | B12: Equivalence Partitioning, Boundary Value Analysis, Decision Table, State Transition, Error Guessing
A14: Sheet-lər
A15: Test Scope | B15: Nə test olunur / nə test olunmur və səbəbləri
A16: Test Scenarios | B16: Yüksək səviyyəli ssenarilər — Guest və Login versiyaları ayrıca
A17: Test Cases | B17: UI test case-lər (strukturlu, manual/avtomat əsaslandırması ilə)
A18: Automation Strategy | B18: Manual vs avtomat seçim kriteriyaları və anti-flaky qaydalar
A19: RTM | B19: Ssenari → test case → avtomatlaşdırma izlənməsi (formula ilə)
A20: Summary | B20: Ümumi göstəricilər (formula ilə avtomatik hesablanır)
A21: Grooming Questions | B21: Tələblərdə qeyri-müəyyən məqamlar üzrə suallar və qəbul edilmiş fərziyyələr
A22: Assumptions & Risks | B22: Fərziyyələr, risklər və onların idarə olunması
A23: Bug Reports | B23: İcra zamanı tapılan defektlər
A24: API_* sheet-lər | B24: API (api.anarabbas.com, Final Project backlog): Test Plan, Scenarios, 168 Test Case, Decision Table, Coverage, Traceability, Grooming Questions
A26: Doldurma qaydası (Legend)
A27: Status | B27: Not Run / Pass / Fail / Blocked — icradan sonra Test Cases sheet-ində seçilir (dropdown)
A28: Automation | B28: Automated — avtomatlaşdırılıb / Manual — manual icra olunur
A29: Regression | B29: Yes — avtomat regression / Yes (Manual) — manual regression / No — regression-a daxil deyil
A30: Priority | B30: P1 - Critical / P2 - High / P3 - Medium / P4 - Low
A31: Actual Result / Execution Date / İcra növü | B31: Test Cases sheet-inin sonundakı sütunlar: faktiki nəticə, icra tarixi və icra üsulu (Avtomat / Manual)

Sheet Test Scope
A1: Test Scope
A2: Test obyekti: https://birmarket.az/ (Production). Real sifariş və ödəniş YARADILMIR.
A4: IN SCOPE
A5: Modul / Funksionallıq | B5: Səviyyə | C5: Səbəb | D5: Ssenari
A6: Ana səhifə və header | B6: UI | C6: Hər istifadəçinin giriş nöqtəsi; smoke üçün əsas | D6: TS_UI_01
A7: Dil seçimi (AZ/RU) | B7: UI | C7: İki dilli auditoriya, URL strukturuna təsir edir | D7: TS_UI_02
A8: Şəhər seçimi | B8: UI | C8: Çatdırılma şərtlərini müəyyən edir | D8: TS_UI_03
A9: Axtarış | B9: UI | C9: Satışın əsas giriş kanalı | D9: TS_UI_04
A10: Kataloq və kateqoriyalar | B10: UI | C10: Naviqasiyanın əsas yolu | D10: TS_UI_05
A11: Məhsul siyahısı (sıralama, filtr, pagination) | B11: UI | C11: Məhsulun tapılmasına birbaşa təsir edir | D11: TS_UI_06
A12: Məhsul detal səhifəsi (PDP) | B12: UI | C12: Alış qərarının verildiyi səhifə | D12: TS_UI_07
A13: Səbət (Guest və Login) | B13: UI | C13: Pul hesablaması — ən yüksək biznes riski | D13: TS_UI_08, TS_UI_12
A14: Seçilmişlər | B14: UI | C14: Guest vs Login davranış fərqi | D14: TS_UI_09
A15: Giriş/Qeydiyyat (telefon + SMS OTP) | B15: UI | C15: Login axını bütün şəxsi funksiyaların açarıdır | D15: TS_UI_10, TS_UI_11
A16: Checkout-a keçid (sifariş TƏSDİQLƏNMƏDƏN) | B16: UI | C16: Satış hunisinin son mərhələsi | D16: TS_UI_13
... A22: Backend API-lər | B22: API | C22: Kurs tərəfindən təqdim olunan API-lər (API_* sheet-lər) | D22: API_TS_*
A24: OUT OF SCOPE
A25: Modul / Funksionallıq | B25: Səbəb
A26: Real sifarişin təsdiqlənməsi və onlayn ödəniş | B26: Production mühitidir — real sifariş/ödəniş satıcıya və şirkətə zərər verir, real pul tələb edir
A27: Kredit və taksit müraciəti (Birbank) | B27: Real şəxsi və maliyyə məlumatları tələb edir, kredit tarixçəsinə təsir edir
A28: Bir Bonus xərcləmə və promokodun sifarişə tətbiqi | B28: Real bonus balansı, aktiv promokod və real sifariş tələb edir (bonus/promokod səhifələrinə baxış in scope-dadır)
A29: Məhsul rəyi yazmaq | B29: Production-da real kontent yaradır (data pollution), yalnız alınmış məhsula icazə verilir
A30: Satıcı portalı (business.umico.az) | B30: Ayrı sistemdir, korporativ hesab tələb edir
A31: Mobil tətbiqlər (iOS / Android) | B31: Layihə tələbi: yalnız web
A32: Performance / Load testing | B32: Production-a yük vermək qadağandır və etik deyil
A33: Security / Penetration testing | B33: İcazə tələb edir; yalnız əsas XSS sanity yoxlaması daxildir
A34: Üçüncü tərəf səhifələrinin məzmunu (sosial şəbəkələr, bir.az) | B34: Birmarket-in məsuliyyət sahəsi deyil
A36: ENTRY / EXIT KRİTERİYALARI
A37: Entry | B37: Sayt əlçatandır (HTTP 200), test hesabı və telefon hazırdır, test case-lər review olunub
A38: Exit | B38: Bütün P1 test case-lər icra olunub; P1/P2 açıq bug yoxdur; avtomatlaşdırılmış regression ardıcıl 3 run-da 100% stabil keçir

Sheet Test Scenarios
A1: Scenario ID | B1: Ssenari | C1: İstifadəçi növü | D1: Təsvir (nəyi test edirik?) | E1: Priority | F1: TC sayı
A2: TS_UI_01 | B2: Ana səhifə və header | C2: Guest | D2: Header elementləri, üst linklər, logo, sol kateqoriya paneli, banner karuseli, üstünlüklər zolağı, chat | E2: P1 - Critical | F2: =COUNTIF('Test Cases'!$J$2:$J$500,A2) -> 16
A3: TS_UI_02 | B3: Ana səhifə və header | C3: Login | D3: Login vəziyyətinin header-də əks olunması, profil menyusu | E3: P1 - Critical | F3: =COUNTIF('Test Cases'!$J$2:$J$500,A3) -> 2
A4: TS_UI_03 | B4: Dil seçimi (AZ / RU) | C4: Guest | D4: Dil dəyişmə, URL strukturu, naviqasiyada saxlanma, RU axtarış | E4: P2 - High | F4: =COUNTIF('Test Cases'!$J$2:$J$500,A4) -> 4
A5: TS_UI_04 | B5: Dil seçimi (AZ / RU) | C5: Login | D5: Dil dəyişdikdə sessiyanın saxlanması, kabinetin tərcüməsi | E5: P2 - High | F5: =COUNTIF('Test Cases'!$J$2:$J$500,A5) -> 2
A6: TS_UI_05 | B6: Şəhər seçimi | C6: Guest | D6: Şəhər seçimi, saxlanması və çatdırılma məlumatına təsiri | E6: P2 - High | F6: =COUNTIF('Test Cases'!$J$2:$J$500,A6) -> 4
A7: TS_UI_06 | B7: Şəhər seçimi | C7: Login | D7: Şəhərin hesabda saxlanması və checkout-a ötürülməsi | E7: P2 - High | F7: =COUNTIF('Test Cases'!$J$2:$J$500,A7) -> 3
A8: TS_UI_07 | B8: Məhsul axtarışı | C8: Guest | D8: Açar söz, tam ad, Enter, case-insensitive, nəticəsiz/boş/uzun/xüsusi sorğu, autocomplete | E8: P1 - Critical | F8: =COUNTIF('Test Cases'!$J$2:$J$500,A8) -> 12
A9: TS_UI_08 | B9: Məhsul axtarışı | C9: Login | D9: Login istifadəçi üçün nəticələrin guest ilə uyğunluğu | E9: P3 - Medium | F9: =COUNTIF('Test Cases'!$J$2:$J$500,A9) -> 1
A10: TS_UI_09 | B10: Kataloq və kateqoriya naviqasiyası | C10: Guest | D10: Kateqoriya menyusu, kateqoriya/alt kateqoriya səhifəsi, breadcrumb, 404 | E10: P1 - Critical | F10: =COUNTIF('Test Cases'!$J$2:$J$500,A10) -> 7
A11: TS_UI_10 | B11: Məhsul siyahısı: sıralama, filtr, səhifələmə | C11: Guest | D11: 6 sıralama seçimi, qiymət/brend/endirimli/xüsusiyyət filtrləri (EP/BVA/Decision Table), sıfırlama, pagination | E11: P1 - Critical | F11: =COUNTIF('Test Cases'!$J$2:$J$500,A11) -> 29
A12: TS_UI_11 | B12: Məhsul detal səhifəsi (PDP) | C12: Guest | D12: Kart↔PDP uyğunluğu, elementlər, variantlar, stok, satıcı, taksit, rəy, 404 | E12: P1 - Critical | F12: =COUNTIF('Test Cases'!$J$2:$J$500,A12) -> 14
A13: TS_UI_12 | B13: Məhsul detal səhifəsi (PDP) | C13: Login | D13: PDP-dən seçilmişlərə əlavə, rəy yazma hüququ | E13: P2 - High | F13: =COUNTIF('Test Cases'!$J$2:$J$500,A13) -> 2
... A30: TS_UI_29 | B30: Bir Bonus: ID kart və əməliyyat tarixçəsi | C30: Login | D30: Balans, bonus hesablaması, son əməliyyatlar, tarixçə filtrləri (tərəfdaş, dövr BVA, bonus növü) | E30: P2 - High | F30: =COUNTIF('Test Cases'!$J$2:$J$500,A30) -> 9

Sheet Test Cases
A1: Test Case ID | B1: Test Case Title | C1: Module / Feature | D1: Priority | E1: Test Type | F1: Preconditions | G1: Test Steps | H1: Test Data | I1: Expected Result | J1: Scenario ID | K1: Manual/Automation əsaslandırma | L1: Status | M1: Automation | N1: Regression | O1: Actual Result | P1: Execution Date | Q1: İcra növü
A2: TC_HOME_POS_001 | B2: Guest ana səhifəni açdıqda əsas header elementləri göstərilir | C2: Ana səhifə → Header | D2: P1 - Critical | E2: Pozitiv, Smoke | F2: 1. Brauzer: Google Chrome (son stabil versiya), incognito rejim (cookies/cache təmizdir) 2. İstifadəçi login olmayıb (Guest) 3. Dil: AZ, Şəhər: Bakı (default) | G2: 1. Brauzerdə ana səhifə URL-ni aç 2. Səhifənin tam yüklənməsini gözlə 3. Səhifə başlığını (title) yoxla 4. Header elementlərini müşahidə et | H2: URL: https://birmarket.az/ | I2: 1. Səhifə title-ı "BIRMARKET" sözünü ehtiva edir 2. Üst zolaqda görünür: "Çatdırılma və ödəmə", "Qaytarılma", "Zəmanət", "Birmarket-də satın", "915", dil seçicisi "AZ", "Qeydiyyat | Giriş" 3. Əsas header-də görünür: logo, "Şəhər: Bakı", "Məhsul kataloqu", "Məhsul axtar" placeholder-li axtarış sahəsi, "Axtar", "Seçilmişlər", "Səbət" 4. Xəta səhifəsi (404/500) göstərilmir | J2: TS_UI_01 | K2: Smoke testdir — hər deploy-dan sonra ilk yoxlanılan; locator-lar stabil, nəticə dinamik data-dan asılı deyil → avtomatlaşdırılır. | L2: Pass | M2: Automated | N2: Yes | O2: Gözlənilən nəticə ilə üst-üstə düşür. Gauge avtomat run (Chrome 154, guest): PASS. | P2: 06.10.2026 | Q2: Avtomat (Gauge + Selenium)
A3: TC_HOME_POS_002 | B3: Daxili səhifədən logoya klik istifadəçini ana səhifəyə qaytarır | C3: Ana səhifə → Logo naviqasiyası | D3: P3 - Medium | E3: Pozitiv | F3: 1. Brauzer: Google Chrome (son stabil versiya), incognito rejim (cookies/cache təmizdir) 2. İstifadəçi login olmayıb (Guest) 3. Dil: AZ, Şəhər: Bakı (default) 4. Kateqoriya səhifəsi açıqdır: https://birmarket.az/categories/2-telefonlar-ve-aksessuarlar | G3: 1. Header-dəki Birmarket logosuna klik et 2. Açılan səhifənin URL-ni yoxla | H3: Başlanğıc URL: https://birmarket.az/categories/2-telefonlar-ve-aksessuarlar | I3: 1. URL https://birmarket.az/ olur 2. Ana səhifənin banner bölməsi görünür | J3: TS_UI_01 | K3: Naviqasiyanın əsas elementi, deterministik nəticə (URL yoxlaması) → avtomatlaşdırılır. | L3: Pass | M3: Automated | N3: Yes | O3: Gözlənilən nəticə ilə üst-üstə düşür. Gauge avtomat run (Chrome 154, guest): PASS. | P3: 06.10.2026 | Q3: Avtomat (Gauge + Selenium)
A4: TC_HOME_POS_006 | B4: Header-in üst linkləri ("Çatdırılma və ödəmə", "Qaytarılma", "Zəmanət") müvafiq məlumat səhifələrini açır | C4: Ana səhifə → Üst məlumat linkləri | D4: P3 - Medium | E4: Pozitiv | F4: 1. Brauzer: Google Chrome (son stabil versiya), incognito rejim (cookies/cache təmizdir) 2. İstifadəçi login olmayıb (Guest) 3. Dil: AZ, Şəhər: Bakı (default) 4. Ana səhifə açıqdır: https://birmarket.az/ | G4: 1. "Çatdırılma və ödəmə" linkinə klik et, URL-i yoxla 2. Geri qayıt, "Qaytarılma" linkinə klik et, URL-i yoxla 3. Geri qayıt, "Zəmanət" linkinə klik et, URL-i yoxla | H4: Gözlənilən URL-lər: /shipping-payment, /questions-answers?target=cancel-refund, /questions-answers?target=warranty | I4: Hər link gözlənilən URL-i açır və səhifədə müvafiq başlıq/məzmun göstərilir | J4: TS_UI_01 | K4: Aşağı riskli, nadir dəyişən funksionallıq; regression ROI aşağıdır → manual. | L4: Not Run | M4: Manual | N4: No
A5: TC_HOME_POS_009 | B5: Ana səhifədə ikən logoya klik səhifəni yeniləyir və istifadəçini səhifənin yuxarısına qaytarır | C5: Ana səhifə → Logo (ana səhifədə) | D5: P4 - Low | E5: Pozitiv | F5: 1. Brauzer: Google Chrome (son stabil versiya), incognito rejim (cookies/cache təmizdir) 2. İstifadəçi login olmayıb (Guest) 3. Dil: AZ, Şəhər: Bakı (default) 4. Ana səhifə açıqdır: https://birmarket.az/ | G5: 1. Səhifəni aşağıya scroll et 2. Header-dəki Birmarket logosuna klik et 3. URL-i və səhifənin mövqeyini yoxla | H5: — | I5: 1. URL https://birmarket.az/ qalır 2. Səhifə yenidən yüklənir və ən yuxarı hissə (banner) göstərilir 3. Xəta yoxdur | J5: TS_UI_01 | K5: Vizual/scroll mövqeyi yoxlamasıdır, biznes riski aşağıdır → manual. | L5: Not Run | M5: Manual | N5: No
A6: TC_HOME_POS_010 | B6: "Bütün kateqoriyalar" sol paneldəki siyahını yerində genişləndirir | C6: Ana səhifə → Sol kateqoriya paneli | D6: P2 - High | E6: Pozitiv | F6: 1. Brauzer: Google Chrome (son stabil versiya), incognito rejim (cookies/cache təmizdir) 2. İstifadəçi login olmayıb (Guest) 3. Dil: AZ, Şəhər: Bakı (default) 4. Ana səhifə açıqdır: https://birmarket.az/ | G6: 1. Sol paneldəki görünən kateqoriyaları oxu 2. "Bütün kateqoriyalar"-a klik et 3. URL-i və paneli yoxla 4. Paneli aşağı scroll et | H6: — | I6: 1. URL dəyişmir (ayrı səhifəyə keçid olmur) 2. Panel yerində genişlənir, səhifənin qalan hissəsi tündləşir (overlay) 3. Panel scroll olunur və əvvəl görünməyən kateqoriyalar ("Məişət kimyası", "İdman və Əyləncə" və s.) göstərilir | J6: TS_UI_01 | K6: Davranış təsdiqlənib; login tələb etmir, deterministikdir → avtomatlaşdırılır. | Avtomatlaşdırma cəhdindən sonra Manual-a keçirildi: Kataloq paneli overlay/hover ilə açılır, stabil locator yoxdur. | L6: Pass | M6: Manual | N6: Yes (Manual) | O6: Siyahı yerində genişlənir, URL dəyişmir, overlay açılır (GQ_UI_25). PASS. | P6: 06.10.2026 | Q6: Manual (saytda yoxlanılıb)
A7: TC_HOME_POS_011 | B7: Sol paneldə kateqoriyaya klik müvafiq kateqoriya səhifəsini açır | C7: Ana səhifə → Sol kateqoriya paneli | D7: P2 - High | E7: Pozitiv | F7: 1. Brauzer: Google Chrome (son stabil versiya), incognito rejim (cookies/cache təmizdir) 2. İstifadəçi login olmayıb (Guest) 3. Dil: AZ, Şəhər: Bakı (default) 4. Ana səhifə açıqdır: https://birmarket.az/ | G7: 1. Sol paneldə "Məişət texnikası"-na klik et 2. URL-i və H1-i yoxla | H7: Kateqoriya: Məişət texnikası | I7: 1. URL "/categories/106-meishet-texnikasi" ehtiva edir 2. H1 = "Məişət texnikası" 3. Ən azı 1 məhsul kartı göstərilir | J7: TS_UI_01 | K7: Regression-a daxildir, hər release-də təkrarlanır; nəticə data-dan asılı olmayan invariantla yoxlanır (hardcode qiymət/ad yoxdur); xarici asılılıq yoxdur → avtomatlaşdırılır. | Avtomatlaşdırma cəhdindən sonra Manual-a keçirildi: Kataloq paneli overlay/hover ilə açılır, stabil locator yoxdur. | L7: Not Run | M7: Manual | N7: Yes (Manual)
A8: TC_HOME_POS_012 | B8: Sol paneldəki "Mega endirimlər" linki endirimlər səhifəsini açır | C8: Ana səhifə → Kampaniya linkləri | D8: P3 - Medium | E8: Pozitiv | F8: 1. Brauzer: Google Chrome (son stabil versiya), incognito rejim (cookies/cache təmizdir) 2. İstifadəçi login olmayıb (Guest) 3. Dil: AZ, Şəhər: Bakı (default) 4. Ana səhifə açıqdır: https://birmarket.az/ | G8: 1. Sol paneldə "Mega endirimlər"-ə klik et 2. URL-i və məhsulları yoxla | H8: — | I8: 1. URL "/mega-discounts" ehtiva edir 2. Göstərilən məhsul kartlarında endirim nişanı var | J8: TS_UI_01 | K8: Kampaniya məzmunu marketinq tərəfindən tez-tez dəyişir → manual. | L8: Not Run | M8: Manual | N8: No
A9: TC_HOME_POS_013 | B9: Üstünlüklər zolağında 4 məlumat bloku göstərilir və pulsuz çatdırılma həddi 50 ₼-dir | C9: Ana səhifə → Üstünlüklər zolağı | D9: P3 - Medium | E9: Pozitiv | F9: 1. Brauzer: Google Chrome (son stabil versiya), incognito rejim (cookies/cache təmizdir) 2. İstifadəçi login olmayıb (Guest) 3. Dil: AZ, Şəhər: Bakı (default) 4. Ana səhifə açıqdır: https://birmarket.az/ | G9: 1. Bannerin altındakı zolağı oxu | H9: — | I9: Bloklar: "500 000-dən çox məhsul", "50 ₼-dən başlayan sifarişlərə pulsuz çatdırılma", "Endirimlər və aksiyalar", "Birbank ilə 24 ayadək taksit" (checkout-dakı çatdırılma həddi ilə uyğun olmalıdır — TC_CHK_BVA_003/004) | J9: TS_UI_01 | K9: Marketinq mətni dəyişə bilər; dəyər checkout BVA testləri ilə çarpaz yoxlanılır → manual. | L9: Not Run | M9: Manual | N9: No
A10: TC_HOME_POS_014 | B10: "Birmarket-də satın" linki satıcı portalının (Business By Birmarket) ana səhifəsini açır | C10: Ana səhifə → Satıcı linki | D10: P3 - Medium | E10: Pozitiv | F10: 1. Brauzer: Google Chrome (son stabil versiya), incognito rejim (cookies/cache təmizdir) 2. İstifadəçi login olmayıb (Guest) 3. Dil: AZ, Şəhər: Bakı (default) 4. Ana səhifə açıqdır: https://birmarket.az/ | G10: 1. Üst zolaqda "Birmarket-də satın"-a klik et 2. Açılan səhifəni yoxla | H10: — | I10: 1. URL "https://business.umico.az" ilə başlayır 2. "Business By Birmarket" loqosu və "Onlayn mağazanızı yaradın və Bakıdan bütün Azərbaycana satış edin" başlığı göstərilir 3. "Satıcı olmaq", "Daxil ol", "Qeydiyyat" düymələri görünür | J10: TS_UI_01 | K10: Xarici/ayrı sistemə keçid (satıcı portalı scope-dan kənardır), yalnız keçid yoxlanılır → manual. | L10: Pass | M10: Manual | N10: No | O10: "Birmarket-də satın" → business.umico.az açılır (GQ_UI_26). PASS. | P10: 06.10.2026 | Q10: Manual (saytda yoxlanılıb)
A11: TC_HOME_POS_015 | B11: "915" seçicisi çağrı mərkəzinin iş saatlarını göstərir, nömrəyə klik zəng tətbiqini çağırır | C11: Ana səhifə → Qaynar xətt | D11: P4 - Low | E11: Pozitiv | F11: 1. Brauzer: Google Chrome (son stabil versiya), incognito rejim (cookies/cache təmizdir) 2. İstifadəçi login olmayıb (Guest) 3. Dil: AZ, Şəhər: Bakı (default) 4. Ana səhifə açıqdır: https://birmarket.az/ | G11: 1. Üst zolaqda "915" yanındakı oxa klik et 2. Açılan bloku oxu 3. "915" nömrəsinə klik et | H11: — | I11: 1. Blokda "Çağrı mərkəzinin iş saatları" — "Hər gün: 09:00 – 00:00" göstərilir 2. Nömrəyə klik brauzerin zəng tətbiqini açma dialoqunu çağırır (tel: link) | J11: TS_UI_01 | K11: Aşağı riskli, nadir dəyişən funksionallıq; regression ROI aşağıdır → manual. | L11: Pass | M11: Manual | N11: No | O11: "915" blokunda "Hər gün: 09:00 – 00:00" göstərilir, nömrə tel: linkdir (GQ_UI_26). PASS. | P11: 06.10.2026 | Q11: Manual (saytda yoxlanılıb)
A12: TC_HOME_POS_016 | B12: Canlı dəstək (chat) düyməsi söhbət pəncərəsini açır | C12: Ana səhifə → Chat widget | D12: P3 - Medium | E12: Pozitiv | F12: 1. Brauzer: Google Chrome (son stabil versiya), incognito rejim (cookies/cache təmizdir) 2. İstifadəçi login olmayıb (Guest) 3. Dil: AZ, Şəhər: Bakı (default) 4. Ana səhifə açıqdır: https://birmarket.az/ | G12: 1. Sağ aşağı küncdəki chat düyməsinə klik et 2. Açılan pəncərəni müşahidə et 3. Pəncərəni bağla | H12: — | I12: 1. Söhbət pəncərəsi açılır 2. Bağlandıqdan sonra düymə yenidən görünür (Mesaj GÖNDƏRİLMİR — real operator yükü yaratmamaq üçün) | J12: TS_UI_01 | K12: Üçüncü tərəf widget-i, iframe və async yükləmə → avtomatlaşdırma qeyri-stabil; real dəstək xidmətinə təsir riski → manual. | L12: Not Run | M12: Manual | N12: No
A13: TC_HOME_POS_017 | B13: "Günün endirimi" blokundakı kampaniya taymeri geri sayır | C13: Ana səhifə → Günün endirimi | D13: P3 - Medium | E13: Pozitiv | F13: 1. Brauzer: Google Chrome (son stabil versiya), incognito rejim (cookies/cache təmizdir) 2. İstifadəçi login olmayıb (Guest) 3. Dil: AZ, Şəhər: Bakı (default) 4. Ana səhifə açıqdır: https://birmarket.az/ | G13: 1. "Günün endirimi" bölməsinə scroll et 2. "Kampaniyanın bitmə müddəti" dəyərini oxu 3. 5 saniyə gözlə və dəyəri yenidən oxu | H13: — | I13: 1. Taymer SS:DD:SS formatındadır 2. 5 saniyə sonra dəyər ~5 saniyə azalır 3. Blokda endirimli məhsul kartları göstərilir | J13: TS_UI_01 | K13: Kampaniya hər gün aktiv olmaya bilər və vaxta bağlıdır → avtomatlaşdırma flaky olar → manual. | L13: Not Run | M13: Manual | N13: No
A14: TC_HOME_POS_018 | B14: Brauzer bildirişləri təklifində "Ləğv et" seçildikdə təklif bağlanır və dərhal təkrar göstərilmir | C14: Ana səhifə → Bildiriş icazəsi təklifi | D14: P3 - Medium | E14: Pozitiv, State Transition | F14: 1. Brauzer: Google Chrome (son stabil versiya), incognito rejim (cookies/cache təmizdir) 2. İstifadəçi login olmayıb (Guest) 3. Dil: AZ, Şəhər: Bakı (default) 4. "Brauzerinizdə bildirişlər almaq istəyirsinizmi?" təklifi göstərilir | G14: 1. Təklifdə "Ləğv et"-ə klik et 2. Səhifəni yenilə (F5) 3. Başqa səhifəyə keç | H14: — | I14: 1. Təklif bağlanır 2. Yeniləmədən və naviqasiyadan sonra təklif təkrar göstərilmir (təkrar göstərilmə müddəti — GQ_UI_35) | J14: TS_UI_01 | K14: Brauzer icazə vəziyyəti və cookie-dən asılıdır; native dialoqla əlaqə avtomatlaşdırmada idarə olunmur → manual. | L14: Not Run | M14: Manual | N14: No
A15: TC_HOME_POS_019 | B15: Bildiriş təklifində "İcazə ver" brauzerin öz icazə dialoqunu çağırır | C15: Ana səhifə → Bildiriş icazəsi təklifi | D15: P4 - Low | E15: Pozitiv | F15: 1. Brauzer: Google Chrome (son stabil versiya), incognito rejim (cookies/cache təmizdir) 2. İstifadəçi login olmayıb (Guest) 3. Dil: AZ, Şəhər: Bakı (default) 4. Bildiriş təklifi göstərilir | G15: 1. "İcazə ver"-ə klik et 2. Ekranı müşahidə et | H15: — | I15: Brauzerin native "Bildirişləri göstər — İcazə ver / Blokla" dialoqu açılır; saytın təklifi bağlanır | J15: TS_UI_01 | K15: Native brauzer dialoqu WebDriver ilə etibarlı idarə olunmur → manual. | L15: Not Run | M15: Manual | N15: No
A16: TC_HOME_UI_003 | B16: Ana səhifə banner karuseli dəyişir və banner klikləndikdə aksiya səhifəsi açılır | C16: Ana səhifə → Banner karusel | D16: P3 - Medium | E16: UI | F16: 1. Brauzer: Google Chrome (son stabil versiya), incognito rejim (cookies/cache təmizdir) 2. İstifadəçi login olmayıb (Guest) 3. Dil: AZ, Şəhər: Bakı (default) 4. Ana səhifə açıqdır: https://birmarket.az/ | G16: 1. Banner karuselini 10 saniyə müşahidə et 2. Karuselin sağ oxuna klik et 3. Aktiv bannerə klik et | H16: — | I16: 1. Bannerlər avtomatik növbə ilə dəyişir, aktiv banner nöqtə göstəricisində (7 nöqtə) qeyd olunur 2. Ox kliki ilə növbəti banner göstərilir 3. Banner kliki URL-i "/flash_sale/" olan aksiya səhifəsini açır, səhifədə məhsul kartları var | J16: TS_UI_01 | K16: Vizual/UX yoxlama insan qiyməti tələb edir, məzmun marketinq tərəfindən tez-tez dəyişir → avtomatlaşdırma flaky olar, ROI aşağıdır. | L16: Not Run | M16: Manual | N16: No
A17: TC_HOME_UI_007 | B17: Səhifə aşağı scroll edildikdə header (axtarış və səbət) görünən qalır | C17: Ana səhifə → Sticky header | D17: P4 - Low | E17: UI | F17: 1. Brauzer: Google Chrome (son stabil versiya), incognito rejim (cookies/cache təmizdir) 2. İstifadəçi login olmayıb (Guest) 3. Dil: AZ, Şəhər: Bakı (default) 4. Ana səhifə açıqdır: https://birmarket.az/ | G17: 1. Səhifəni ən aşağıya qədər scroll et 2. Ekranın yuxarı hissəsini müşahidə et | H17: — | I17: Axtarış sahəsi və səbət ikonu ekranın yuxarısında görünən qalır | J17: TS_UI_01 | K17: Vizual/UX yoxlama insan qiyməti tələb edir, məzmun marketinq tərəfindən tez-tez dəyişir → avtomatlaşdırma flaky olar, ROI aşağıdır. | L17: Not Run | M17: Manual | N17: No
A18: TC_HOME_POS_004 | B18: [Login] Login olmuş istifadəçinin header-ində "Şəxsi hesabım" göstərilir, "Qeydiyyat | Giriş" göstərilmir | C18: Ana səhifə (Login) → Header | D18: P1 - Critical | E18: Pozitiv | F18: 1. Brauzer: Google Chrome (son stabil versiya) 2. Test hesabı Birmarket-də qeydiyyatdadır, telefon nömrəsi SMS qəbul edir (test icraçısının əlindədir) 3. İstifadəçi həmin hesabla login olub (header-də "Şəxsi hesabım" görünür) 4. Ana səhifə açıqdır: https://birmarket.az/ | G18: 1. Header-i müşahidə et 2. Səhifəni yenilə (F5) 3. Header-i yenidən müşahidə et | H18: — | I18: 1. Üst zolaqda "Şəxsi hesabım" göstərilir 2. "Qeydiyyat | Giriş" linki göstərilmir 3. Yeniləmədən sonra login vəziyyəti saxlanılır | J18: TS_UI_02 | K18: SMS OTP real telefon tələb edir, prod-da OTP bypass yoxdur, SMS limitləri var → stabil avtomatlaşdırmaq mümkün deyil. Biznes kritik olduğu üçün manual regression-a daxildir. | L18: Pass | M18: Manual | N18: Yes (Manual) | O18: Login vəziyyətində header-də "Şəxsi hesabım" göstərilir, "Qeydiyyat | Giriş" yoxdur; F5-dən sonra login vəziyyəti saxlanılır. PASS. | P18: 07.10.2026 | Q18: Manual (saytda yoxlanılıb)
A19: TC_HOME_POS_005 | B19: [Login] "Şəxsi hesabım"-a klik edildikdə bütün kabinet bölmələri olan menyu açılır | C19: Ana səhifə (Login) → Profil menyusu | D19: P2 - High | E19: Pozitiv | F19: 1. Brauzer: Google Chrome (son stabil versiya) 2. Test hesabı Birmarket-də qeydiyyatdadır, telefon nömrəsi SMS qəbul edir (test icraçısının əlindədir) 3. İstifadəçi həmin hesabla login olub (header-də "Şəxsi hesabım" görünür) 4. Ana səhifə açıqdır: https://birmarket.az/ | G19: 1. Header-dəki "Şəxsi hesabım"-a klik et 2. Açılan menyunun bəndlərini oxu | H19: Gözlənilən bəndlər: Hesab, Bildirişlər, Mənim sifarişlərim, Mesaj, Promokodlar, Kredit müraciətləri, Seçilmişlər, Mənim rəylərim, Mənim ünvanlarım, Mənim ID kartım, Əməliyyat tarixçəsi, Çıxış | I19: 1. Menyu açılır, "birmarket" və "bir bonus" bölmələri ayrıca göstərilir 2. Menyuda dəqiq bu bəndlər var: Hesab, Bildirişlər, Mənim sifarişlərim, Mesaj, Promokodlar, Kredit müraciətləri, Seçilmişlər, Mənim rəylərim, Mənim ünvanlarım, Mənim ID kartım, Əməliyyat tarixçəsi, Çıxış 3. Oxunmamış bildiriş varsa "Bildirişlər" yanında say nişanı göstərilir | J19: TS_UI_02 | K19: SMS OTP real telefon tələb edir, prod-da OTP bypass yoxdur, SMS limitləri var → stabil avtomatlaşdırmaq mümkün deyil. Biznes kritik olduğu üçün manual regression-a daxildir. | L19: Not Run | M19: Manual | N19: Yes (Manual)
A20: TC_LANG_POS_001 | B20: Dil AZ-dan RU-ya dəyişdirildikdə URL /ru prefiksi alır və interfeys rus dilində göstərilir | C20: Dil seçimi → AZ→RU | D20: P2 - High | E20: Pozitiv | F20: 1. Brauzer: Google Chrome (son stabil versiya), incognito rejim (cookies/cache təmizdir) 2. İstifadəçi login olmayıb (Guest) 3. Dil: AZ, Şəhər: Bakı (default) 4. Ana səhifə açıqdır: https://birmarket.az/ | G20: 1. Header-dəki dil seçicisinə (AZ) klik et 2. "Русский" seçimini et 3. URL-i yoxla 4. Header mətnlərini yoxla | H20: Dil: Русский | I20: 1. URL "https://birmarket.az/ru" ilə başlayır 2. Dil seçicisi "RU" göstərir 3. Header mətnləri rus dilindədir (məs. "Qeydiyyat | Giriş" əvəzinə rusca qarşılığı) | J20: TS_UI_03 | K20: Regression-a daxildir, hər release-də təkrarlanır; nəticə data-dan asılı olmayan invariantla yoxlanır (hardcode qiymət/ad yoxdur); xarici asılılıq yoxdur → avtomatlaşdırılır. | L20: Pass | M20: Automated | N20: Yes | O20: Gözlənilən nəticə ilə üst-üstə düşür. Gauge avtomat run (Chrome 154, guest): PASS. | P20: 06.10.2026 | Q20: Avtomat (Gauge + Selenium)
A21: TC_LANG_POS_002 | B21: Dil RU-dan AZ-a qaytarıldıqda URL-dən /ru prefiksi silinir və interfeys AZ dilində göstərilir | C21: Dil seçimi → RU→AZ | D21: P2 - High | E21: Pozitiv | F21: 1. Brauzer: Google Chrome (son stabil versiya), incognito rejim (cookies/cache təmizdir) 2. İstifadəçi login olmayıb (Guest) 3. Dil: AZ, Şəhər: Bakı (default) 4. Ana səhifə RU dilində açıqdır: https://birmarket.az/ru | G21: 1. Dil seçicisinə (RU) klik et 2. "Azərbaycan" seçimini et 3. URL-i yoxla 4. Header mətnlərini yoxla | H21: Dil: Azərbaycan | I21: 1. URL-də "/ru" prefiksi yoxdur 2. Dil seçicisi "AZ" göstərir 3. Header-də "Qeydiyyat | Giriş" mətni görünür | J21: TS_UI_03 | K21: Regression-a daxildir, hər release-də təkrarlanır; nəticə data-dan asılı olmayan invariantla yoxlanır (hardcode qiymət/ad yoxdur); xarici asılılıq yoxdur → avtomatlaşdırılır. | L21: Pass | M21: Automated | N21: Yes | O21: Gözlənilən nəticə ilə üst-üstə düşür. Gauge avtomat run (Chrome 154, guest): PASS. | P21: 06.10.2026 | Q21: Avtomat (Gauge + Selenium)
A22: TC_LANG_POS_003 | B22: RU dili seçildikdən sonra kateqoriyaya keçid zamanı dil saxlanılır | C22: Dil seçimi → Naviqasiyada saxlanma | D22: P2 - High | E22: Pozitiv | F22: 1. Brauzer: Google Chrome (son stabil versiya), incognito rejim (cookies/cache təmizdir) 2. İstifadəçi login olmayıb (Guest) 3. Dil: AZ, Şəhər: Bakı (default) 4. Ana səhifə RU dilində açıqdır: https://birmarket.az/ru | G22: 1. Kataloq menyusunu aç 2. 1-ci kateqoriyaya klik et 3. URL-i və H1 başlığını yoxla | H22: — | I22: 1. URL "https://birmarket.az/ru/categories/" ilə başlayır 2. H1 başlığı rus dilindədir (kiril əlifbası) | J22: TS_UI_03 | K22: Regression-a daxildir, hər release-də təkrarlanır; nəticə data-dan asılı olmayan invariantla yoxlanır (hardcode qiymət/ad yoxdur); xarici asılılıq yoxdur → avtomatlaşdırılır. | Avtomatlaşdırma cəhdindən sonra Manual-a keçirildi: Kateqoriya keçidi overlay menyudan asılıdır. | L22: Not Run | M22: Manual | N22: Yes (Manual)
A23: TC_LANG_POS_004 | B23: RU interfeysində kiril əlifbası ilə axtarış nəticə qaytarır | C23: Dil seçimi → RU axtarış | D23: P2 - High | E23: Pozitiv | F23: 1. Brauzer: Google Chrome (son stabil versiya), incognito rejim (cookies/cache təmizdir) 2. İstifadəçi login olmayıb (Guest) 3. Dil: AZ, Şəhər: Bakı (default) 4. Ana səhifə RU dilində açıqdır: https://birmarket.az/ru | G23: 1. Axtarış sahəsinə açar sözü daxil et 2. Axtarışı icra et 3. Nəticələri yoxla | H23: Açar söz: телефон | I23: 1. Ən azı 1 məhsul kartı göstərilir 2. URL "/ru" prefiksini saxlayır | J23: TS_UI_03 | K23: Regression-a daxildir, hər release-də təkrarlanır; nəticə data-dan asılı olmayan invariantla yoxlanır (hardcode qiymət/ad yoxdur); xarici asılılıq yoxdur → avtomatlaşdırılır. | L23: Pass | M23: Automated | N23: Yes | O23: RU interfeysində "телефон" axtarışı nəticə qaytardı. PASS. | P23: 06.10.2026 | Q23: Avtomat (Gauge + Selenium)
A24: TC_LANG_POS_005 | B24: [Login] Login istifadəçi dili RU-ya dəyişdikdə sessiya saxlanılır | C24: Dil seçimi (Login) → Sessiya | D24: P2 - High | E24: Pozitiv, State Transition | F24: 1. Brauzer: Google Chrome (son stabil versiya) 2. Test hesabı Birmarket-də qeydiyyatdadır, telefon nömrəsi SMS qəbul edir (test icraçısının əlindədir) 3. İstifadəçi həmin hesabla login olub (header-də "Şəxsi hesabım" görünür) 4. Ana səhifə açıqdır: https://birmarket.az/ | G24: 1. Dil seçicisindən "Русский" seç 2. Header-i yoxla 3. Səbət ikonundakı sayğacı yoxla | H24: Dil: Русский | I24: 1. İstifadəçi login qalır ("Şəxsi hesabım" görünür) 2. Səbət sayğacı dil dəyişməzdən əvvəlki ilə eynidir | J24: TS_UI_04 | K24: SMS OTP real telefon tələb edir, prod-da OTP bypass yoxdur, SMS limitləri var → stabil avtomatlaşdırmaq mümkün deyil. Biznes kritik olduğu üçün manual regression-a daxildir. | L24: Not Run | M24: Manual | N24: Yes (Manual)
A25: TC_LANG_POS_006 | B25: [Login] Şəxsi kabinet səhifələri RU dilində tam tərcümə olunmuş göstərilir | C25: Dil seçimi (Login) → Kabinet tərcüməsi | D25: P3 - Medium | E25: UI | F25: 1. Brauzer: Google Chrome (son stabil versiya) 2. Test hesabı Birmarket-də qeydiyyatdadır, telefon nömrəsi SMS qəbul edir (test icraçısının əlindədir) 3. İstifadəçi həmin hesabla login olub (header-də "Şəxsi hesabım" görünür) 4. Dil: Русский | G25: 1. "Şəxsi hesabım" menyusunu aç 2. Şəxsi kabinetə keç 3. "Mənim sifarişlərim" bölməsinə keç 4. Hər səhifədə mətnləri yoxla | H25: — | I25: Kabinet səhifələrində AZ dilində qalmış (tərcümə olunmamış) mətn yoxdur | J25: TS_UI_04 | K25: OTP ilə login tələb edir (prod-da bypass yoxdur) → avtomatlaşdırıla bilmir. Biznes riski orta/aşağı olduğu üçün regression-a daxil edilmir. | L25: Not Run | M25: Manual | N25: No
A26: TC_CITY_NEG_007 | B26: Şəhər pəncərəsi seçim etmədən "X" ilə bağlandıqda şəhər dəyişmir | C26: Şəhər seçimi → Pəncərənin bağlanması | D26: P3 - Medium | E26: Neqativ, State Transition | F26: 1. Brauzer: Google Chrome (son stabil versiya), incognito rejim (cookies/cache təmizdir) 2. İstifadəçi login olmayıb (Guest) 3. Dil: AZ, Şəhər: Bakı (default) 4. Ana səhifə açıqdır: https://birmarket.az/ | G26: 1. Header-dəki "Şəhər: Bakı"-ya klik et 2. Pəncərədə heç bir şəhər seçmə 3. Sağ yuxarıdakı "X"-ə klik et 4. Header-i yoxla | H26: — | I26: 1. Pəncərə bağlanır 2. Header-də "Şəhər: Bakı" qalır | J26: TS_UI_05 | K26: Regression-a daxildir, hər release-də təkrarlanır; nəticə data-dan asılı olmayan invariantla yoxlanır (hardcode qiymət/ad yoxdur); xarici asılılıq yoxdur → avtomatlaşdırılır. | L26: Pass | M26: Automated | N26: Yes | O26: Pəncərə X ilə bağlandı, header-də "Şəhər: Bakı" dəyişmədi. PASS. | P26: 06.10.2026 | Q26: Avtomat (Gauge + Selenium)
A27: TC_CITY_POS_001 | B27: Şəhər siyahısından "Gəncə" seçildikdə header-də seçilmiş şəhər göstərilir | C27: Şəhər seçimi → Şəhər dəyişmə | D27: P2 - High | E27: Pozitiv | F27: 1. Brauzer: Google Chrome (son stabil versiya), incognito rejim (cookies/cache təmizdir) 2. İstifadəçi login olmayıb (Guest) 3. Dil: AZ, Şəhər: Bakı (default) 4. Ana səhifə açıqdır: https://birmarket.az/ | G27: 1. Header-dəki "Şəhər: Bakı" elementinə klik et 2. Açılan "Şəhərinizi seçin" siyahısından şəhəri seç 3. Header-dəki şəhər mətnini yoxla | H27: Şəhər: Gəncə | I27: 1. Şəhər siyahısı bağlanır 2. Header-də "Şəhər: Gəncə" göstərilir | J27: TS_UI_05 | K27: Şəhər seçimi çatdırılma şərtlərinə təsir edir; deterministik nəticə, stabil locator → avtomatlaşdırılır. | L27: Pass | M27: Automated | N27: Yes | O27: Gözlənilən nəticə ilə üst-üstə düşür. Gauge avtomat run (Chrome 154, guest): PASS. | P27: 06.10.2026 | Q27: Avtomat (Gauge + Selenium)
A28: TC_CITY_POS_002 | B28: Seçilmiş şəhər səhifə yeniləndikdən sonra saxlanılır | C28: Şəhər seçimi → Persistence | D28: P2 - High | E28: Pozitiv | F28: 1. Brauzer: Google Chrome (son stabil versiya), incognito rejim (cookies/cache təmizdir) 2. İstifadəçi login olmayıb (Guest) 3. Dil: AZ, Şəhər: Bakı (default) 4. Ana səhifə açıqdır: https://birmarket.az/ | G28: 1. Header-dəki şəhər elementinə klik et 2. Şəhəri seç 3. Səhifəni yenilə (F5) 4. Header-dəki şəhər mətnini yoxla | H28: Şəhər: Sumqayıt | I28: Səhifə yeniləndikdən sonra header-də "Şəhər: Sumqayıt" göstərilir (default "Bakı"-ya qayıtmır) | J28: TS_UI_05 | K28: State persistence bug-ları regression-da tez-tez qayıdır; deterministikdir → avtomatlaşdırılır. | L28: Pass | M28: Automated | N28: Yes | O28: Gözlənilən nəticə ilə üst-üstə düşür. Gauge avtomat run (Chrome 154, guest): PASS. | P28: 06.10.2026 | Q28: Avtomat (Gauge + Selenium)
A29: TC_CITY_POS_003 | B29: Şəhər dəyişdirildikdə PDP-dəki çatdırılma məlumatı yenilənir | C29: Şəhər seçimi → Çatdırılma məlumatı | D29: P2 - High | E29: Pozitiv | F29: 1. Brauzer: Google Chrome (son stabil versiya), incognito rejim (cookies/cache təmizdir) 2. İstifadəçi login olmayıb (Guest) 3. Dil: AZ, Şəhər: Bakı (default) 4. Kateqoriya səhifəsi açıqdır: https://birmarket.az/categories/2-telefonlar-ve-aksessuarlar 5. Məhsul seçim qaydası: kateqoriyada stokda olan ilk məhsul kartı (qiymət/ad hardcode edilmir) — PDP açıqdır | G29: 1. PDP-dəki çatdırılma tarixini/məlumatını qeyd et 2. Header-dən şəhəri dəyiş 3. PDP-dəki çatdırılma məlumatını yenidən oxu | H29: Şəhər: Bakı → Naxçıvan | I29: Çatdırılma məlumatı seçilmiş şəhərə uyğun yenilənir (Bakı üçün göstərilən məlumatla eyni qalmır və ya çatdırılma mümkün olmadığı bildirilir) | J29: TS_UI_05 | K29: Nəticə prod-da dinamik dəyişən data-dan (stok, sifariş tarixçəsi, məhsul sayı) asılıdır → avtomatlaşdırma flaky olar → manual. | L29: Not Run | M29: Manual | N29: No
A30: TC_CITY_POS_004 | B30: [Login] Login istifadəçinin seçdiyi şəhər logout və təkrar login-dən sonra saxlanılır | C30: Şəhər seçimi (Login) → Hesabda saxlanma | D30: P3 - Medium | E30: Pozitiv, State Transition | F30: 1. Brauzer: Google Chrome (son stabil versiya) 2. Test hesabı Birmarket-də qeydiyyatdadır, telefon nömrəsi SMS qəbul edir (test icraçısının əlindədir) 3. İstifadəçi həmin hesabla login olub (header-də "Şəxsi hesabım" görünür) 4. Ana səhifə açıqdır: https://birmarket.az/ | G30: 1. Şəhəri dəyiş 2. Logout et 3. Təkrar OTP ilə login ol 4. Header-dəki şəhəri yoxla | H30: Şəhər: Gəncə | I30: Header-də "Şəhər: Gəncə" göstərilir (GQ_UI_13) | J30: TS_UI_06 | K30: OTP ilə login tələb edir (prod-da bypass yoxdur) → avtomatlaşdırıla bilmir. Biznes riski orta/aşağı olduğu üçün regression-a daxil edilmir. | L30: Not Run | M30: Manual | N30: No
A31: TC_CITY_POS_005 | B31: [Login] Checkout-da çatdırılma şəhəri header-də seçilmiş şəhərlə uyğun gəlir | C31: Şəhər seçimi (Login) → Checkout | D31: P2 - High | E31: Pozitiv | F31: 1. Brauzer: Google Chrome (son stabil versiya) 2. Test hesabı Birmarket-də qeydiyyatdadır, telefon nömrəsi SMS qəbul edir (test icraçısının əlindədir) 3. İstifadəçi həmin hesabla login olub (header-də "Şəxsi hesabım" görünür) 4. Header-də şəhər: Sumqayıt 5. Səbətdə 1 məhsul var | G31: 1. Səbətə keç 2. "Sifarişi rəsmiləşdir"-ə klik et 3. Çatdırılma bölməsində şəhəri yoxla 4. Sifarişi TƏSDİQLƏMƏ | H31: Şəhər: Sumqayıt | I31: Checkout-da çatdırılma şəhəri "Sumqayıt" kimi göstərilir və ya ilkin seçilmiş olur | J31: TS_UI_06 | K31: OTP ilə login tələb edir (prod-da bypass yoxdur) → avtomatlaşdırıla bilmir. Biznes riski orta/aşağı olduğu üçün regression-a daxil edilmir. | L31: Not Run | M31: Manual | N31: No
A32: TC_CITY_POS_006 | B32: [Login→Logout] Logout-dan sonra "Şəhərinizi seçin" pəncərəsi avtomatik açılır | C32: Şəhər seçimi (Login→Logout) → Avtomatik pəncərə | D32: P3 - Medium | E32: Pozitiv, State Transition | F32: 1. Brauzer: Google Chrome (son stabil versiya) 2. Test hesabı Birmarket-də qeydiyyatdadır, telefon nömrəsi SMS qəbul edir (test icraçısının əlindədir) 3. İstifadəçi həmin hesabla login olub (header-də profil ikonu görünür) 4. Header-də şəhər: Bakı | G32: 1. "Şəxsi hesabım" → "Çıxış"-a klik et 2. Açılan ekranı müşahidə et 3. Pəncərədə seçilmiş şəhəri yoxla | H32: — | I32: 1. "Şəhərinizi seçin" pəncərəsi avtomatik açılır 2. "Bakı" ✓ işarəsi ilə seçili göstərilir 3. Siyahıda bütün şəhərlər əlifba sırası ilə sütunlarda göstərilir (GQ_UI_13) | J32: TS_UI_06 | K32: OTP ilə login tələb edir (prod-da bypass yoxdur) → avtomatlaşdırıla bilmir. Biznes riski orta/aşağı olduğu üçün regression-a daxil edilmir. | L32: Not Run | M32: Manual | N32: No
A33: TC_SRCH_EDGE_005 | B33: Axtarışa HTML/JS kodu daxil edildikdə kod icra olunmur və mətn kimi işlənir | C33: Axtarış → Xüsusi simvollar | D33: P2 - High | E33: Neqativ, Edge | F33: 1. Brauzer: Google Chrome (son stabil versiya), incognito rejim (cookies/cache təmizdir) 2. İstifadəçi login olmayıb (Guest) 3. Dil: AZ, Şəhər: Bakı (default) 4. Ana səhifə açıqdır: https://birmarket.az/ | G33: 1. Axtarış sahəsinə test datanı daxil et 2. "Axtar" düyməsinə klik et 3. Səhifəni müşahidə et | H33: Açar söz: <script>alert(1)</script> | I33: 1. Brauzerdə alert pəncərəsi açılmır 2. Səhifədə düz mətn kimi göstərilir: Sorğuya uyğun məhsul tapılmadı "<script>alert(1)</script>" 3. Səhifə 500 xətası vermir | J33: TS_UI_07 | K33: Bir dəfəlik təhlükəsizlik sanity yoxlamasıdır; tam security testi scope-dan kənardır, funksional regression-a aid deyil → manual. | L33: Not Run | M33: Manual | N33: No
A34: TC_SRCH_EDGE_007 | B34: Çox uzun (256 simvol) sorğu ilə axtarış sistemi çökdürmür | C34: Axtarış → Uzun sorğu | D34: P3 - Medium | E34: Edge | F34: 1. Brauzer: Google Chrome (son stabil versiya), incognito rejim (cookies/cache təmizdir) 2. İstifadəçi login olmayıb (Guest) 3. Dil: AZ, Şəhər: Bakı (default) 4. Ana səhifə açıqdır: https://birmarket.az/ | G34: 1. Axtarış sahəsinə test datanı daxil et 2. "Axtar" düyməsinə klik et 3. Səhifəni müşahidə et | H34: Açar söz: "a" simvolu × 256 | I34: 1. Səhifə 500/timeout xətası vermir 2. Sorğuya uyğun məhsul tapılmadı "aaa…" mesajı göstərilir və ya sahə simvol limitindən artığını qəbul etmir | J34: TS_UI_07 | K34: Edge case, bir dəfəlik exploratory yoxlama; regression dəyəri aşağı → manual. | L34: Not Run | M34: Manual | N34: No
A35: TC_SRCH_EDGE_012 | B35: Tək simvolla ("a") axtarış sistemi çökdürmür | C35: Axtarış → Minimum uzunluq | D35: P3 - Medium | E35: Edge, BVA | F35: 1. Brauzer: Google Chrome (son stabil versiya), incognito rejim (cookies/cache təmizdir) 2. İstifadəçi login olmayıb (Guest) 3. Dil: AZ, Şəhər: Bakı (default) 4. Ana səhifə açıqdır: https://birmarket.az/ | G35: 1. Axtarış sahəsinə 1 simvol daxil et 2. Axtarışı icra et 3. Nəticəni müşahidə et | H35: Açar söz: a (1 simvol) | I35: Ya nəticələr göstərilir, ya da minimum simvol sayı barədə mesaj göstərilir; 500 xətası yoxdur (GQ_UI_20) | J35: TS_UI_07 | K35: Gözlənilən davranış tələbdə müəyyən deyil (Grooming Questions sheet-ə bax). Cavab gəlməyənə qədər manual; təsdiqdən sonra avtomatlaşdırma namizədidir. | L35: Not Run | M35: Manual | N35: No
A36: TC_SRCH_NEG_003 | B36: Mövcud olmayan açar sözlə axtarışda məhsul qaytarılmır və boş nəticə mesajı göstərilir | C36: Axtarış → Nəticəsiz sorğu | D36: P1 - Critical | E36: Neqativ | F36: 1. Brauzer: Google Chrome (son stabil versiya), incognito rejim (cookies/cache təmizdir) 2. İstifadəçi login olmayıb (Guest) 3. Dil: AZ, Şəhər: Bakı (default) 4. Ana səhifə açıqdır: https://birmarket.az/ | G36: 1. Axtarış sahəsinə açar sözü daxil et 2. "Axtar" düyməsinə klik et 3. Nəticə səhifəsini müşahidə et | H36: Açar söz: qwxzqwxz123 | I36: 1. Məhsul kartı sayı = 0 2. Mesaj göstərilir: Sorğuya uyğun məhsul tapılmadı "qwxzqwxz123" 3. Alt mətn göstərilir: "Yazılış qaydasını yoxlayın, digər açar sözlərini istifadə edin və ya axtarışı kateqoriya seçimindən başlayın" 4. Səhifə xəta vermir (500 yoxdur) | J36: TS_UI_07 | K36: Regression-a daxildir, hər release-də təkrarlanır; nəticə data-dan asılı olmayan invariantla yoxlanır (hardcode qiymət/ad yoxdur); xarici asılılıq yoxdur → avtomatlaşdırılır. | L36: Pass | M36: Automated | N36: Yes | O36: Gözlənilən nəticə ilə üst-üstə düşür. Gauge avtomat run (Chrome 154, guest): PASS. | P36: 06.10.2026 | Q36: Avtomat (Gauge + Selenium)
A37: TC_SRCH_NEG_004 | B37: Boş axtarış sahəsi ilə "Axtar" düyməsinə klik edildikdə axtarış icra olunmur | C37: Axtarış → Boş sorğu | D37: P2 - High | E37: Neqativ, Edge | F37: 1. Brauzer: Google Chrome (son stabil versiya), incognito rejim (cookies/cache təmizdir) 2. İstifadəçi login olmayıb (Guest) 3. Dil: AZ, Şəhər: Bakı (default) 4. Ana səhifə açıqdır: https://birmarket.az/ | G37: 1. Axtarış sahəsini boş saxla 2. "Axtar" düyməsinə klik et 3. URL-i və səhifəni müşahidə et | H37: Açar söz: (boş) | I37: 1. Heç bir reaksiya olmur: nəticə səhifəsinə keçid baş vermir 2. URL dəyişmir (https://birmarket.az/ qalır) 3. Səhifə xəta vermir | J37: TS_UI_07 | K37: Davranış saytda təsdiqlənib (GQ cavablanıb); deterministik nəticə, SMS/login tələb etmir → avtomatlaşdırılır. | L37: Pass | M37: Automated | N37: Yes | O37: Gözlənilən nəticə ilə üst-üstə düşür. Gauge avtomat run (Chrome 154, guest): PASS. | P37: 06.10.2026 | Q37: Avtomat (Gauge + Selenium)
A38: TC_SRCH_POS_001 | B38: Mövcud açar sözlə ("iphone") axtarış nəticələri açar sözü ehtiva edən məhsulları qaytarır | C38: Axtarış → Açar söz | D38: P1 - Critical | E38: Pozitiv, Smoke | F38: 1. Brauzer: Google Chrome (son stabil versiya), incognito rejim (cookies/cache təmizdir) 2. İstifadəçi login olmayıb (Guest) 3. Dil: AZ, Şəhər: Bakı (default) 4. Ana səhifə açıqdır: https://birmarket.az/ | G38: 1. Axtarış sahəsinə açar sözü daxil et 2. "Axtar" düyməsinə klik et 3. Nəticə səhifəsindəki məhsul kartlarını yoxla | H38: Açar söz: iphone | I38: 1. Nəticə səhifəsində ən azı 1 məhsul kartı var 2. İlk 10 kartın hər birinin adı "iphone" sözünü ehtiva edir (böyük/kiçik hərfdən asılı olmayaraq) 3. Hər kartda qiymət "₼" valyutası ilə göstərilir | J38: TS_UI_07 | K38: Əsas biznes axını (axtarış = satışın girişi). Yoxlama sabit nəticə sayına yox, invarianta (ad açar sözü ehtiva edir) əsaslanır → flaky deyil, avtomatlaşdırılır. | L38: Pass | M38: Automated | N38: Yes | O38: Gözlənilən nəticə ilə üst-üstə düşür. Gauge avtomat run (Chrome 154, guest): PASS. | P38: 06.10.2026 | Q38: Avtomat (Gauge + Selenium)
A39: TC_SRCH_POS_002 | B39: Axtarış böyük/kiçik hərfə həssas deyil: "IPHONE" və "iphone" eyni nəticəni qaytarır | C39: Axtarış → Case-insensitive | D39: P2 - High | E39: Pozitiv, Edge | F39: 1. Brauzer: Google Chrome (son stabil versiya), incognito rejim (cookies/cache təmizdir) 2. İstifadəçi login olmayıb (Guest) 3. Dil: AZ, Şəhər: Bakı (default) 4. Ana səhifə açıqdır: https://birmarket.az/ | G39: 1. Axtarış sahəsinə 1-ci açar sözü daxil edib axtar 2. İlk 5 məhsulun adlarını qeyd et 3. Ana səhifəyə qayıt 4. Axtarış sahəsinə 2-ci açar sözü daxil edib axtar 5. İlk 5 məhsulun adlarını müqayisə et | H39: Açar söz 1: iphone Açar söz 2: IPHONE | I39: Hər iki axtarışda ilk 5 məhsulun adları və sırası eynidir | J39: TS_UI_07 | K39: İki nəticə bir-biri ilə müqayisə olunur (hardcode yoxdur) → data dəyişsə də stabil; regression-da axtarış alqoritmi dəyişikliyini tutur → avtomatlaşdırılır. | L39: Pass | M39: Automated | N39: Yes | O39: "iphone" və "IPHONE" sorğuları eyni nəticəni qaytardı: "Tapılan məhsul: 300". PASS. | P39: 06.10.2026 | Q39: Avtomat (Gauge + Selenium)
A40: TC_SRCH_POS_006 | B40: Axtarış sahəsinə yazarkən avtomatik təkliflər (autocomplete) göstərilir | C40: Axtarış → Autocomplete | D40: P3 - Medium | E40: Pozitiv, UI | F40: 1. Brauzer: Google Chrome (son stabil versiya), incognito rejim (cookies/cache təmizdir) 2. İstifadəçi login olmayıb (Guest) 3. Dil: AZ, Şəhər: Bakı (default) 4. Ana səhifə açıqdır: https://birmarket.az/ | G40: 1. Axtarış sahəsinə klik et 2. Test datanı yaz, Enter basma 3. Açılan təkliflər siyahısını müşahidə et 4. İlk təklifə klik et | H40: Mətn: sams | I40: 1. Sahənin altında təkliflər siyahısı açılır 2. Təkliflər "sams" hərf birləşməsini ehtiva edir 3. Təklifə klik nəticə səhifəsini açır | J40: TS_UI_07 | K40: Təkliflər populyarlığa görə dinamik dəyişir və debounce/async render olunur; biznes riski aşağı → manual. | L40: Not Run | M40: Manual | N40: No
A41: TC_SRCH_POS_008 | B41: Axtarış Enter düyməsi ilə də icra olunur və "Axtar" düyməsi ilə eyni nəticəni verir | C41: Axtarış → Enter ilə axtarış | D41: P2 - High | E41: Pozitiv | F41: 1. Brauzer: Google Chrome (son stabil versiya), incognito rejim (cookies/cache təmizdir) 2. İstifadəçi login olmayıb (Guest) 3. Dil: AZ, Şəhər: Bakı (default) 4. Ana səhifə açıqdır: https://birmarket.az/ | G41: 1. Axtarış sahəsinə açar sözü yaz 2. Klaviaturada Enter bas 3. İlk 5 məhsulun adını qeyd et 4. Ana səhifəyə qayıt, eyni sözü yazıb "Axtar" düyməsinə klik et 5. İlk 5 məhsulu müqayisə et | H41: Açar söz: samsung | I41: 1. Enter ilə nəticə səhifəsi açılır 2. Hər iki üsulla ilk 5 məhsulun adları eynidir | J41: TS_UI_07 | K41: Regression-a daxildir, hər release-də təkrarlanır; nəticə data-dan asılı olmayan invariantla yoxlanır (hardcode qiymət/ad yoxdur); xarici asılılıq yoxdur → avtomatlaşdırılır. | L41: Pass | M41: Automated | N41: Yes | O41: Gözlənilən nəticə ilə üst-üstə düşür. Gauge avtomat run (Chrome 154, guest): PASS. | P41: 06.10.2026 | Q41: Avtomat (Gauge + Selenium)
A42: TC_SRCH_POS_009 | B42: Axtarış nəticəsindəki karta klik edildikdə həmin məhsulun PDP-si açılır | C42: Axtarış → Nəticədən PDP-yə keçid | D42: P2 - High | E42: Pozitiv | F42: 1. Brauzer: Google Chrome (son stabil versiya), incognito rejim (cookies/cache təmizdir) 2. İstifadəçi login olmayıb (Guest) 3. Dil: AZ, Şəhər: Bakı (default) 4. Ana səhifə açıqdır: https://birmarket.az/ | G42: 1. Açar sözlə axtar 2. İlk kartın adını qeyd et 3. Karta klik et 4. PDP-dəki adı oxu | H42: Açar söz: iphone | I42: 1. URL "/product/" ehtiva edir 2. PDP adı = kartdakı ad | J42: TS_UI_07 | K42: Regression-a daxildir, hər release-də təkrarlanır; nəticə data-dan asılı olmayan invariantla yoxlanır (hardcode qiymət/ad yoxdur); xarici asılılıq yoxdur → avtomatlaşdırılır. | L42: Pass | M42: Automated | N42: Yes | O42: Gözlənilən nəticə ilə üst-üstə düşür. Gauge avtomat run (Chrome 154, guest): PASS. | P42: 06.10.2026 | Q42: Avtomat (Gauge + Selenium)
A43: TC_SRCH_POS_010 | B43: Kateqoriyadan götürülmüş tam məhsul adı ilə axtarışda həmin məhsul ilk 10 nəticədə olur | C43: Axtarış → Tam adla axtarış | D43: P1 - Critical | E43: Pozitiv | F43: 1. Brauzer: Google Chrome (son stabil versiya), incognito rejim (cookies/cache təmizdir) 2. İstifadəçi login olmayıb (Guest) 3. Dil: AZ, Şəhər: Bakı (default) 4. Kateqoriya səhifəsi açıqdır: https://birmarket.az/categories/2-telefonlar-ve-aksessuarlar | G43: 1. Kateqoriyadakı 1-ci kartın tam adını qeyd et 2. Həmin adı axtarış sahəsinə daxil et və axtar 3. İlk 10 nəticənin adlarını oxu | H43: Açar söz: 1-ci kartın adı (dinamik — UI-dan oxunur) | I43: Qeyd edilmiş ad ilk 10 nəticənin birinin adı ilə tam üst-üstə düşür | J43: TS_UI_07 | K43: Axtarış relevansını yoxlayır; test data UI-dan dinamik götürülür (hardcode yoxdur) → məhsul dəyişsə də stabil, avtomatlaşdırılır. | Avtomatlaşdırma cəhdindən sonra Manual-a keçirildi: Nəticə dinamik prod məhsul adından asılıdır. | L43: Pass | M43: Manual | N43: Yes (Manual) | O43: Kateqoriyanın 1-ci məhsulu "Smartfon Apple iPhone 18 Pro 256GB Burgundy" adı ilə axtarıldı: "Tapılan məhsul: 172", həmin məhsul (3 587.89 ₼, MJRR4QN) nəticələrdə 1-ci yerdədir. PASS. | P43: 07.10.2026 | Q43: Manual (saytda yoxlanılıb)
A44: TC_SRCH_POS_011 | B44: Axtarış icra olunduqdan sonra sorğu mətni axtarış sahəsində qalır | C44: Axtarış → Sorğunun saxlanması | D44: P3 - Medium | E44: UI | F44: 1. Brauzer: Google Chrome (son stabil versiya), incognito rejim (cookies/cache təmizdir) 2. İstifadəçi login olmayıb (Guest) 3. Dil: AZ, Şəhər: Bakı (default) 4. Ana səhifə açıqdır: https://birmarket.az/ | G44: 1. Açar sözlə axtar 2. Nəticə səhifəsində axtarış sahəsinin dəyərini oxu | H44: Açar söz: xiaomi | I44: Axtarış sahəsində "xiaomi" mətni qalır | J44: TS_UI_07 | K44: Aşağı riskli, nadir dəyişən funksionallıq; regression ROI aşağıdır → manual. | L44: Not Run | M44: Manual | N44: No
A45: TC_SRCH_POS_013 | B45: [Login] Login istifadəçi üçün axtarış nəticələri guest ilə eynidir | C45: Axtarış (Login) → Nəticə uyğunluğu | D45: P3 - Medium | E45: Pozitiv | F45: 1. Brauzer: Google Chrome (son stabil versiya) 2. Test hesabı Birmarket-də qeydiyyatdadır, telefon nömrəsi SMS qəbul edir (test icraçısının əlindədir) 3. İstifadəçi həmin hesabla login olub (header-də "Şəxsi hesabım" görünür) 4. Ana səhifə açıqdır: https://birmarket.az/ 5. Paralel olaraq incognito pəncərədə guest sessiyası açıqdır | G45: 1. Login sessiyasında açar sözlə axtar, ilk 5 məhsulu qeyd et 2. Guest sessiyasında eyni sözlə axtar, ilk 5 məhsulu qeyd et 3. Müqayisə et | H45: Açar söz: iphone | I45: Hər iki sessiyada ilk 5 məhsul eynidir (personallaşdırma axtarışı pozmur) | J45: TS_UI_08 | K45: OTP ilə login tələb edir (prod-da bypass yoxdur) → avtomatlaşdırıla bilmir. Biznes riski orta/aşağı olduğu üçün regression-a daxil edilmir. | L45: Not Run | M45: Manual | N45: No
A46: TC_CAT_NEG_006 | B46: Mövcud olmayan kateqoriya URL-i açıldıqda 404 səhifəsi göstərilir | C46: Kataloq → Yanlış URL | D46: P3 - Medium | E46: Neqativ | F46: 1. Brauzer: Google Chrome (son stabil versiya), incognito rejim (cookies/cache təmizdir) 2. İstifadəçi login olmayıb (Guest) 3. Dil: AZ, Şəhər: Bakı (default) | G46: 1. Brauzerdə test URL-ni aç 2. Səhifəni müşahidə et | H46: URL: https://birmarket.az/categories/999999-movcud-olmayan | I46: 1. Başlıq: "Səhifə tapılmadı" 2. Mətn: "Əfsuslar olsun ki belə səhifə yoxdur və ya ünvan yanlışdır" 3. 500 xətası yoxdur | J46: TS_UI_09 | K46: Deterministik nəticə, error handling regression-u → avtomatlaşdırılır. | L46: Pass | M46: Automated | N46: Yes | O46: Gözlənilən nəticə ilə üst-üstə düşür. Gauge avtomat run (Chrome 154, guest): PASS. | P46: 06.10.2026 | Q46: Avtomat (Gauge + Selenium)
A47: TC_CAT_POS_001 | B47: "Məhsul kataloqu" düyməsinə klik edildikdə əsas kateqoriyalar siyahısı açılır | C47: Kataloq → Kateqoriya menyusu | D47: P1 - Critical | E47: Pozitiv, Smoke | F47: 1. Brauzer: Google Chrome (son stabil versiya), incognito rejim (cookies/cache təmizdir) 2. İstifadəçi login olmayıb (Guest) 3. Dil: AZ, Şəhər: Bakı (default) 4. Ana səhifə açıqdır: https://birmarket.az/ | G47: 1. Header-dəki "Məhsul kataloqu" düyməsinə klik et 2. Açılan menyunu müşahidə et | H47: Gözlənilən kateqoriya: Telefonlar, Smart cihazlar və telefon aksessuarları | I47: 1. Kateqoriya menyusu açılır 2. Siyahıda ən azı 10 kateqoriya var 3. "Telefonlar, Smart cihazlar və telefon aksessuarları" kateqoriyası siyahıdadır | J47: TS_UI_09 | K47: Naviqasiyanın əsas girişi, smoke; kateqoriya strukturu stabildir → avtomatlaşdırılır. | Avtomatlaşdırma cəhdindən sonra Manual-a keçirildi: Kataloq menyusu overlay/hover ilə açılır, stabil locator yoxdur. | L47: Pass | M47: Manual | N47: Yes (Manual) | O47: "Məhsul kataloqu" menyusu açıldı: 20 kateqoriya + 3 kampaniya linki (60%-dək payız endirimləri, iPhone 18, Mega endirimlər). "Telefonlar, Smart cihazlar və telefon aksessuarları" siyahıdadır. PASS. | P47: 07.10.2026 | Q47: Manual (saytda yoxlanılıb)
A48: TC_CAT_POS_002 | B48: Kateqoriyaya klik edildikdə müvafiq kateqoriya səhifəsi məhsullarla açılır | C48: Kataloq → Kateqoriya səhifəsi | D48: P1 - Critical | E48: Pozitiv, Smoke | F48: 1. Brauzer: Google Chrome (son stabil versiya), incognito rejim (cookies/cache təmizdir) 2. İstifadəçi login olmayıb (Guest) 3. Dil: AZ, Şəhər: Bakı (default) 4. Ana səhifə açıqdır: https://birmarket.az/ | G48: 1. "Məhsul kataloqu" düyməsinə klik et 2. Kateqoriyaya klik et 3. URL-i, H1 başlığını və məhsul kartlarını yoxla | H48: Kateqoriya: Telefonlar, Smart cihazlar və telefon aksessuarları | I48: 1. URL "/categories/2-telefonlar-ve-aksessuarlar" ehtiva edir 2. H1 başlığı = "Telefonlar, Smart cihazlar və telefon aksessuarları" 3. Ən azı 1 məhsul kartı göstərilir | J48: TS_UI_09 | K48: Regression-a daxildir, hər release-də təkrarlanır; nəticə data-dan asılı olmayan invariantla yoxlanır (hardcode qiymət/ad yoxdur); xarici asılılıq yoxdur → avtomatlaşdırılır. | L48: Pass | M48: Automated | N48: Yes | O48: Gözlənilən nəticə ilə üst-üstə düşür. Gauge avtomat run (Chrome 154, guest): PASS. | P48: 06.10.2026 | Q48: Avtomat (Gauge + Selenium)
A49: TC_CAT_POS_003 | B49: Kateqoriya səhifəsindəki breadcrumb düzgün iyerarxiyanı göstərir və "Birmarket" linki ana səhifəyə aparır | C49: Kataloq → Breadcrumb | D49: P3 - Medium | E49: Pozitiv | F49: 1. Brauzer: Google Chrome (son stabil versiya), incognito rejim (cookies/cache təmizdir) 2. İstifadəçi login olmayıb (Guest) 3. Dil: AZ, Şəhər: Bakı (default) 4. Kateqoriya səhifəsi açıqdır: https://birmarket.az/categories/2-telefonlar-ve-aksessuarlar | G49: 1. Breadcrumb elementlərini oxu 2. Breadcrumb-dakı "Birmarket" linkinə klik et 3. URL-i yoxla | H49: — | I49: 1. Breadcrumb ardıcıllığı: Birmarket → Kateqoriyalar → Elektronika və məişət texnikası 2. "Birmarket" linki https://birmarket.az/ açır | J49: TS_UI_09 | K49: İyerarxiya kataloq dəyişikliklərində sınır; stabil və deterministikdir → avtomatlaşdırılır. | L49: Pass | M49: Automated | N49: Yes | O49: Gözlənilən nəticə ilə üst-üstə düşür. Gauge avtomat run (Chrome 154, guest): PASS. | P49: 06.10.2026 | Q49: Avtomat (Gauge + Selenium)
A50: TC_CAT_POS_004 | B50: Alt kateqoriyaya keçid zamanı H1 və breadcrumb alt kateqoriyanı əks etdirir | C50: Kataloq → Alt kateqoriya | D50: P2 - High | E50: Pozitiv | F50: 1. Brauzer: Google Chrome (son stabil versiya), incognito rejim (cookies/cache təmizdir) 2. İstifadəçi login olmayıb (Guest) 3. Dil: AZ, Şəhər: Bakı (default) 4. Kateqoriya səhifəsi açıqdır: https://birmarket.az/categories/2-telefonlar-ve-aksessuarlar | G50: 1. "Mobil telefonlar və smartfonlar" alt kateqoriyasına klik et 2. URL-i yoxla 3. H1 başlığını yoxla 4. Breadcrumb-u yoxla | H50: Alt kateqoriya: Mobil telefonlar və smartfonlar | I50: 1. URL "/categories/3-mobil-telefonlar-ve-smartfonlar" ehtiva edir 2. H1 = "Mobil telefonlar və smartfonlar" 3. Breadcrumb-da valideyn kateqoriya göstərilir 4. Ən azı 1 məhsul kartı var | J50: TS_UI_09 | K50: Regression-a daxildir, hər release-də təkrarlanır; nəticə data-dan asılı olmayan invariantla yoxlanır (hardcode qiymət/ad yoxdur); xarici asılılıq yoxdur → avtomatlaşdırılır. | Avtomatlaşdırma cəhdindən sonra Manual-a keçirildi: Alt kateqoriya strukturu dinamikdir, stabil locator yoxdur. | L50: Not Run | M50: Manual | N50: Yes (Manual)
A51: TC_CAT_POS_005 | B51: "Bütün kateqoriyalar" linki bütün əsas kateqoriyaları göstərən səhifəni açır | C51: Kataloq → Bütün kateqoriyalar | D51: P3 - Medium | E51: Pozitiv | F51: 1. Brauzer: Google Chrome (son stabil versiya), incognito rejim (cookies/cache təmizdir) 2. İstifadəçi login olmayıb (Guest) 3. Dil: AZ, Şəhər: Bakı (default) 4. Ana səhifə açıqdır: https://birmarket.az/ | G51: 1. "Məhsul kataloqu"-nu aç 2. "Bütün kateqoriyalar" linkinə klik et 3. Səhifəni yoxla | H51: — | I51: 1. URL "/categories" olur 2. Kataloq menyusundakı bütün əsas kateqoriyalar səhifədə göstərilir | J51: TS_UI_09 | K51: Aşağı riskli, nadir dəyişən funksionallıq; regression ROI aşağıdır → manual. | L51: Not Run | M51: Manual | N51: No
A52: TC_CAT_UI_007 | B52: Kataloq menyusunda kursor kateqoriyanın üzərinə gətirildikdə alt kateqoriyalar göstərilir | C52: Kataloq → Hover menyu | D52: P3 - Medium | E52: UI | F52: 1. Brauzer: Google Chrome (son stabil versiya), incognito rejim (cookies/cache təmizdir) 2. İstifadəçi login olmayıb (Guest) 3. Dil: AZ, Şəhər: Bakı (default) 4. Ana səhifə açıqdır: https://birmarket.az/ | G52: 1. "Məhsul kataloqu"-nu aç 2. Kursoru "Məişət texnikası" kateqoriyasının üzərinə gətir 3. Sağ paneli müşahidə et | H52: Kateqoriya: Məişət texnikası | I52: Sağ paneldə "Məişət texnikası"-nın alt kateqoriyaları göstərilir | J52: TS_UI_09 | K52: Hover əsaslı interaksiya avtomatlaşdırmada qeyri-stabildir; vizual yoxlamadır → manual. | L52: Not Run | M52: Manual | N52: No
A53: TC_PLP_BVA_005 | B53: Qiymət filtrinə mənfi dəyər (-1) daxil edildikdə sahə onu qəbul etmir | C53: Məhsul siyahısı → Qiymət filtri | D53: P3 - Medium | E53: Neqativ, BVA | F53: 1. Brauzer: Google Chrome (son stabil versiya), incognito rejim (cookies/cache təmizdir) 2. İstifadəçi login olmayıb (Guest) 3. Dil: AZ, Şəhər: Bakı (default) 4. Kateqoriya səhifəsi açıqdır: https://birmarket.az/categories/2-telefonlar-ve-aksessuarlar | G53: 1. Minimum qiymət sahəsinə test datanı daxil et 2. Sahədə qalan dəyəri yoxla 3. Filtri tətbiq et | H53: Min: -1 (alt sərhəd 0-ın altı) | I53: 1. Mənfi dəyər daxil edilən kimi sahə avtomatik sıfırlanır 2. Filtr tətbiq olunmur, məhsul sayı dəyişmir | J53: TS_UI_10 | K53: Davranış təsdiqlənib (sahə yanlış dəyəri avtomatik sıfırlayır) → deterministik, SMS/login tələb etmir, avtomatlaşdırılır. | L53: Pass | M53: Automated | N53: Yes | O53: Gözlənilən nəticə ilə üst-üstə düşür. Gauge avtomat run (Chrome 154, guest): PASS. | P53: 06.10.2026 | Q53: Avtomat (Gauge + Selenium)
A54: TC_PLP_BVA_012 | B54: Qiymət filtrində min = max olduqda sistem xəta vermir | C54: Məhsul siyahısı → Qiymət filtri | D54: P3 - Medium | E54: BVA, Edge | F54: 1. Brauzer: Google Chrome (son stabil versiya), incognito rejim (cookies/cache təmizdir) 2. İstifadəçi login olmayıb (Guest) 3. Dil: AZ, Şəhər: Bakı (default) 4. Kateqoriya səhifəsi açıqdır: https://birmarket.az/categories/2-telefonlar-ve-aksessuarlar | G54: 1. Min dəyəri daxil et 2. Max dəyəri daxil et 3. Filtri tətbiq et | H54: Min: 25 Max: 25 | I54: 1. Yalnız qiyməti 25.00 ₼ olan məhsullar göstərilir və ya boş nəticə mesajı 2. 500 xətası yoxdur | J54: TS_UI_10 | K54: Gözlənilən davranış tələbdə müəyyən deyil (Grooming Questions sheet-ə bax). Cavab gəlməyənə qədər manual; təsdiqdən sonra avtomatlaşdırma namizədidir. | L54: Not Run | M54: Manual | N54: No
A55: TC_PLP_NEG_004 | B55: Qiymət filtrində minimum maksimumdan böyük daxil edildikdə dəyər avtomatik sıfırlanır | C55: Məhsul siyahısı → Qiymət filtri | D55: P2 - High | E55: Neqativ, Decision Table | F55: 1. Brauzer: Google Chrome (son stabil versiya), incognito rejim (cookies/cache təmizdir) 2. İstifadəçi login olmayıb (Guest) 3. Dil: AZ, Şəhər: Bakı (default) 4. Kateqoriya səhifəsi açıqdır: https://birmarket.az/categories/2-telefonlar-ve-aksessuarlar | G55: 1. "Qiyməti" bölməsində max dəyəri daxil et 2. Min dəyəri daxil et 3. Sahələrin dəyərlərini oxu 4. Kartların sayını yoxla | H55: Min: 200 Max: 100 | I55: 1. Yanlış dəyər daxil edilən kimi sahə avtomatik sıfırlanır 2. Filtr tətbiq olunmur, məhsul sayı dəyişmir 3. 500 xətası yoxdur | J55: TS_UI_10 | K55: Davranış təsdiqlənib (sahə yanlış dəyəri avtomatik sıfırlayır) → deterministik, SMS/login tələb etmir, avtomatlaşdırılır. | Avtomatlaşdırma cəhdindən sonra Manual-a keçirildi: Qiymət filtrinin "OK" düyməsi avtomatlaşdırmada tətbiq olunmur (filtr URL parametri ilə işləyir). | L55: Pass | M55: Manual | N55: Yes (Manual) | O55: Min > Max daxil edildikdə sahə avtomatik sıfırlanır, xəta/500 yoxdur (GQ_UI_02). PASS. | P55: 06.10.2026 | Q55: Manual (saytda yoxlanılıb)
A56: TC_PLP_NEG_013 | B56: Qiymət filtrinə hərf daxil edildikdə sahə onu qəbul etmir | C56: Məhsul siyahısı → Qiymət filtri | D56: P3 - Medium | E56: Neqativ, EP | F56: 1. Brauzer: Google Chrome (son stabil versiya), incognito rejim (cookies/cache təmizdir) 2. İstifadəçi login olmayıb (Guest) 3. Dil: AZ, Şəhər: Bakı (default) 4. Kateqoriya səhifəsi açıqdır: https://birmarket.az/categories/2-telefonlar-ve-aksessuarlar | G56: 1. Min qiymət sahəsinə test datanı daxil et 2. Sahənin dəyərini oxu | H56: Min: abc | I56: Hərf daxil edilən kimi sahə avtomatik sıfırlanır (boş qalır), filtr tətbiq olunmur | J56: TS_UI_10 | K56: Davranış təsdiqlənib (sahə yanlış dəyəri avtomatik sıfırlayır) → deterministik, SMS/login tələb etmir, avtomatlaşdırılır. | L56: Pass | M56: Automated | N56: Yes | O56: Gözlənilən nəticə ilə üst-üstə düşür. Gauge avtomat run (Chrome 154, guest): PASS. | P56: 06.10.2026 | Q56: Avtomat (Gauge + Selenium)
A57: TC_PLP_NEG_014 | B57: Mövcud olmayan səhifə nömrəsi (page=99999) xəta vermədən idarə olunur | C57: Məhsul siyahısı → Pagination sərhədi | D57: P3 - Medium | E57: Neqativ, BVA | F57: 1. Brauzer: Google Chrome (son stabil versiya), incognito rejim (cookies/cache təmizdir) 2. İstifadəçi login olmayıb (Guest) 3. Dil: AZ, Şəhər: Bakı (default) | G57: 1. Brauzerdə test URL-ni aç 2. Səhifəni müşahidə et | H57: URL: https://birmarket.az/categories/2-telefonlar-ve-aksessuarlar?page=99999 | I57: 1. 500 xətası yoxdur 2. Ya boş siyahı mesajı, ya 404, ya da son səhifəyə yönləndirmə baş verir | J57: TS_UI_10 | K57: Regression-a daxildir, hər release-də təkrarlanır; nəticə data-dan asılı olmayan invariantla yoxlanır (hardcode qiymət/ad yoxdur); xarici asılılıq yoxdur → avtomatlaşdırılır. | L57: Pass | M57: Automated | N57: Yes | O57: Gözlənilən nəticə ilə üst-üstə düşür. Gauge avtomat run (Chrome 154, guest): PASS. | P57: 06.10.2026 | Q57: Avtomat (Gauge + Selenium)
A58: TC_PLP_POS_001 | B58: Məhsullar "Ən ucuz" sıralandıqda qiymətlər azalmayan ardıcıllıqla göstərilir | C58: Məhsul siyahısı → Sıralama | D58: P1 - Critical | E58: Pozitiv | F58: 1. Brauzer: Google Chrome (son stabil versiya), incognito rejim (cookies/cache təmizdir) 2. İstifadəçi login olmayıb (Guest) 3. Dil: AZ, Şəhər: Bakı (default) 4. Kateqoriya səhifəsi açıqdır: https://birmarket.az/categories/2-telefonlar-ve-aksessuarlar | G58: 1. Sıralama seçicisinə klik et 2. "Ən ucuz" seçimini et 3. Siyahının yenilənməsini gözlə 4. İlk 20 kartın cari (endirimli) qiymətini oxu | H58: Sıralama: Ən ucuz | I58: Hər qonşu kart cütü üçün: qiymət[i] ≤ qiymət[i+1] (ilk 20 kart) | J58: TS_UI_10 | K58: Sıralama seçimi saytda təsdiqlənib; konkret qiymət yox, sıralama invariantı yoxlanılır → data dəyişsə də stabil, avtomatlaşdırılır. | L58: Pass | M58: Automated | N58: Yes | O58: Gözlənilən nəticə ilə üst-üstə düşür. Gauge avtomat run (Chrome 154, guest): PASS. | P58: 06.10.2026 | Q58: Avtomat (Gauge + Selenium)
A59: TC_PLP_POS_002 | B59: Məhsullar "Ən bahalı" sıralandıqda qiymətlər artmayan ardıcıllıqla göstərilir | C59: Məhsul siyahısı → Sıralama | D59: P2 - High | E59: Pozitiv | F59: 1. Brauzer: Google Chrome (son stabil versiya), incognito rejim (cookies/cache təmizdir) 2. İstifadəçi login olmayıb (Guest) 3. Dil: AZ, Şəhər: Bakı (default) 4. Kateqoriya səhifəsi açıqdır: https://birmarket.az/categories/2-telefonlar-ve-aksessuarlar | G59: 1. Sıralama seçicisinə klik et 2. "Ən bahalı" seçimini et 3. Siyahının yenilənməsini gözlə 4. İlk 20 kartın cari qiymətini oxu | H59: Sıralama: Ən bahalı | I59: Hər qonşu kart cütü üçün: qiymət[i] ≥ qiymət[i+1] (ilk 20 kart) | J59: TS_UI_10 | K59: Sıralama seçimi saytda təsdiqlənib; konkret qiymət yox, sıralama invariantı yoxlanılır → data dəyişsə də stabil, avtomatlaşdırılır. | L59: Pass | M59: Automated | N59: Yes | O59: Gözlənilən nəticə ilə üst-üstə düşür. Gauge avtomat run (Chrome 154, guest): PASS. | P59: 06.10.2026 | Q59: Avtomat (Gauge + Selenium)
A60: TC_PLP_POS_003 | B60: Qiymət filtri (100–200 ₼) tətbiq edildikdə yalnız həmin aralıqda qiyməti olan məhsullar göstərilir | C60: Məhsul siyahısı → Qiymət filtri | D60: P1 - Critical | E60: Pozitiv, EP | F60: 1. Brauzer: Google Chrome (son stabil versiya), incognito rejim (cookies/cache təmizdir) 2. İstifadəçi login olmayıb (Guest) 3. Dil: AZ, Şəhər: Bakı (default) 4. Kateqoriya səhifəsi açıqdır: https://birmarket.az/categories/2-telefonlar-ve-aksessuarlar | G60: 1. Filtr panelində "Qiyməti" bölməsində minimum dəyəri daxil et 2. Maksimum dəyəri daxil et 3. "OK" düyməsinə klik et 4. Göstərilən bütün kartların cari qiymətini oxu | H60: Min: 100 Max: 200 | I60: 1. Ən azı 1 məhsul göstərilir 2. Hər kartın cari qiyməti 100.00 ≤ qiymət ≤ 200.00 ₼ 3. URL-də/filtr panelində tətbiq olunmuş filtr görünür | J60: TS_UI_10 | K60: Aralıq invariantı yoxlanılır (hardcode nəticə yoxdur); filtr məntiqi regression riski yüksəkdir → avtomatlaşdırılır. | L60: Pass | M60: Automated | N60: Yes | O60: Filtr URL parametrləri ilə tətbiq olunur (?price_from=100&price_to=200). Min/Max sahələri 100/200 göstərir, bütün məhsul qiymətləri 100–200 ₼ aralığındadır. PASS. | P60: 06.10.2026 | Q60: Avtomat (Gauge + Selenium)
A61: TC_PLP_POS_006 | B61: Səhifələmədə 2-ci səhifəyə keçid fərqli məhsullar göstərir | C61: Məhsul siyahısı → Pagination | D61: P2 - High | E61: Pozitiv | F61: 1. Brauzer: Google Chrome (son stabil versiya), incognito rejim (cookies/cache təmizdir) 2. İstifadəçi login olmayıb (Guest) 3. Dil: AZ, Şəhər: Bakı (default) 4. Kateqoriya səhifəsi açıqdır: https://birmarket.az/categories/2-telefonlar-ve-aksessuarlar | G61: 1. 1-ci səhifədəki ilk 5 məhsulun adını qeyd et 2. Səhifənin aşağısındakı "2" səhifə linkinə klik et 3. URL-i yoxla 4. İlk 5 məhsulun adını müqayisə et | H61: Səhifə: 2 | I61: 1. URL "?page=2" ehtiva edir 2. 2-ci səhifənin ilk 5 məhsulu 1-ci səhifənin ilk 5 məhsulundan fərqlidir 3. Aktiv səhifə göstəricisi "2"-dir | J61: TS_UI_10 | K61: Regression-a daxildir, hər release-də təkrarlanır; nəticə data-dan asılı olmayan invariantla yoxlanır (hardcode qiymət/ad yoxdur); xarici asılılıq yoxdur → avtomatlaşdırılır. | L61: Pass | M61: Automated | N61: Yes | O61: Gözlənilən nəticə ilə üst-üstə düşür. Gauge avtomat run (Chrome 154, guest): PASS. | P61: 06.10.2026 | Q61: Avtomat (Gauge + Selenium)
A62: TC_PLP_POS_007 | B62: Endirimli məhsul kartında köhnə qiymət, yeni qiymət və endirim faizi düzgün hesablanır | C62: Məhsul siyahısı → Endirim göstəricisi | D62: P2 - High | E62: Pozitiv | F62: 1. Brauzer: Google Chrome (son stabil versiya), incognito rejim (cookies/cache təmizdir) 2. İstifadəçi login olmayıb (Guest) 3. Dil: AZ, Şəhər: Bakı (default) 4. Kateqoriya səhifəsi açıqdır: https://birmarket.az/categories/2-telefonlar-ve-aksessuarlar | G62: 1. Endirim nişanı (məs. "-9 %") olan ilk kartı tap 2. Köhnə (üstüxətli) qiyməti oxu 3. Yeni qiyməti oxu 4. Endirim faizini oxu | H62: Seçim qaydası: endirim nişanı olan ilk kart Formula: round((köhnə − yeni) / köhnə × 100) | I62: 1. Köhnə qiymət > yeni qiymət 2. Göstərilən endirim faizi formula nəticəsi ilə ±1% dəqiqliklə üst-üstə düşür | J62: TS_UI_10 | K62: Biznes məntiqi (qiymət hesablanması); dəyərlər UI-dan oxunub bir-biri ilə müqayisə olunur, yuvarlaqlaşdırma üçün ±1 tolerans → stabil, avtomatlaşdırılır. | Avtomatlaşdırma cəhdindən sonra Manual-a keçirildi: Endirim faizi yuvarlaqlaşdırması və kampaniyalar dəyişkəndir. | L62: Not Run | M62: Manual | N62: Yes (Manual)
A63: TC_PLP_POS_008 | B63: Brend filtri (Xiaomi) tətbiq edildikdə yalnız həmin brendin məhsulları göstərilir | C63: Məhsul siyahısı → Brend filtri | D63: P1 - Critical | E63: Pozitiv, EP | F63: 1. Brauzer: Google Chrome (son stabil versiya), incognito rejim (cookies/cache təmizdir) 2. İstifadəçi login olmayıb (Guest) 3. Dil: AZ, Şəhər: Bakı (default) 4. Alt kateqoriya səhifəsi açıqdır: https://birmarket.az/categories/3-mobil-telefonlar-ve-smartfonlar | G63: 1. Kateqoriyanın ümumi məhsul sayını oxu (məs. "1496 məhsul") 2. Filtr panelində "Brend" bölməsində brendi seç (lazım olsa "Hamısını göstər"-ə klik et) 3. Siyahının yenilənməsini gözlə 4. Ümumi məhsul sayını yenidən oxu 5. İlk 20 kartın adını oxu | H63: Brend: Xiaomi | I63: 1. Yeni məhsul sayı > 0 və ilkin saydan azdır 2. Hər kartın adı "Xiaomi" sözünü ehtiva edir | J63: TS_UI_10 | K63: İnvariant yoxlaması (ad brendi ehtiva edir); filtr məntiqi yüksək riskli → avtomatlaşdırılır. | Avtomatlaşdırma cəhdindən sonra Manual-a keçirildi: Brend filtri siyahısı dinamikdir, locator toplanmayıb. | L63: Pass | M63: Manual | N63: Yes (Manual) | O63: "Mobil telefonlar və smartfonlar": 1504 məhsul → Brend "Xiaomi" seçildikdən sonra 139 məhsul. Görünən bütün kartların adında "Xiaomi" var. PASS. | P63: 07.10.2026 | Q63: Manual (saytda yoxlanılıb)
A64: TC_PLP_POS_009 | B64: Brend və qiymət filtri birlikdə tətbiq edildikdə hər iki şərtə uyğun məhsullar göstərilir | C64: Məhsul siyahısı → Kombinə filtr | D64: P2 - High | E64: Pozitiv, Decision Table | F64: 1. Brauzer: Google Chrome (son stabil versiya), incognito rejim (cookies/cache təmizdir) 2. İstifadəçi login olmayıb (Guest) 3. Dil: AZ, Şəhər: Bakı (default) 4. Alt kateqoriya səhifəsi açıqdır: https://birmarket.az/categories/3-mobil-telefonlar-ve-smartfonlar | G64: 1. "Brend" bölməsindən brendi seç 2. "Qiyməti" bölməsində min dəyəri daxil et 3. Max dəyəri daxil et 4. "OK" düyməsinə klik et 5. Bütün kartları yoxla | H64: Brend: Xiaomi Min: 200 Max: 500 | I64: Hər kart üçün: ad "Xiaomi" ehtiva edir VƏ 200.00 ≤ qiymət ≤ 500.00 ₼ | J64: TS_UI_10 | K64: Decision Table — şərtlərin AND kombinasiyası; invariant yoxlaması → stabil, avtomatlaşdırılır. | Avtomatlaşdırma cəhdindən sonra Manual-a keçirildi: Brend filtri siyahısı dinamikdir, locator toplanmayıb. | L64: Not Run | M64: Manual | N64: Yes (Manual)
A65: TC_PLP_POS_010 | B65: Filtrlər sıfırlandıqda siyahı ilkin vəziyyətə qayıdır | C65: Məhsul siyahısı → Filtrləri sıfırlama | D65: P2 - High | E65: Pozitiv, State Transition | F65: 1. Brauzer: Google Chrome (son stabil versiya), incognito rejim (cookies/cache təmizdir) 2. İstifadəçi login olmayıb (Guest) 3. Dil: AZ, Şəhər: Bakı (default) 4. Alt kateqoriya səhifəsi açıqdır: https://birmarket.az/categories/3-mobil-telefonlar-ve-smartfonlar | G65: 1. İlk 5 kartın adını qeyd et 2. Brend filtrini tətbiq et 3. "Sıfırla"/filtri ləğv et düyməsinə klik et 4. İlk 5 kartın adını müqayisə et | H65: Brend: Xiaomi | I65: 1. Aktiv filtr göstəricisi yox olur 2. İlk 5 kart filtrdən əvvəlki ilə eynidir | J65: TS_UI_10 | K65: Regression-a daxildir, hər release-də təkrarlanır; nəticə data-dan asılı olmayan invariantla yoxlanır (hardcode qiymət/ad yoxdur); xarici asılılıq yoxdur → avtomatlaşdırılır. | Avtomatlaşdırma cəhdindən sonra Manual-a keçirildi: Qiymət filtrinin "OK" düyməsi avtomatlaşdırmada tətbiq olunmur. | L65: Not Run | M65: Manual | N65: Yes (Manual)
A66: TC_PLP_POS_011 | B66: Tətbiq olunmuş filtr səhifə yeniləndikdən sonra saxlanılır | C66: Məhsul siyahısı → Filtrin saxlanması | D66: P3 - Medium | E66: Pozitiv | F66: 1. Brauzer: Google Chrome (son stabil versiya), incognito rejim (cookies/cache təmizdir) 2. İstifadəçi login olmayıb (Guest) 3. Dil: AZ, Şəhər: Bakı (default) 4. Alt kateqoriya səhifəsi açıqdır: https://birmarket.az/categories/3-mobil-telefonlar-ve-smartfonlar | G66: 1. Brend filtrini tətbiq et 2. URL-i qeyd et 3. Səhifəni yenilə (F5) 4. Filtr panelini və kartları yoxla | H66: Brend: Xiaomi | I66: 1. URL dəyişmir 2. Brend filtri seçilmiş qalır 3. Bütün kartların adı "Xiaomi" ehtiva edir | J66: TS_UI_10 | K66: Regression-a daxildir, hər release-də təkrarlanır; nəticə data-dan asılı olmayan invariantla yoxlanır (hardcode qiymət/ad yoxdur); xarici asılılıq yoxdur → avtomatlaşdırılır. | Avtomatlaşdırma cəhdindən sonra Manual-a keçirildi: Qiymət filtrinin "OK" düyməsi avtomatlaşdırmada tətbiq olunmur. | L66: Not Run | M66: Manual | N66: Yes (Manual)
A67: TC_PLP_POS_015 | B67: Son səhifədə "İrəli" düyməsi göstərilmir və ya deaktivdir | C67: Məhsul siyahısı → Son səhifə | D67: P3 - Medium | E67: BVA | F67: 1. Brauzer: Google Chrome (son stabil versiya), incognito rejim (cookies/cache təmizdir) 2. İstifadəçi login olmayıb (Guest) 3. Dil: AZ, Şəhər: Bakı (default) 4. Kateqoriya səhifəsi açıqdır: https://birmarket.az/categories/2-telefonlar-ve-aksessuarlar | G67: 1. Pagination-da son səhifə nömrəsinə klik et 2. "İrəli" düyməsinin vəziyyətini yoxla | H67: Səhifə: son (max) | I67: 1. Son səhifədə ən azı 1 kart var 2. "İrəli" düyməsi yoxdur və ya deaktivdir | J67: TS_UI_10 | K67: Nəticə prod-da dinamik dəyişən data-dan (stok, sifariş tarixçəsi, məhsul sayı) asılıdır → avtomatlaşdırma flaky olar → manual. | L67: Not Run | M67: Manual | N67: No
A68: TC_PLP_POS_016 | B68: "Daha çox göstər" düyməsi əvvəlki kartları saxlayaraq əlavə kartlar yükləyir | C68: Məhsul siyahısı → Daha çox göstər | D68: P3 - Medium | E68: Pozitiv | F68: 1. Brauzer: Google Chrome (son stabil versiya), incognito rejim (cookies/cache təmizdir) 2. İstifadəçi login olmayıb (Guest) 3. Dil: AZ, Şəhər: Bakı (default) 4. Kateqoriya səhifəsi açıqdır: https://birmarket.az/categories/2-telefonlar-ve-aksessuarlar | G68: 1. Kart sayını qeyd et 2. "Daha çox göstər" düyməsinə klik et 3. Kart sayını və ilk kartı yoxla | H68: — | I68: 1. Kart sayı artır 2. İlk kart dəyişmir (əvvəlkilər silinmir) | J68: TS_UI_10 | K68: Lazy-load/async yükləmə; funksional olaraq pagination ilə əhatə olunur → manual. | L68: Not Run | M68: Manual | N68: No
A69: TC_PLP_POS_017 | B69: "Endirimli" sürətli filtri tətbiq edildikdə yalnız endirimli məhsullar göstərilir | C69: Məhsul siyahısı → Endirimli filtri | D69: P2 - High | E69: Pozitiv | F69: 1. Brauzer: Google Chrome (son stabil versiya), incognito rejim (cookies/cache təmizdir) 2. İstifadəçi login olmayıb (Guest) 3. Dil: AZ, Şəhər: Bakı (default) 4. Alt kateqoriya səhifəsi açıqdır: https://birmarket.az/categories/3-mobil-telefonlar-ve-smartfonlar | G69: 1. Filtrlər bölməsində "Endirimli" seçimini aktiv et 2. Siyahının yenilənməsini gözlə 3. İlk 20 kartı yoxla | H69: Filtr: Endirimli | I69: Hər kartda: endirim nişanı ("-X %") var VƏ köhnə qiymət > yeni qiymət | J69: TS_UI_10 | K69: İnvariant yoxlaması (endirim nişanı + qiymət müqayisəsi); hardcode yoxdur → stabil, avtomatlaşdırılır. | L69: Pass | M69: Automated | N69: Yes | O69: Gözlənilən nəticə ilə üst-üstə düşür. Gauge avtomat run (Chrome 154, guest): PASS. | P69: 06.10.2026 | Q69: Avtomat (Gauge + Selenium)
A70: TC_PLP_POS_018 | B70: "Endirimli" və brend filtri birlikdə tətbiq edildikdə hər iki şərtə uyğun məhsullar göstərilir | C70: Məhsul siyahısı → Kombinə filtr | D70: P3 - Medium | E70: Pozitiv, Decision Table | F70: 1. Brauzer: Google Chrome (son stabil versiya), incognito rejim (cookies/cache təmizdir) 2. İstifadəçi login olmayıb (Guest) 3. Dil: AZ, Şəhər: Bakı (default) 4. Alt kateqoriya səhifəsi açıqdır: https://birmarket.az/categories/3-mobil-telefonlar-ve-smartfonlar | G70: 1. "Endirimli" seçimini aktiv et 2. "Brend" bölməsindən brendi seç 3. Bütün kartları yoxla | H70: Filtr: Endirimli + Brend: Samsung | I70: Hər kart üçün: ad "Samsung" ehtiva edir VƏ endirim nişanı var; və ya nəticə yoxdursa boş nəticə mesajı göstərilir | J70: TS_UI_10 | K70: Decision Table halı; aşağı prioritetdir və TC_PLP_POS_009 kombinə filtri artıq avtomat əhatə edir → manual. | L70: Not Run | M70: Manual | N70: No
A71: TC_PLP_POS_019 | B71: "Rəsmi satıcı" sürətli filtri yalnız rəsmi satıcıların məhsullarını göstərir | C71: Məhsul siyahısı → Rəsmi satıcı filtri | D71: P3 - Medium | E71: Pozitiv | F71: 1. Brauzer: Google Chrome (son stabil versiya), incognito rejim (cookies/cache təmizdir) 2. İstifadəçi login olmayıb (Guest) 3. Dil: AZ, Şəhər: Bakı (default) 4. Alt kateqoriya səhifəsi açıqdır: https://birmarket.az/categories/3-mobil-telefonlar-ve-smartfonlar | G71: 1. "Rəsmi satıcı" seçimini aktiv et 2. İlk 5 kartın PDP-sini aç və satıcı məlumatını yoxla | H71: Filtr: Rəsmi satıcı | I71: Hər yoxlanılan məhsulun satıcısı "rəsmi satıcı" nişanı/statusu ilə göstərilir | J71: TS_UI_10 | K71: Rəsmi satıcı statusu kartda görünmür, hər PDP-ni açmaq tələb edir — yavaş və satıcı siyahısı dəyişkəndir → manual. | L71: Not Run | M71: Manual | N71: No
A72: TC_PLP_POS_020 | B72: Xüsusiyyət filtri (Daxili yaddaş həcmi = 256 GB) tətbiq edildikdə uyğun məhsullar göstərilir | C72: Məhsul siyahısı → Xüsusiyyət filtri | D72: P3 - Medium | E72: Pozitiv, EP | F72: 1. Brauzer: Google Chrome (son stabil versiya), incognito rejim (cookies/cache təmizdir) 2. İstifadəçi login olmayıb (Guest) 3. Dil: AZ, Şəhər: Bakı (default) 4. Alt kateqoriya səhifəsi açıqdır: https://birmarket.az/categories/3-mobil-telefonlar-ve-smartfonlar | G72: 1. "Daxili yaddaş həcmi" bölməsini aç ("Hamısını göstər") 2. Dəyəri seç 3. İlk 5 kartın PDP-sində xüsusiyyətləri yoxla | H72: Daxili yaddaş: 256 GB | I72: Yoxlanılan hər məhsulun daxili yaddaşı 256 GB-dır | J72: TS_UI_10 | K72: Məhsul adları standart deyil ("256GB", "256 GB", adda olmaya bilər) — avtomat assertion flaky olar → manual. | L72: Not Run | M72: Manual | N72: No
A73: TC_PLP_POS_022 | B73: Sıralama seçicisində 5 ümumi seçim göstərilir | C73: Məhsul siyahısı → Sıralama seçimləri | D73: P2 - High | E73: Pozitiv | F73: 1. Brauzer: Google Chrome (son stabil versiya), incognito rejim (cookies/cache təmizdir) 2. İstifadəçi login olmayıb (Guest) 3. Dil: AZ, Şəhər: Bakı (default) 4. Alt kateqoriya səhifəsi açıqdır: https://birmarket.az/categories/3-mobil-telefonlar-ve-smartfonlar | G73: 1. Sıralama seçicisinə klik et 2. Seçimlərin siyahısını oxu | H73: Gözlənilən: Ən ucuz, Ən bahalı, Populyar, Yüksək reytinq, Ən böyük endirimli, Yeniliklər | I73: Sıralama dropdown-unda 5 seçim göstərilir (saytda təsdiqlənib; ilkin fərziyyə 6 idi) | J73: TS_UI_10 | K73: Seçimlər bütün kateqoriyalarda ortaqdır (təsdiqlənib); deterministik → avtomatlaşdırılır. | L73: Pass | M73: Automated | N73: Yes | O73: Sıralama dropdown-unda 5 seçim göstərilir (ilkin fərziyyədə 6 idi — Expected Result saytın faktiki davranışına görə yeniləndi). PASS. | P73: 06.10.2026 | Q73: Avtomat (Gauge + Selenium)
A74: TC_PLP_POS_023 | B74: "Ən böyük endirimli" sıralandıqda endirim faizləri artmayan ardıcıllıqla göstərilir | C74: Məhsul siyahısı → Sıralama | D74: P2 - High | E74: Pozitiv | F74: 1. Brauzer: Google Chrome (son stabil versiya), incognito rejim (cookies/cache təmizdir) 2. İstifadəçi login olmayıb (Guest) 3. Dil: AZ, Şəhər: Bakı (default) 4. Alt kateqoriya səhifəsi açıqdır: https://birmarket.az/categories/3-mobil-telefonlar-ve-smartfonlar | G74: 1. Sıralama seçicisindən "Ən böyük endirimli"-ni seç 2. Siyahının yenilənməsini gözlə 3. İlk 20 kartın endirim faizini ("-X %") oxu | H74: Sıralama: Ən böyük endirimli | I74: 1. İlk kartda endirim nişanı var 2. Hər qonşu cüt üçün: endirim[i] ≥ endirim[i+1] (nişanı olmayan kartlar 0% sayılır və sonda gəlir) | J74: TS_UI_10 | K74: Sıralama seçimi saytda təsdiqlənib; konkret qiymət yox, sıralama invariantı yoxlanılır → data dəyişsə də stabil, avtomatlaşdırılır. | L74: Pass | M74: Automated | N74: Yes | O74: Gözlənilən nəticə ilə üst-üstə düşür. Gauge avtomat run (Chrome 154, guest): PASS. | P74: 06.10.2026 | Q74: Avtomat (Gauge + Selenium)
A75: TC_PLP_POS_024 | B75: "Ən ucuz" sıralama 2-ci səhifədə də davam edir | C75: Məhsul siyahısı → Sıralama + Pagination | D75: P2 - High | E75: Pozitiv | F75: 1. Brauzer: Google Chrome (son stabil versiya), incognito rejim (cookies/cache təmizdir) 2. İstifadəçi login olmayıb (Guest) 3. Dil: AZ, Şəhər: Bakı (default) 4. Alt kateqoriya səhifəsi açıqdır: https://birmarket.az/categories/3-mobil-telefonlar-ve-smartfonlar | G75: 1. "Ən ucuz" sıralamanı seç 2. 1-ci səhifənin sonuncu kartının qiymətini oxu 3. 2-ci səhifəyə keç 4. URL-i və 2-ci səhifənin ilk kartının qiymətini oxu | H75: Sıralama: Ən ucuz Səhifə: 2 | I75: 1. URL-də sıralama parametri saxlanılır 2. 2-ci səhifənin ilk qiyməti ≥ 1-ci səhifənin son qiyməti | J75: TS_UI_10 | K75: Sıralama seçimi saytda təsdiqlənib; konkret qiymət yox, sıralama invariantı yoxlanılır → data dəyişsə də stabil, avtomatlaşdırılır. | L75: Pass | M75: Automated | N75: Yes | O75: 2-ci səhifədə "Ən ucuz" sıralaması saxlanılır, qiymətlər artan sıradadır. PASS. | P75: 06.10.2026 | Q75: Avtomat (Gauge + Selenium)
A76: TC_PLP_POS_025 | B76: Sıralama və brend filtri birlikdə tətbiq edildikdə hər iki şərt qorunur | C76: Məhsul siyahısı → Sıralama + Filtr | D76: P2 - High | E76: Pozitiv, Decision Table | F76: 1. Brauzer: Google Chrome (son stabil versiya), incognito rejim (cookies/cache təmizdir) 2. İstifadəçi login olmayıb (Guest) 3. Dil: AZ, Şəhər: Bakı (default) 4. Alt kateqoriya səhifəsi açıqdır: https://birmarket.az/categories/3-mobil-telefonlar-ve-smartfonlar | G76: 1. "Brend" bölməsindən brendi seç 2. "Ən bahalı" sıralamanı seç 3. İlk 20 kartın adını və qiymətini oxu | H76: Brend: Samsung Sıralama: Ən bahalı | I76: 1. Hər kartın adı "Samsung" ehtiva edir 2. Hər qonşu cüt üçün qiymət[i] ≥ qiymət[i+1] 3. Sıralama seçildikdən sonra filtr ləğv olunmur | J76: TS_UI_10 | K76: Sıralama seçimi saytda təsdiqlənib; konkret qiymət yox, sıralama invariantı yoxlanılır → data dəyişsə də stabil, avtomatlaşdırılır. | Avtomatlaşdırma cəhdindən sonra Manual-a keçirildi: Brend filtri siyahısı dinamikdir, locator toplanmayıb. | L76: Not Run | M76: Manual | N76: Yes (Manual)
A77: TC_PLP_POS_026 | B77: "Yüksək reytinq" sıralamada reytinqi yüksək məhsullar əvvəldə göstərilir | C77: Məhsul siyahısı → Sıralama | D77: P3 - Medium | E77: Pozitiv | F77: 1. Brauzer: Google Chrome (son stabil versiya), incognito rejim (cookies/cache təmizdir) 2. İstifadəçi login olmayıb (Guest) 3. Dil: AZ, Şəhər: Bakı (default) 4. Alt kateqoriya səhifəsi açıqdır: https://birmarket.az/categories/3-mobil-telefonlar-ve-smartfonlar | G77: 1. "Yüksək reytinq"-i seç 2. İlk 20 kartın reytinqini və rəy sayını oxu | H77: Sıralama: Yüksək reytinq | I77: Reytinqlər əsasən azalan sıradadır; reytinqi olmayan kartlar sonda gəlir (sıralama meyarı — GQ_UI_22) | J77: TS_UI_10 | K77: Sıralama yalnız reytinqə yox, rəy sayına da əsaslana bilər (meyar bilinmir) → sərt assertion flaky olar → manual. | L77: Not Run | M77: Manual | N77: No
A78: TC_PLP_POS_027 | B78: "Yeniliklər" sıralamada "Yenilik" nişanlı məhsullar əvvəldə göstərilir | C78: Məhsul siyahısı → Sıralama | D78: P3 - Medium | E78: Pozitiv | F78: 1. Brauzer: Google Chrome (son stabil versiya), incognito rejim (cookies/cache təmizdir) 2. İstifadəçi login olmayıb (Guest) 3. Dil: AZ, Şəhər: Bakı (default) 4. Alt kateqoriya səhifəsi açıqdır: https://birmarket.az/categories/3-mobil-telefonlar-ve-smartfonlar | G78: 1. "Yeniliklər"-i seç 2. İlk 10 kartda "Yenilik" nişanını yoxla | H78: Sıralama: Yeniliklər | I78: İlk kartlarda "Yenilik" nişanı var (əlavə olunma tarixinə görə sıralama — GQ_UI_22) | J78: TS_UI_10 | K78: Əlavə olunma tarixi UI-da görünmür, nişan hər məhsulda olmaya bilər → manual. | L78: Not Run | M78: Manual | N78: No
A79: TC_PLP_POS_028 | B79: Kateqoriya açıldıqda default sıralama seçimi göstərilir | C79: Məhsul siyahısı → Default sıralama | D79: P3 - Medium | E79: Pozitiv | F79: 1. Brauzer: Google Chrome (son stabil versiya), incognito rejim (cookies/cache təmizdir) 2. İstifadəçi login olmayıb (Guest) 3. Dil: AZ, Şəhər: Bakı (default) 4. Alt kateqoriya səhifəsi açıqdır: https://birmarket.az/categories/3-mobil-telefonlar-ve-smartfonlar | G79: 1. Sıralama seçicisində seçilmiş dəyəri oxu | H79: — | I79: Default olaraq "Populyar" seçilib (GQ_UI_23) | J79: TS_UI_10 | K79: Gözlənilən davranış tələbdə müəyyən deyil (Grooming Questions sheet-ə bax). Cavab gəlməyənə qədər manual; təsdiqdən sonra avtomatlaşdırma namizədidir. | L79: Not Run | M79: Manual | N79: No
A80: TC_PLP_POS_029 | B80: Filtr paneli kateqoriyaya uyğun dəyişir, sıralama seçimləri isə eyni qalır | C80: Məhsul siyahısı → Kateqoriyaya görə filtrlər | D80: P3 - Medium | E80: Pozitiv | F80: 1. Brauzer: Google Chrome (son stabil versiya), incognito rejim (cookies/cache təmizdir) 2. İstifadəçi login olmayıb (Guest) 3. Dil: AZ, Şəhər: Bakı (default) 4. Alt kateqoriya səhifəsi açıqdır: https://birmarket.az/categories/3-mobil-telefonlar-ve-smartfonlar | G80: 1. Filtr bölmələrinin adlarını qeyd et 2. "Məişət texnikası" kateqoriyasına keç 3. Filtr bölmələrini və sıralama seçimlərini müqayisə et | H80: Kateqoriya 1: Mobil telefonlar və smartfonlar Kateqoriya 2: Məişət texnikası | I80: 1. Telefonlara xas filtrlər (məs. "Əməliyyat sistemi", "SİM kartların sayı") 2-ci kateqoriyada göstərilmir 2. "Qiyməti" və "Brend" hər iki kateqoriyada var 3. Sıralama seçimləri eynidir: Ən ucuz, Ən bahalı, Populyar, Yüksək reytinq, Ən böyük endirimli, Yeniliklər | J80: TS_UI_10 | K80: Filtr adları kateqoriyalar üzrə dinamikdir və tez-tez dəyişir → manual. | L80: Not Run | M80: Manual | N80: No
A81: TC_PLP_UI_021 | B81: Filtr bölməsində "Hamısını göstər" linki bütün dəyərləri açır | C81: Məhsul siyahısı → Hamısını göstər | D81: P4 - Low | E81: UI | F81: 1. Brauzer: Google Chrome (son stabil versiya), incognito rejim (cookies/cache təmizdir) 2. İstifadəçi login olmayıb (Guest) 3. Dil: AZ, Şəhər: Bakı (default) 4. Alt kateqoriya səhifəsi açıqdır: https://birmarket.az/categories/3-mobil-telefonlar-ve-smartfonlar | G81: 1. "Brend" bölməsində görünən dəyər sayını qeyd et 2. "Hamısını göstər"-ə klik et 3. Dəyər sayını yenidən yoxla | H81: Bölmə: Brend | I81: Göstərilən brend sayı artır, əlavə brendlər görünür | J81: TS_UI_10 | K81: Aşağı riskli, nadir dəyişən funksionallıq; regression ROI aşağıdır → manual. | L81: Not Run | M81: Manual | N81: No
A82: TC_PDP_NEG_005 | B82: Mövcud olmayan məhsul URL-i açıldıqda 404 səhifəsi göstərilir | C82: Məhsul detalı → Yanlış URL | D82: P3 - Medium | E82: Neqativ | F82: 1. Brauzer: Google Chrome (son stabil versiya), incognito rejim (cookies/cache təmizdir) 2. İstifadəçi login olmayıb (Guest) 3. Dil: AZ, Şəhər: Bakı (default) | G82: 1. Brauzerdə test URL-ni aç 2. Səhifəni müşahidə et | H82: URL: https://birmarket.az/product/999999999-movcud-olmayan-mehsul | I82: 1. Başlıq: "Səhifə tapılmadı" 2. Mətn: "Əfsuslar olsun ki belə səhifə yoxdur və ya ünvan yanlışdır" 3. 500 xətası yoxdur | J82: TS_UI_11 | K82: Davranış saytda təsdiqlənib; deterministik nəticə, SMS/login tələb etmir → avtomatlaşdırılır. | L82: Pass | M82: Automated | N82: Yes | O82: Gözlənilən nəticə ilə üst-üstə düşür. Gauge avtomat run (Chrome 154, guest): PASS. | P82: 06.10.2026 | Q82: Avtomat (Gauge + Selenium)
A83: TC_PDP_NEG_012 | B83: Guest istifadəçi məhsula rəy yazmağa cəhd etdikdə giriş tələb olunur | C83: Məhsul detalı → Rəy (Guest) | D83: P3 - Medium | E83: Neqativ | F83: 1. Brauzer: Google Chrome (son stabil versiya), incognito rejim (cookies/cache təmizdir) 2. İstifadəçi login olmayıb (Guest) 3. Dil: AZ, Şəhər: Bakı (default) 4. Kateqoriya səhifəsi açıqdır: https://birmarket.az/categories/2-telefonlar-ve-aksessuarlar 5. Məhsul seçim qaydası: kateqoriyada stokda olan ilk məhsul kartı (qiymət/ad hardcode edilmir) — PDP açıqdır | G83: 1. Rəylər bölməsinə keç 2. "Rəy yaz" düyməsinə klik et | H83: — | I83: Giriş ekranı açılır və ya rəy yazmaq üçün login tələb olunduğu bildirilir (GQ_UI_19) | J83: TS_UI_11 | K83: Gözlənilən davranış tələbdə müəyyən deyil (Grooming Questions sheet-ə bax). Cavab gəlməyənə qədər manual; təsdiqdən sonra avtomatlaşdırma namizədidir. | L83: Not Run | M83: Manual | N83: No
A84: TC_PDP_POS_001 | B84: Məhsul kartından açılan PDP-də ad və qiymət kartdakı ilə eynidir | C84: Məhsul detalı → Kartdan keçid | D84: P1 - Critical | E84: Pozitiv, Smoke | F84: 1. Brauzer: Google Chrome (son stabil versiya), incognito rejim (cookies/cache təmizdir) 2. İstifadəçi login olmayıb (Guest) 3. Dil: AZ, Şəhər: Bakı (default) 4. Kateqoriya səhifəsi açıqdır: https://birmarket.az/categories/2-telefonlar-ve-aksessuarlar | G84: 1. İlk məhsul kartının adını və qiymətini qeyd et 2. Karta klik et 3. PDP-də məhsul adını və qiymətini oxu | H84: Məhsul seçim qaydası: kateqoriyada stokda olan ilk məhsul kartı (qiymət/ad hardcode edilmir) | I84: 1. URL "/product/" ehtiva edir 2. PDP-dəki ad = kartdakı ad 3. PDP-dəki qiymət = kartdakı qiymət | J84: TS_UI_11 | K84: Dəyərlər bir-biri ilə müqayisə olunur (hardcode yoxdur); kart↔PDP uyğunsuzluğu kritik biznes bug-dır → avtomatlaşdırılır. | L84: Pass | M84: Automated | N84: Yes | O84: Kartdakı ad və qiymət PDP-dəki ilə eynidir (məs. "Yağ qızdırıcısı Hausberg PH9865", 169.88 ₼). PASS. | P84: 06.10.2026 | Q84: Avtomat (Gauge + Selenium)
A85: TC_PDP_POS_002 | B85: PDP-də əsas elementlər göstərilir və qiymət formatı düzgündür | C85: Məhsul detalı → Elementlər | D85: P2 - High | E85: Pozitiv | F85: 1. Brauzer: Google Chrome (son stabil versiya), incognito rejim (cookies/cache təmizdir) 2. İstifadəçi login olmayıb (Guest) 3. Dil: AZ, Şəhər: Bakı (default) 4. Kateqoriya səhifəsi açıqdır: https://birmarket.az/categories/2-telefonlar-ve-aksessuarlar 5. Məhsul seçim qaydası: kateqoriyada stokda olan ilk məhsul kartı (qiymət/ad hardcode edilmir) — PDP açılıb | G85: 1. Məhsul şəklini yoxla 2. Məhsul adını yoxla 3. Qiyməti və formatını yoxla 4. "Səbətə əlavə et" düyməsini yoxla | H85: Qiymət formatı regex: ^\d+(\.\d{2})? ₼$ | I85: 1. Əsas məhsul şəkli yüklənib (boş/sınıq deyil) 2. Ad boş deyil 3. Qiymət iki onluq rəqəm və "₼" ilə göstərilir 4. "Səbətə əlavə et" düyməsi görünür və aktivdir | J85: TS_UI_11 | K85: Regression-a daxildir, hər release-də təkrarlanır; nəticə data-dan asılı olmayan invariantla yoxlanır (hardcode qiymət/ad yoxdur); xarici asılılıq yoxdur → avtomatlaşdırılır. | L85: Pass | M85: Automated | N85: Yes | O85: Gözlənilən nəticə ilə üst-üstə düşür. Gauge avtomat run (Chrome 154, guest): PASS. | P85: 06.10.2026 | Q85: Avtomat (Gauge + Selenium)
A86: TC_PDP_POS_004 | B86: PDP-də kredit seçimində 6/12/18/24 ay müddətləri təklif olunur və hər biri üçün aylıq məbləğ göstərilir | C86: Məhsul detalı → Taksit hesablaması | D86: P2 - High | E86: Pozitiv | F86: 1. Brauzer: Google Chrome (son stabil versiya), incognito rejim (cookies/cache təmizdir) 2. İstifadəçi login olmayıb (Guest) 3. Dil: AZ, Şəhər: Bakı (default) 4. Kateqoriya səhifəsi açıqdır: https://birmarket.az/categories/2-telefonlar-ve-aksessuarlar 5. Taksit seçimi olan məhsulun PDP-si açıqdır | G86: 1. Məhsul qiymətini oxu 2. Kreditlə alma seçiminə klik et 3. Təklif olunan müddətləri oxu 4. Hər müddəti ardıcıl seç və aylıq məbləği qeyd et | H86: Müddətlər: 6, 12, 18, 24 ay | I86: 1. Dəqiq 4 müddət təklif olunur: 6, 12, 18, 24 ay 2. Hər müddət seçildikdə aylıq məbləğ yenilənir 3. Aylıq məbləğ "₼" ilə, 2 onluq rəqəmlə göstərilir (Dəqiq faiz/formula — GQ_UI_10) | J86: TS_UI_11 | K86: Gözlənilən davranış tələbdə müəyyən deyil (Grooming Questions sheet-ə bax). Cavab gəlməyənə qədər manual; təsdiqdən sonra avtomatlaşdırma namizədidir. | L86: Not Run | M86: Manual | N86: No
A87: TC_PDP_POS_006 | B87: Stokda olmayan məhsulun PDP-sində səbətə əlavə etmək mümkün deyil | C87: Məhsul detalı → Stokda yoxdur | D87: P2 - High | E87: Neqativ | F87: 1. Brauzer: Google Chrome (son stabil versiya), incognito rejim (cookies/cache təmizdir) 2. İstifadəçi login olmayıb (Guest) 3. Dil: AZ, Şəhər: Bakı (default) 4. Stokda olmayan məhsulun PDP-si açıqdır (manual tapılır) | G87: 1. Stok məlumatını yoxla 2. "Səbətə əlavə et" düyməsinin vəziyyətini yoxla | H87: — | I87: 1. "Stokda yoxdur" tipli məlumat göstərilir 2. "Səbətə əlavə et" düyməsi yoxdur və ya deaktivdir | J87: TS_UI_11 | K87: Nəticə prod-da dinamik dəyişən data-dan (stok, sifariş tarixçəsi, məhsul sayı) asılıdır → avtomatlaşdırma flaky olar → manual. | L87: Not Run | M87: Manual | N87: No
A88: TC_PDP_POS_007 | B88: Məhsul variantı (rəng/yaddaş) dəyişdirildikdə qiymət və məlumatlar yenilənir | C88: Məhsul detalı → Variant seçimi | D88: P2 - High | E88: Pozitiv | F88: 1. Brauzer: Google Chrome (son stabil versiya), incognito rejim (cookies/cache təmizdir) 2. İstifadəçi login olmayıb (Guest) 3. Dil: AZ, Şəhər: Bakı (default) 4. Bir neçə variantı olan smartfonun PDP-si açıqdır | G88: 1. Cari qiyməti və variantı qeyd et 2. Fərqli yaddaş variantını seç 3. Qiyməti, adı və URL-i yoxla | H88: Variant: fərqli yaddaş həcmi | I88: 1. Seçilmiş variant aktiv göstərilir 2. Ad/URL yeni variantı əks etdirir 3. Qiymət seçilmiş variantın qiymətidir | J88: TS_UI_11 | K88: Nəticə prod-da dinamik dəyişən data-dan (stok, sifariş tarixçəsi, məhsul sayı) asılıdır → avtomatlaşdırma flaky olar → manual. | L88: Not Run | M88: Manual | N88: No
A89: TC_PDP_POS_008 | B89: PDP-də məhsulun satıcısının adı göstərilir | C89: Məhsul detalı → Satıcı | D89: P3 - Medium | E89: Pozitiv | F89: 1. Brauzer: Google Chrome (son stabil versiya), incognito rejim (cookies/cache təmizdir) 2. İstifadəçi login olmayıb (Guest) 3. Dil: AZ, Şəhər: Bakı (default) 4. Kateqoriya səhifəsi açıqdır: https://birmarket.az/categories/2-telefonlar-ve-aksessuarlar 5. Məhsul seçim qaydası: kateqoriyada stokda olan ilk məhsul kartı (qiymət/ad hardcode edilmir) — PDP açıqdır | G89: 1. PDP-də satıcı bölməsini tap 2. Satıcı adını oxu | H89: — | I89: 1. Satıcı adı boş deyil 2. Satıcı adı mətn kimi göstərilir (link deyil) | J89: TS_UI_11 | K89: Məlumat xarakterli, aşağı riskli element → manual. | L89: Not Run | M89: Manual | N89: No
A90: TC_PDP_POS_009 | B90: PDP-də çatdırılma tarixi/müddəti barədə məlumat göstərilir | C90: Məhsul detalı → Çatdırılma məlumatı | D90: P3 - Medium | E90: Pozitiv | F90: 1. Brauzer: Google Chrome (son stabil versiya), incognito rejim (cookies/cache təmizdir) 2. İstifadəçi login olmayıb (Guest) 3. Dil: AZ, Şəhər: Bakı (default) 4. Kateqoriya səhifəsi açıqdır: https://birmarket.az/categories/2-telefonlar-ve-aksessuarlar 5. Məhsul seçim qaydası: kateqoriyada stokda olan ilk məhsul kartı (qiymət/ad hardcode edilmir) — PDP açıqdır | G90: 1. Çatdırılma bölməsini tap 2. Məlumatı oxu | H90: — | I90: Çatdırılma tarixi və ya müddəti (məs. "Sabah") göstərilir | J90: TS_UI_11 | K90: Nəticə prod-da dinamik dəyişən data-dan (stok, sifariş tarixçəsi, məhsul sayı) asılıdır → avtomatlaşdırma flaky olar → manual. | L90: Not Run | M90: Manual | N90: No
A91: TC_PDP_POS_010 | B91: Məhsul səbətə əlavə edildikdən sonra PDP-də düymə "səbətdə" vəziyyətinə keçir | C91: Məhsul detalı → Düymə vəziyyəti | D91: P2 - High | E91: Pozitiv, State Transition | F91: 1. Brauzer: Google Chrome (son stabil versiya), incognito rejim (cookies/cache təmizdir) 2. İstifadəçi login olmayıb (Guest) 3. Dil: AZ, Şəhər: Bakı (default) 4. Səbət boşdur (header-də səbət sayğacı göstərilmir) 5. Məhsul seçim qaydası: kateqoriyada stokda olan ilk məhsul kartı (qiymət/ad hardcode edilmir) — PDP açıqdır | G91: 1. "Səbətə əlavə et" düyməsinə klik et 2. Düymənin yeni vəziyyətini yoxla 3. Səhifəni yenilə, düyməni yenidən yoxla | H91: — | I91: 1. Düymə yaşıl rəngdə "Səbətdə" mətni ilə göstərilir 2. Səhifə yeniləndikdən sonra da "Səbətdə" vəziyyəti qalır | J91: TS_UI_11 | K91: Regression-a daxildir, hər release-də təkrarlanır; nəticə data-dan asılı olmayan invariantla yoxlanır (hardcode qiymət/ad yoxdur); xarici asılılıq yoxdur → avtomatlaşdırılır. | Avtomatlaşdırılıb və 06.10.2026-da PASS olub, lakin təkrar full run-larda flaky çıxdı: production-da "Səbətə əlavə et" server tərəfində qonaq səbəti yaradır, ardıcıl run-larda nəticə deterministik deyil (rate-limit). Flaky test qəbul olunmadığı üçün Manual regression-a keçirildi (K2, K6). | L91: Pass | M91: Manual | N91: Yes (Manual) | O91: Səbətə əlavədən sonra header səbət sayğacı "1" oldu, PDP düyməsi "Səbətə keçmək" vəziyyətinə keçdi. — Avtomat run-da PASS (06.10.2026); təkrar run-larda flaky olduğu üçün Manual regression-a keçirildi. | P91: 06.10.2026 | Q91: Avtomat → Manual regression
A92: TC_PDP_POS_011 | B92: PDP breadcrumb-u məhsulun kateqoriyasını göstərir və kateqoriyaya keçid verir | C92: Məhsul detalı → Breadcrumb | D92: P3 - Medium | E92: Pozitiv | F92: 1. Brauzer: Google Chrome (son stabil versiya), incognito rejim (cookies/cache təmizdir) 2. İstifadəçi login olmayıb (Guest) 3. Dil: AZ, Şəhər: Bakı (default) 4. Kateqoriya səhifəsi açıqdır: https://birmarket.az/categories/2-telefonlar-ve-aksessuarlar 5. Məhsul seçim qaydası: kateqoriyada stokda olan ilk məhsul kartı (qiymət/ad hardcode edilmir) — PDP açıqdır | G92: 1. Breadcrumb-u oxu 2. Sonuncu kateqoriya linkinə klik et | H92: — | I92: 1. Breadcrumb məhsulun aid olduğu kateqoriyanı göstərir 2. Klik həmin kateqoriya səhifəsini açır | J92: TS_UI_11 | K92: Aşağı riskli, nadir dəyişən funksionallıq; regression ROI aşağıdır → manual. | L92: Not Run | M92: Manual | N92: No
A93: TC_PDP_POS_015 | B93: Kredit müddəti artdıqca aylıq ödəniş azalır | C93: Məhsul detalı → Kredit hesablaması | D93: P2 - High | E93: Pozitiv | F93: 1. Brauzer: Google Chrome (son stabil versiya), incognito rejim (cookies/cache təmizdir) 2. İstifadəçi login olmayıb (Guest) 3. Dil: AZ, Şəhər: Bakı (default) 4. Kateqoriya səhifəsi açıqdır: https://birmarket.az/categories/2-telefonlar-ve-aksessuarlar 5. Kredit seçimi olan məhsulun PDP-si açıqdır | G93: 1. Kreditlə alma seçiminə klik et 2. 6, 12, 18, 24 ay müddətlərini ardıcıl seç və aylıq məbləği qeyd et 3. Məbləğləri müqayisə et | H93: Müddətlər: 6, 12, 18, 24 ay | I93: aylıq(6) > aylıq(12) > aylıq(18) > aylıq(24) | J93: TS_UI_11 | K93: Biznes məntiqi invariantı (konkret faiz bilinmədən yoxlanılır); dəyərlər UI-dan oxunur → stabil, avtomatlaşdırılır. | L93: Pass | M93: Automated | N93: Yes | O93: 6 ay: 30.28 ₼ x 6, 24 ay: 8.71 ₼ x 24 — müddət artdıqca aylıq ödəniş azalır. PASS. | P93: 06.10.2026 | Q93: Avtomat (Gauge + Selenium)
A94: TC_PDP_POS_016 | B94: Hər kredit müddəti üçün ümumi ödəniş (aylıq × ay) məhsul qiymətindən az deyil | C94: Məhsul detalı → Kredit hesablaması | D94: P2 - High | E94: Pozitiv | F94: 1. Brauzer: Google Chrome (son stabil versiya), incognito rejim (cookies/cache təmizdir) 2. İstifadəçi login olmayıb (Guest) 3. Dil: AZ, Şəhər: Bakı (default) 4. Kateqoriya səhifəsi açıqdır: https://birmarket.az/categories/2-telefonlar-ve-aksessuarlar 5. Kredit seçimi olan məhsulun PDP-si açıqdır | G94: 1. Məhsul qiymətini oxu 2. Hər müddət üçün aylıq məbləği oxu 3. aylıq × ay hasilini hesabla və qiymətlə müqayisə et | H94: Müddətlər: 6, 12, 18, 24 ay | I94: Hər müddət üçün: aylıq × ay ≥ qiymət − 0.01 ₼ (yuvarlaqlaşdırma toleransı) | J94: TS_UI_11 | K94: Pul hesablamasında məntiqi invariant; faizdən asılı olmadan doğrudur → stabil, avtomatlaşdırılır. | Avtomatlaşdırma cəhdindən sonra Manual-a keçirildi: Kredit faizi/yuvarlaqlaşdırma dəyişkəndir; əsas yoxlama TC_PDP_POS_015 ilə avtomatdır. | L94: Not Run | M94: Manual | N94: Yes (Manual)
A95: TC_PDP_UI_003 | B95: PDP şəkil qalereyasında kiçik şəkilə klik əsas şəkli dəyişir | C95: Məhsul detalı → Şəkil qalereyası | D95: P3 - Medium | E95: UI | F95: 1. Brauzer: Google Chrome (son stabil versiya), incognito rejim (cookies/cache təmizdir) 2. İstifadəçi login olmayıb (Guest) 3. Dil: AZ, Şəhər: Bakı (default) 4. Kateqoriya səhifəsi açıqdır: https://birmarket.az/categories/2-telefonlar-ve-aksessuarlar 5. Ən azı 2 şəkli olan məhsulun PDP-si açıqdır | G95: 1. 2-ci kiçik şəkilə (thumbnail) klik et 2. Əsas şəkli müşahidə et 3. Əsas şəkilə klik et | H95: — | I95: 1. Əsas şəkil seçilmiş thumbnail ilə əvəz olunur 2. Əsas şəkilə klik böyüdülmüş görüntü açır | J95: TS_UI_11 | K95: Vizual/UX yoxlama insan qiyməti tələb edir, məzmun marketinq tərəfindən tez-tez dəyişir → avtomatlaşdırma flaky olar, ROI aşağıdır. | L95: Not Run | M95: Manual | N95: No
A96: TC_PDP_NEG_014 | B96: [Login] Məhsulu almamış istifadəçi həmin məhsula rəy yaza bilmir | C96: Məhsul detalı (Login) → Rəy | D96: P3 - Medium | E96: Neqativ | F96: 1. Brauzer: Google Chrome (son stabil versiya) 2. Test hesabı Birmarket-də qeydiyyatdadır, telefon nömrəsi SMS qəbul edir (test icraçısının əlindədir) 3. İstifadəçi həmin hesabla login olub (header-də "Şəxsi hesabım" görünür) 4. Hesab heç vaxt almadığı məhsulun PDP-si açıqdır | G96: 1. Rəylər bölməsinə keç 2. "Rəy yaz" düyməsinə klik et | H96: — | I96: Rəy yazmaq yalnız çatdırılmış məhsullar üçün mümkündür: "Rəy yazmaq" tabında yalnız çatdırılmış məhsullar siyahılanır, alınmamış məhsul üçün rəy forması açılmır | J96: TS_UI_12 | K96: OTP ilə login tələb edir (prod-da bypass yoxdur) → avtomatlaşdırıla bilmir. Biznes riski orta/aşağı olduğu üçün regression-a daxil edilmir. | L96: Pass | M96: Manual | N96: No | O96: "Rəy yazmaq" tabında "Çatdırılmış məhsul yoxdur" — alınmamış məhsula rəy yazmaq mümkün deyil (GQ_UI_19). PASS. | P96: 06.10.2026 | Q96: Manual (saytda yoxlanılıb)
A97: TC_PDP_POS_013 | B97: [Login] PDP-dən məhsul seçilmişlərə əlavə edildikdə ikon aktivləşir | C97: Məhsul detalı (Login) → Seçilmişlər | D97: P2 - High | E97: Pozitiv | F97: 1. Brauzer: Google Chrome (son stabil versiya) 2. Test hesabı Birmarket-də qeydiyyatdadır, telefon nömrəsi SMS qəbul edir (test icraçısının əlindədir) 3. İstifadəçi həmin hesabla login olub (header-də "Şəxsi hesabım" görünür) 4. Seçilmişlər boşdur 5. Məhsul seçim qaydası: kateqoriyada stokda olan ilk məhsul kartı (qiymət/ad hardcode edilmir) — PDP açıqdır | G97: 1. PDP-dəki ürək ikonuna klik et 2. İkonun vəziyyətini yoxla 3. Seçilmişlər səhifəsini aç | H97: — | I97: 1. İkon aktiv (doldurulmuş) olur 2. Məhsul Seçilmişlər səhifəsində görünür | J97: TS_UI_12 | K97: SMS OTP real telefon tələb edir, prod-da OTP bypass yoxdur, SMS limitləri var → stabil avtomatlaşdırmaq mümkün deyil. Biznes kritik olduğu üçün manual regression-a daxildir. | L97: Not Run | M97: Manual | N97: Yes (Manual)
A98: TC_CART_BVA_004 | B98: Miqdar minimum sərhəddə (1) olduqda "−" düyməsi miqdarı 0-a endirmir | C98: Səbət (Guest) → Miqdar alt sərhədi | D98: P2 - High | E98: Neqativ, BVA | F98: 1. Brauzer: Google Chrome (son stabil versiya), incognito rejim (cookies/cache təmizdir) 2. İstifadəçi login olmayıb (Guest) 3. Dil: AZ, Şəhər: Bakı (default) 4. Səbət boşdur (header-də səbət sayğacı göstərilmir) 5. Səbətdə 1 məhsul var (miqdar = 1), səbət səhifəsi açıqdır | G98: 1. "−" düyməsinin vəziyyətini yoxla 2. "−" düyməsinə klik et 3. Miqdarı oxu | H98: Miqdar: 1 (min) → cəhd: 0 (min−1) | I98: 1. "−" düyməsi deaktivdir (klik edilə bilmir) 2. Miqdar 1 olaraq qalır (0 və ya mənfi dəyər göstərilmir) | J98: TS_UI_13 | K98: Davranış saytda təsdiqlənib (GQ cavablanıb); deterministik nəticə, SMS/login tələb etmir → avtomatlaşdırılır. | Avtomatlaşdırılıb və 06.10.2026-da PASS olub, lakin təkrar full run-larda flaky çıxdı: production-da "Səbətə əlavə et" server tərəfində qonaq səbəti yaradır, ardıcıl run-larda nəticə deterministik deyil (rate-limit). Flaky test qəbul olunmadığı üçün Manual regression-a keçirildi (K2, K6). | L98: Pass | M98: Manual | N98: Yes (Manual) | O98: Gözlənilən nəticə ilə üst-üstə düşür. Gauge avtomat run (Chrome 154, guest): — Avtomat run-da PASS (06.10.2026); təkrar run-larda flaky olduğu üçün Manual regression-a keçirildi. | P98: 06.10.2026 | Q98: Avtomat → Manual regression
A99: TC_CART_BVA_005 | B99: Stokda 1 ədəd qalan məhsul üçün səbətdə miqdar dəyişdirilə bilmir | C99: Səbət (Guest) → Miqdar üst sərhədi | D99: P3 - Medium | E99: Neqativ, BVA | F99: 1. Brauzer: Google Chrome (son stabil versiya), incognito rejim (cookies/cache təmizdir) 2. İstifadəçi login olmayıb (Guest) 3. Dil: AZ, Şəhər: Bakı (default) 4. Səbət boşdur (header-də səbət sayğacı göstərilmir) 5. Stokda yalnız 1 ədəd qalan məhsul səbətdədir (manual tapılır) | G99: 1. "+" düyməsinin vəziyyətini yoxla və klik et 2. "−" düyməsinin vəziyyətini yoxla və klik et 3. Miqdarı oxu | H99: Stok: 1 (min = max = 1) | I99: 1. "+" və "−" düymələri deaktivdir 2. Miqdar 1 olaraq qalır | J99: TS_UI_13 | K99: Davranış təsdiqlənib, amma stoku 1 olan məhsul prod-da dinamikdir (satıla bilər) → avtomatlaşdırma flaky olar → manual. | L99: Pass | M99: Manual | N99: No | O99: Stokda 1 ədəd qalan məhsulda ("1 əd qalıb") "+" və "−" deaktivdir, miqdar 1 qalır (GQ_UI_06). PASS. | P99: 06.10.2026 | Q99: Manual (saytda yoxlanılıb)
A100: TC_CART_NEG_012 | B100: Səbətdə miqdar sahəsinə əl ilə 0 daxil edildikdə qəbul edilmir | C100: Səbət (Guest) → Miqdar daxiletmə | D100: P3 - Medium | E100: Neqativ, BVA | F100: 1. Brauzer: Google Chrome (son stabil versiya), incognito rejim (cookies/cache təmizdir) 2. İstifadəçi login olmayıb (Guest) 3. Dil: AZ, Şəhər: Bakı (default) 4. Səbət boşdur (header-də səbət sayğacı göstərilmir) 5. Səbətdə 1 məhsul var | G100: 1. Miqdar sahəsinə klik et (redaktə olunursa) 2. Dəyəri sil və test datanı yaz 3. Sahədən çıx | H100: Miqdar: 0 | I100: Miqdar 0 qəbul edilmir: dəyər 1-ə qaytarılır və ya silmə təsdiqi soruşulur (GQ_UI_05) | J100: TS_UI_13 | K100: Gözlənilən davranış tələbdə müəyyən deyil (Grooming Questions sheet-ə bax). Cavab gəlməyənə qədər manual; təsdiqdən sonra avtomatlaşdırma namizədidir. | L100: Not Run | M100: Manual | N100: No
...

Sheet Automation Strategy
A1: Automation Strategy — Manual vs Avtomat seçimi
A3: 1. Test case-in avtomatlaşdırılması üçün kriteriyalar (hamısı ödənməlidir)
A4: Kod | B4: Kriteriya | C4: İzah
A5: K1 | B5: Regression dəyəri | C5: Hər release-də təkrar icra olunur, P1/P2 biznes funksionallığıdır
A6: K2 | B6: Deterministik nəticə | C6: Assertion invarianta əsaslanır (sıralama, aralıq, cəm, uyğunluq), dəyişən prod data-ya (qiymət, stok, ad) hardcode edilmir
A7: K3 | B7: Xarici asılılıq yoxdur | C7: SMS/OTP, real ödəniş, e-poçt və s. tələb olunmur
A8: K4 | B8: Tələb aydındır | C8: Gözlənilən nəticə dəqiqdir (açıq Grooming Question yoxdur)
A9: K5 | B9: Stabil locator / UI | C9: Element animasiya, A/B test və ya marketinq kontentindən asılı deyil
A10: K6 | B10: Prod-a təhlükəsizdir | C10: Real sifariş, hesab, rəy və ya SMS yaratmır
A12: 2. Manual saxlanılma səbəbləri
A13: Səbəb | B13: Nümunə TC-lər | C13: İzah
A14: SMS OTP | B14: Başlığı [Login] ilə başlayan bütün TC-lər, TC_AUTH_POS_008…024, TC_REG_*, TC_PRF_*, TC_ORD_* | C14: Prod-da OTP bypass yoxdur; real SMS limitlidir. Biznes kritik olanlar "Yes (Manual)" ilə manual regression-dadır (GQ_UI_12)
A15: Qeyri-müəyyən tələb | B15: TC_SRCH_NEG_004, TC_PLP_NEG_004, TC_PLP_BVA_005/012, TC_FAV_NEG_001/003, TC_AUTH_NEG_007, TC_AUTH_EDGE_015 | C15: Gözlənilən nəticə təsdiqlənənə qədər avtomatlaşdırma yanlış assertion yaradar
A16: Vizual / UX | B16: TC_HOME_UI_003/007, TC_PDP_UI_003, TC_CAT_UI_007, TC_XBR_UI_001 | C16: İnsan qiymətləndirməsi tələb edir; marketinq kontenti dəyişkəndir
A17: Dinamik prod data | B17: TC_CART_BVA_005, TC_CHK_BVA_003/004, TC_PDP_POS_006/007, TC_ORD_POS_003 | C17: Stok və qiymətlər real vaxtda dəyişir → flaky risk
A18: Bir dəfəlik / aşağı risk | B18: TC_SRCH_EDGE_005, TC_SRCH_EDGE_007, TC_FTR_POS_001, TC_HOME_POS_002 | C18: Regression ROI aşağıdır
A19: Arxitektura məhdudiyyəti | B19: TC_XBR_UI_002 | C19: Verilmiş arxitektura tək brauzer üçündür, dəyişdirilə bilməz
A21: 3. Anti-flaky qaydalar (avtomatlaşdırılmış testlər üçün)
A22: Qayda | B22: Tətbiq | C22: Niyə
A23: Hardcode data yoxdur | B23: Qiymət və adlar UI-dan oxunub bir-biri ilə müqayisə olunur (kart↔PDP↔səbət) | C23: Prod data dəyişir, test yox
A24: Explicit wait | B24: Thread.sleep əvəzinə element/şərt gözləmələri (visibility, clickable, URL contains) | C24: Şəbəkə gecikməsi testi sındırmır
A25: Müstəqil testlər | B25: Hər test yeni brauzer sessiyası ilə, təmiz cookies, öz preconditions-ı ilə başlayır; test sırası önəmli deyil | C25: Bir testin FAIL-i digərini bloklamır
A26: Stabil test data | B26: Açar sözlər həmişə nəticə qaytaran ("iphone") və heç vaxt qaytarmayan ("qwxzqwxz123") seçilib; məhsul "stokda olan ilk kart" qaydası ilə seçilir | C26: Məhsul satışdan çıxsa da test işləyir
A27: Tolerans | B27: Faiz yuvarlaqlaşdırması ±1%, məbləğ cəmi 0.01 ₼ dəqiqliklə | C27: Yuvarlaqlaşdırma fərqi false FAIL yaratmır
A28: Retry ilə gizlətmə yoxdur | B28: FAIL olan test retry ilə "yaşıl" edilmir, səbəbi araşdırılır | C28: Flaky test real bug-ı gizlədir
A29: Stabillik sübutu | B29: Regression suite ardıcıl 3 dəfə run edilir, hamısı eyni nəticə verməlidir | C29: Exit kriteriyası
A31: 4. Avtomatlaşdırma nəticəsi (icra: 06.10.2026)
A32: Mövzu | B32: Dəyər | C32: Qeyd
A33: Framework | B33: Gauge 1.6 + Selenium 4 + Java 25 + Maven | C33: Verilmiş arxitektura: imp (step) → helper (məntiq) → locator JSON
A34: Spec faylları | B34: specs/ui-testing/birmarket/ — 10 spec + birmarket.cpt | C34: Modullara görə bölünüb (home, language, city, search, plp, pdp, cart, favorites, auth, account)
A35: Locator-lar | B35: src/test/resources/locator/birmarket-*.json — 7 fayl | C35: XPATH və ID; data-info atributlarına üstünlük verilib
A36: Əlavə kod | B36: BirmarketHelper.java + BirmarketImp.java | C36: Qiymət sıralaması, qiymət aralığı, rəqəm müqayisəsi, təkrar cəhdli klik
A37: Smoke run | B37: mvn test "-Dgauge.specs.dir=specs/ui-testing/birmarket" "-Dtags=smoke" | C37: 15/15 PASS (13 ssenari + data-driven account) — popup idarəsi əlavə olunduqdan sonra təkrar təsdiqləndi
A38: Full regression run | B38: mvn test "-Dgauge.specs.dir=specs/ui-testing/birmarket" | C38: 43/43 PASS — ardıcıl 3 run (06.10 23:58, 07.10 00:21, 07.10 12:44), ~11–12 dəq; prod data dəyişsə də (axtarış sayı 300→305, kateqoriyanın 1-ci məhsulu dəyişdi) stabil
A39: Manual-a keçirilən TC-lər | B39: 30 TC | C39: 22 TC stabil locator/prod data səbəbilə, 8 TC (səbətə əlavə) flaky olduğu üçün. Səbəb Test Cases → K sütununda
A41: 5. API avtomatlaşdırması (api.anarabbas.com)
A42: Mövzu | B42: Dəyər | C42: Qeyd
A43: Kriteriya | B43: P1/P2 + deterministik nəticə → avtomat regression; P3/P4 → manual (CallMan) | C43: 123 avtomat, 45 manual TC
A44: Spec faylları | B44: specs/api-testing/final-project/ — 11 spec + fp.cpt | C44: Hər task ayrıca spec; TC ID-ləri ssenari adındadır (traceability)
A45: Əlavə kod | B45: FinalProjectApiHelper.java + FinalProjectApiImp.java | C45: Boş body, kart expiry (Bakı vaxtı +3 il), alıcı body-si
A46: Contract | B46: src/test/resources/schema/fp-*.json — 6 JSON Schema | C46: Alıcı, alıcı siyahısı, kart, kataloq, ödəniş, tarixçə
A47: Data izolyasiyası | B47: Hər ssenaridən əvvəl yeni login → boş sandbox | C47: Testlər müstəqil, istənilən ardıcıllıqla işləyir
A48: Run əmri | B48: mvn test "-Dgauge.specs.dir=specs/api-testing/final-project" | C48: Smoke: "-Dtags=smoke"
A49: Nəticə (08.10.2026) | B49: Run 1: 123/123 PASS (4m12s) · Run 2: 100/123 — 23 düşmə server 500 səbəbindən (BUG_API_004) · Run 3: 123/123 PASS (2m55s) · Smoke: 10/10 PASS · 13.10.2026 (təhvil günü): 123/123 PASS (2m41s) | C49: Assertion səbəbli düşmə yoxdur
A51: 6. API avtomatlaşdırması — RestAssured + JUnit 5 + Allure (tapşırığın Mərhələ 4–5 tələbi)
A52: Mövzu | B52: Dəyər | C52: Qeyd
A53: Layihə | B53: final-project-api-restassured (ayrıca Maven layihəsi) | C53: Java + RestAssured 5.4 + JUnit 5 + Jackson + AssertJ + Allure 2.27
A54: POJO | B54: model/request (5) + model/response (13) | C54: Pul sahələri BigDecimal — float yuvarlaqlaşdırma xətası olmasın
A55: Base spec / token | B55: core/ApiSpec (base URL, UTF-8, Allure filter) · tests/BaseTest (@BeforeEach yeni login) | C55: Hər test təmiz sandbox-da
A56: Data-driven BVA | B56: @ParameterizedTest + @CsvSource | C56: fullName, IBAN, initialAmount, amount, Idempotency-Key, limit, page, tək/gündəlik limit, balans
A57: State transition | B57: CardStateTransitionTest — 13 sətirlik keçid cədvəli | C57: Hər sətir Allure-da ayrıca test
A58: Contract | B58: 6 JSON Schema (matchesJsonSchemaInClasspath) | C58: Gauge layihəsi ilə eyni schema-lar
A59: Allure | B59: @Epic → @Feature → @Story, @Severity, TC ID-li @DisplayName; Environment + Categories (5xx ayrıca) | C59: mvn allure:serve · single-file: allure generate --single-file
A60: Əhatə | B60: 130 / 168 TC (API_Test Cases → T sütunu) | C60: 80 test metodu → 166 icra
A61: Run əmri | B61: mvn clean test | C61: Hesabat: mvn allure:serve
A62: Nəticə (08.10.2026) | B62: Run 1: 166/166 PASS (2m52s) · Run 2: 166/166 PASS (2m48s) · 13.10.2026 (təhvil günü): 166/166 PASS (2m55s) | C62: 0 failure, 0 flaky

Sheet RTM
A1: Scenario ID | B1: Ssenari | C1: İstifadəçi növü | D1: Test Case ID-lər | E1: Cəmi TC | F1: Automated | G1: Manual | H1: Regression | I1: Passed | J1: Coverage Status
A2: TS_UI_01 | B2: Ana səhifə və header | C2: Guest | D2: TC_HOME_POS_001, TC_HOME_POS_002, TC_HOME_POS_006, TC_HOME_POS_009, TC_HOME_POS_010, TC_HOME_POS_011, TC_HOME_POS_012, TC_HOME_POS_013, TC_HOME_POS_014, TC_HOME_POS_015, TC_HOME_POS_016, TC_HOME_POS_017, TC_HOME_POS_018, TC_HOME_POS_019, TC_HOME_UI_003, TC_HOME_UI_007 | E2: =COUNTIF('Test Cases'!$J$2:$J$500,A2) -> 16 | F2: =COUNTIFS('Test Cases'!$J$2:$J$500,A2,'Test Cases'!$M$2:$M$500,"Automated") -> 2 | G2: =COUNTIFS('Test Cases'!$J$2:$J$500,A2,'Test Cases'!$M$2:$M$500,"Manual") -> 14 | H2: =COUNTIFS('Test Cases'!$J$2:$J$500,A2,'Test Cases'!$N$2:$N$500,"Yes*") -> 4 | I2: =COUNTIFS('Test Cases'!$J$2:$J$500,A2,'Test Cases'!$L$2:$L$500,"Pass") -> 5 | J2: =IF(E2=0,"Not Covered",IF(I2=E2,"Covered & Passed","Covered")) -> Covered
A3: TS_UI_02 | B3: Ana səhifə və header | C3: Login | D3: TC_HOME_POS_004, TC_HOME_POS_005 | E3: =COUNTIF('Test Cases'!$J$2:$J$500,A3) -> 2 | F3: =COUNTIFS('Test Cases'!$J$2:$J$500,A3,'Test Cases'!$M$2:$M$500,"Automated") -> 0 | G3: =COUNTIFS('Test Cases'!$J$2:$J$500,A3,'Test Cases'!$M$2:$M$500,"Manual") -> 2 | H3: =COUNTIFS('Test Cases'!$J$2:$J$500,A3,'Test Cases'!$N$2:$N$500,"Yes*") -> 2 | I3: =COUNTIFS('Test Cases'!$J$2:$J$500,A3,'Test Cases'!$L$2:$L$500,"Pass") -> 1 | J3: =IF(E3=0,"Not Covered",IF(I3=E3,"Covered & Passed","Covered")) -> Covered
A4: TS_UI_03 | B4: Dil seçimi (AZ / RU) | C4: Guest | D4: TC_LANG_POS_001, TC_LANG_POS_002, TC_LANG_POS_003, TC_LANG_POS_004 | E4: =COUNTIF('Test Cases'!$J$2:$J$500,A4) -> 4 | F4: =COUNTIFS('Test Cases'!$J$2:$J$500,A4,'Test Cases'!$M$2:$M$500,"Automated") -> 3 | G4: =COUNTIFS('Test Cases'!$J$2:$J$500,A4,'Test Cases'!$M$2:$M$500,"Manual") -> 1 | H4: =COUNTIFS('Test Cases'!$J$2:$J$500,A4,'Test Cases'!$N$2:$N$500,"Yes*") -> 4 | I4: =COUNTIFS('Test Cases'!$J$2:$J$500,A4,'Test Cases'!$L$2:$L$500,"Pass") -> 3 | J4: =IF(E4=0,"Not Covered",IF(I4=E4,"Covered & Passed","Covered")) -> Covered
A5: TS_UI_04 | B5: Dil seçimi (AZ / RU) | C5: Login | D5: TC_LANG_POS_005, TC_LANG_POS_006 | E5: =COUNTIF('Test Cases'!$J$2:$J$500,A5) -> 2 | F5: =COUNTIFS('Test Cases'!$J$2:$J$500,A5,'Test Cases'!$M$2:$M$500,"Automated") -> 0 | G5: =COUNTIFS('Test Cases'!$J$2:$J$500,A5,'Test Cases'!$M$2:$M$500,"Manual") -> 2 | H5: =COUNTIFS('Test Cases'!$J$2:$J$500,A5,'Test Cases'!$N$2:$N$500,"Yes*") -> 1 | I5: =COUNTIFS('Test Cases'!$J$2:$J$500,A5,'Test Cases'!$L$2:$L$500,"Pass") -> 0 | J5: =IF(E5=0,"Not Covered",IF(I5=E5,"Covered & Passed","Covered")) -> Covered
A6: TS_UI_05 | B6: Şəhər seçimi | C6: Guest | D6: TC_CITY_NEG_007, TC_CITY_POS_001, TC_CITY_POS_002, TC_CITY_POS_003 | E6: =COUNTIF('Test Cases'!$J$2:$J$500,A6) -> 4 | F6: =COUNTIFS('Test Cases'!$J$2:$J$500,A6,'Test Cases'!$M$2:$M$500,"Automated") -> 3 | G6: =COUNTIFS('Test Cases'!$J$2:$J$500,A6,'Test Cases'!$M$2:$M$500,"Manual") -> 1 | H6: =COUNTIFS('Test Cases'!$J$2:$J$500,A6,'Test Cases'!$N$2:$N$500,"Yes*") -> 3 | I6: =COUNTIFS('Test Cases'!$J$2:$J$500,A6,'Test Cases'!$L$2:$L$500,"Pass") -> 3 | J6: =IF(E6=0,"Not Covered",IF(I6=E6,"Covered & Passed","Covered")) -> Covered
A7: TS_UI_06 | B7: Şəhər seçimi | C7: Login | D7: TC_CITY_POS_004, TC_CITY_POS_005, TC_CITY_POS_006 | E7: =COUNTIF('Test Cases'!$J$2:$J$500,A7) -> 3 | F7: =COUNTIFS('Test Cases'!$J$2:$J$500,A7,'Test Cases'!$M$2:$M$500,"Automated") -> 0 | G7: =COUNTIFS('Test Cases'!$J$2:$J$500,A7,'Test Cases'!$M$2:$M$500,"Manual") -> 3 | H7: =COUNTIFS('Test Cases'!$J$2:$J$500,A7,'Test Cases'!$N$2:$N$500,"Yes*") -> 0 | I7: =COUNTIFS('Test Cases'!$J$2:$J$500,A7,'Test Cases'!$L$2:$L$500,"Pass") -> 0 | J7: =IF(E7=0,"Not Covered",IF(I7=E7,"Covered & Passed","Covered")) -> Covered
A8: TS_UI_07 | B8: Məhsul axtarışı | C8: Guest | D8: TC_SRCH_EDGE_005, TC_SRCH_EDGE_007, TC_SRCH_EDGE_012, TC_SRCH_NEG_003, TC_SRCH_NEG_004, TC_SRCH_POS_001, TC_SRCH_POS_002, TC_SRCH_POS_006, TC_SRCH_POS_008, TC_SRCH_POS_009, TC_SRCH_POS_010, TC_SRCH_POS_011 | E8: =COUNTIF('Test Cases'!$J$2:$J$500,A8) -> 12 | F8: =COUNTIFS('Test Cases'!$J$2:$J$500,A8,'Test Cases'!$M$2:$M$500,"Automated") -> 6 | G8: =COUNTIFS('Test Cases'!$J$2:$J$500,A8,'Test Cases'!$M$2:$M$500,"Manual") -> 6 | H8: =COUNTIFS('Test Cases'!$J$2:$J$500,A8,'Test Cases'!$N$2:$N$500,"Yes*") -> 7 | I8: =COUNTIFS('Test Cases'!$J$2:$J$500,A8,'Test Cases'!$L$2:$L$500,"Pass") -> 7 | J8: =IF(E8=0,"Not Covered",IF(I8=E8,"Covered & Passed","Covered")) -> Covered
A9: TS_UI_08 | B9: Məhsul axtarışı | C9: Login | D9: TC_SRCH_POS_013 | E9: =COUNTIF('Test Cases'!$J$2:$J$500,A9) -> 1 | F9: =COUNTIFS('Test Cases'!$J$2:$J$500,A9,'Test Cases'!$M$2:$M$500,"Automated") -> 0 | G9: =COUNTIFS('Test Cases'!$J$2:$J$500,A9,'Test Cases'!$M$2:$M$500,"Manual") -> 1 | H9: =COUNTIFS('Test Cases'!$J$2:$J$500,A9,'Test Cases'!$N$2:$N$500,"Yes*") -> 0 | I9: =COUNTIFS('Test Cases'!$J$2:$J$500,A9,'Test Cases'!$L$2:$L$500,"Pass") -> 0 | J9: =IF(E9=0,"Not Covered",IF(I9=E9,"Covered & Passed","Covered")) -> Covered
A10: TS_UI_09 | B10: Kataloq və kateqoriya naviqasiyası | C10: Guest | D10: TC_CAT_NEG_006, TC_CAT_POS_001, TC_CAT_POS_002, TC_CAT_POS_003, TC_CAT_POS_004, TC_CAT_POS_005, TC_CAT_UI_007 | E10: =COUNTIF('Test Cases'!$J$2:$J$500,A10) -> 7 | F10: =COUNTIFS('Test Cases'!$J$2:$J$500,A10,'Test Cases'!$M$2:$M$500,"Automated") -> 3 | G10: =COUNTIFS('Test Cases'!$J$2:$J$500,A10,'Test Cases'!$M$2:$M$500,"Manual") -> 4 | H10: =COUNTIFS('Test Cases'!$J$2:$J$500,A10,'Test Cases'!$N$2:$N$500,"Yes*") -> 5 | I10: =COUNTIFS('Test Cases'!$J$2:$J$500,A10,'Test Cases'!$L$2:$L$500,"Pass") -> 4 | J10: =IF(E10=0,"Not Covered",IF(I10=E10,"Covered & Passed","Covered")) -> Covered
A11: TS_UI_10 | B11: Məhsul siyahısı: sıralama, filtr, səhifələmə | C11: Guest | D11: TC_PLP_BVA_005, TC_PLP_BVA_012, TC_PLP_NEG_004, TC_PLP_NEG_013, TC_PLP_NEG_014, TC_PLP_POS_001, TC_PLP_POS_002, TC_PLP_POS_003, TC_PLP_POS_006, TC_PLP_POS_007, TC_PLP_POS_008, TC_PLP_POS_009, TC_PLP_POS_010, TC_PLP_POS_011, TC_PLP_POS_015, TC_PLP_POS_016, TC_PLP_POS_017, TC_PLP_POS_018, TC_PLP_POS_019, TC_PLP_POS_020, TC_PLP_POS_022, TC_PLP_POS_023, TC_PLP_POS_024, TC_PLP_POS_025, TC_PLP_POS_026, TC_PLP_POS_027, TC_PLP_POS_028, TC_PLP_POS_029, TC_PLP_UI_021 | E11: =COUNTIF('Test Cases'!$J$2:$J$500,A11) -> 29 | F11: =COUNTIFS('Test Cases'!$J$2:$J$500,A11,'Test Cases'!$M$2:$M$500,"Automated") -> 11 | G11: =COUNTIFS('Test Cases'!$J$2:$J$500,A11,'Test Cases'!$M$2:$M$500,"Manual") -> 18 | H11: =COUNTIFS('Test Cases'!$J$2:$J$500,A11,'Test Cases'!$N$2:$N$500,"Yes*") -> 18 | I11: =COUNTIFS('Test Cases'!$J$2:$J$500,A11,'Test Cases'!$L$2:$L$500,"Pass") -> 13 | J11: =IF(E11=0,"Not Covered",IF(I11=E11,"Covered & Passed","Covered")) -> Covered
A12: TS_UI_11 | B12: Məhsul detal səhifəsi (PDP) | C12: Guest | D12: TC_PDP_NEG_005, TC_PDP_NEG_012, TC_PDP_POS_001, TC_PDP_POS_002, TC_PDP_POS_004, TC_PDP_POS_006, TC_PDP_POS_007, TC_PDP_POS_008, TC_PDP_POS_009, TC_PDP_POS_010, TC_PDP_POS_011, TC_PDP_POS_015, TC_PDP_POS_016, TC_PDP_UI_003 | E12: =COUNTIF('Test Cases'!$J$2:$J$500,A12) -> 14 | F12: =COUNTIFS('Test Cases'!$J$2:$J$500,A12,'Test Cases'!$M$2:$M$500,"Automated") -> 4 | G12: =COUNTIFS('Test Cases'!$J$2:$J$500,A12,'Test Cases'!$M$2:$M$500,"Manual") -> 10 | H12: =COUNTIFS('Test Cases'!$J$2:$J$500,A12,'Test Cases'!$N$2:$N$500,"Yes*") -> 6 | I12: =COUNTIFS('Test Cases'!$J$2:$J$500,A12,'Test Cases'!$L$2:$L$500,"Pass") -> 5 | J12: =IF(E12=0,"Not Covered",IF(I12=E12,"Covered & Passed","Covered")) -> Covered
A13: TS_UI_12 | B13: Məhsul detal səhifəsi (PDP) | C13: Login | D13: TC_PDP_NEG_014, TC_PDP_POS_013 | E13: =COUNTIF('Test Cases'!$J$2:$J$500,A13) -> 2 | F13: =COUNTIFS('Test Cases'!$J$2:$J$500,A13,'Test Cases'!$M$2:$M$500,"Automated") -> 0 | G13: =COUNTIFS('Test Cases'!$J$2:$J$500,A13,'Test Cases'!$M$2:$M$500,"Manual") -> 2 | H13: =COUNTIFS('Test Cases'!$J$2:$J$500,A13,'Test Cases'!$N$2:$N$500,"Yes*") -> 1 | I13: =COUNTIFS('Test Cases'!$J$2:$J$500,A13,'Test Cases'!$L$2:$L$500,"Pass") -> 1 | J13: =IF(E13=0,"Not Covered",IF(I13=E13,"Covered & Passed","Covered")) -> Covered
... A30: TS_UI_29 | B30: Bir Bonus: ID kart və əməliyyat tarixçəsi | C30: Login | D30: TC_BON_POS_001, TC_BON_POS_002, TC_BON_POS_003, TC_BON_POS_005, TC_BON_UI_004, TC_TRX_BVA_007, TC_TRX_NEG_009, TC_TRX_POS_006, TC_TRX_POS_008 | E30: =COUNTIF('Test Cases'!$J$2:$J$500,A30) -> 9 | F30: =COUNTIFS('Test Cases'!$J$2:$J$500,A30,'Test Cases'!$M$2:$M$500,"Automated") -> 0 | G30: =COUNTIFS('Test Cases'!$J$2:$J$500,A30,'Test Cases'!$M$2:$M$500,"Manual") -> 9 | H30: =COUNTIFS('Test Cases'!$J$2:$J$500,A30,'Test Cases'!$N$2:$N$500,"Yes*") -> 1 | I30: =COUNTIFS('Test Cases'!$J$2:$J$500,A30,'Test Cases'!$L$2:$L$500,"Pass") -> 0 | J30: =IF(E30=0,"Not Covered",IF(I30=E30,"Covered & Passed","Covered")) -> Covered

Sheet Summary
A1: Summary — UI Test Göstəriciləri
A3: Göstərici
A4: Cəmi UI test case | B4: =COUNTA('Test Cases'!$A$2:$A$500) -> 228
A5: Cəmi ssenari | B5: =COUNTA('Test Scenarios'!$A$2:$A$100) -> 29
A7: Prioritet üzrə
A8: Göstərici | B8: Say | C8: Faiz
A9: P1 - Critical | B9: =COUNTIF('Test Cases'!$D$2:$D$500,"P1 - Critical") -> 36 | C9: =IFERROR(B9/$B$4,0) -> 0.15789474
A10: P2 - High | B10: =COUNTIF('Test Cases'!$D$2:$D$500,"P2 - High") -> 93 | C10: =IFERROR(B10/$B$4,0) -> 0.40789474
A11: P3 - Medium | B11: =COUNTIF('Test Cases'!$D$2:$D$500,"P3 - Medium") -> 92 | C11: =IFERROR(B11/$B$4,0) -> 0.40350877
A12: P4 - Low | B12: =COUNTIF('Test Cases'!$D$2:$D$500,"P4 - Low") -> 7 | C12: =IFERROR(B12/$B$4,0) -> 0.030701754
A14: Test növü üzrə (bir TC bir neçə növə aid ola bilər)
A15: Göstərici | B15: Say | C15: Faiz
A16: Pozitiv | B16: =COUNTIF('Test Cases'!$E$2:$E$500,"*Pozitiv*") -> 148 | C16: =IFERROR(B16/$B$4,0) -> 0.64912281
A17: Neqativ | B17: =COUNTIF('Test Cases'!$E$2:$E$500,"*Neqativ*") -> 59 | C17: =IFERROR(B17/$B$4,0) -> 0.25877193
A18: BVA | B18: =COUNTIF('Test Cases'!$E$2:$E$500,"*BVA*") -> 24 | C18: =IFERROR(B18/$B$4,0) -> 0.10526316
A19: EP | B19: =COUNTIF('Test Cases'!$E$2:$E$500,"*EP*") -> 17 | C19: =IFERROR(B19/$B$4,0) -> 0.074561404
A20: Edge | B20: =COUNTIF('Test Cases'!$E$2:$E$500,"*Edge*") -> 10 | C20: =IFERROR(B20/$B$4,0) -> 0.043859649
A21: Decision Table | B21: =COUNTIF('Test Cases'!$E$2:$E$500,"*Decision Table*") -> 7 | C21: =IFERROR(B21/$B$4,0) -> 0.030701754
A22: State Transition | B22: =COUNTIF('Test Cases'!$E$2:$E$500,"*State Transition*") -> 25 | C22: =IFERROR(B22/$B$4,0) -> 0.10964912
A23: UI | B23: =COUNTIF('Test Cases'!$E$2:$E$500,"*UI*") -> 11 | C23: =IFERROR(B23/$B$4,0) -> 0.048245614
A24: Smoke | B24: =COUNTIF('Test Cases'!$E$2:$E$500,"*Smoke*") -> 8 | C24: =IFERROR(B24/$B$4,0) -> 0.035087719
A26: Manual vs Avtomat
A27: Göstərici | B27: Say | C27: Faiz
A28: Automated | B28: =COUNTIF('Test Cases'!$M$2:$M$500,"Automated") -> 43 | C28: =IFERROR(B28/$B$4,0) -> 0.18859649
A29: Manual | B29: =COUNTIF('Test Cases'!$M$2:$M$500,"Manual") -> 185 | C29: =IFERROR(B29/$B$4,0) -> 0.81140351
A31: Regression
A32: Göstərici | B32: Say | C32: Faiz
A33: Regression — Avtomat (Yes) | B33: =COUNTIF('Test Cases'!$N$2:$N$500,"Yes") -> 43 | C33: =IFERROR(B33/$B$4,0) -> 0.18859649
A34: Regression — Manual (Yes (Manual)) | B34: =COUNTIF('Test Cases'!$N$2:$N$500,"Yes (Manual)") -> 57 | C34: =IFERROR(B34/$B$4,0) -> 0.25
A35: Regression-a daxil deyil (No) | B35: =COUNTIF('Test Cases'!$N$2:$N$500,"No") -> 128 | C35: =IFERROR(B35/$B$4,0) -> 0.56140351
A36: Regression-un avtomatlaşdırılma faizi | B36: =IFERROR(B33/(B33+B34),0) -> 0.43
A38: İcra statusu
A39: Göstərici | B39: Say | C39: Faiz
A40: Pass | B40: =COUNTIF('Test Cases'!$L$2:$L$500,"Pass") -> 79 | C40: =IFERROR(B40/$B$4,0) -> 0.34649123
A41: Fail | B41: =COUNTIF('Test Cases'!$L$2:$L$500,"Fail") -> 3 | C41: =IFERROR(B41/$B$4,0) -> 0.013157895
A42: Blocked | B42: =COUNTIF('Test Cases'!$L$2:$L$500,"Blocked") -> 0 | C42: =IFERROR(B42/$B$4,0) -> 0
A43: Not Run | B43: =COUNTIF('Test Cases'!$L$2:$L$500,"Not Run") -> 146 | C43: =IFERROR(B43/$B$4,0) -> 0.64035088
A44: Qeyd: icra risk əsaslı aparılıb — 43 avtomat TC (regression) + 17 P1 manual TC icra olunub, 3 Fail = BUG_001–003. "Not Run" olan 146 TC P2–P4 manual regression TC-ləridir: dizayn edilib və növbəti regression dövründə icra üçün planlaşdırılıb (Assumptions & Risks → R-14).
A45: Summary — API Test Göstəriciləri (api.anarabbas.com)
A47: Göstərici | B47: Say | C47: Faiz
A48: Cəmi API test case | B48: =COUNTA('API_Test Cases'!$A$2:$A$500) -> 168
A49: Cəmi API ssenari | B49: =COUNTIF('API_Test Scenarios'!$A$2:$A$100,"SC_API_*") -> 11
A50: API bug-ları | B50: =COUNTIF('Bug Reports'!$A:$A,"BUG_API*") -> 4
A52: Prioritet üzrə
A53: Göstərici | B53: Say | C53: Faiz
A54: P1 - Critical | B54: =COUNTIF('API_Test Cases'!$E$2:$E$500,"P1 - Critical") -> 47 | C54: =IFERROR(B54/$B$48,0) -> 0.2797619
A55: P2 - High | B55: =COUNTIF('API_Test Cases'!$E$2:$E$500,"P2 - High") -> 76 | C55: =IFERROR(B55/$B$48,0) -> 0.45238095
A56: P3 - Medium | B56: =COUNTIF('API_Test Cases'!$E$2:$E$500,"P3 - Medium") -> 41 | C56: =IFERROR(B56/$B$48,0) -> 0.24404762
A57: P4 - Low | B57: =COUNTIF('API_Test Cases'!$E$2:$E$500,"P4 - Low") -> 4 | C57: =IFERROR(B57/$B$48,0) -> 0.023809524
A59: Test texnikası üzrə (bir TC bir neçə texnikaya aid ola bilər)
A60: Göstərici | B60: Say | C60: Faiz
A61: Equivalence partitioning | B61: =COUNTIF('API_Test Cases'!$P$2:$P$500,"*EP*") -> 82 | C61: =IFERROR(B61/$B$48,0) -> 0.48809524
A62: Boundary value analysis | B62: =COUNTIF('API_Test Cases'!$P$2:$P$500,"*BVA*") -> 38 | C62: =IFERROR(B62/$B$48,0) -> 0.22619048
A63: Decision table | B63: =COUNTIF('API_Test Cases'!$P$2:$P$500,"*Decision table*") -> 8 | C63: =IFERROR(B63/$B$48,0) -> 0.047619048
A64: State transition | B64: =COUNTIF('API_Test Cases'!$P$2:$P$500,"*State transition*") -> 24 | C64: =IFERROR(B64/$B$48,0) -> 0.14285714
A65: Error guessing | B65: =COUNTIF('API_Test Cases'!$P$2:$P$500,"*Error guessing*") -> 22 | C65: =IFERROR(B65/$B$48,0) -> 0.13095238
A66: Contract (JSON Schema) | B66: =COUNTIF('API_Test Cases'!$P$2:$P$500,"*Contract*") -> 6 | C66: =IFERROR(B66/$B$48,0) -> 0.035714286
A68: İcra statusu (manual, CallMan)
A69: Göstərici | B69: Say | C69: Faiz
A70: Pass | B70: =COUNTIF('API_Test Cases'!$M$2:$M$500,"Pass") -> 168 | C70: =IFERROR(B70/$B$48,0) -> 1
A71: Fail | B71: =COUNTIF('API_Test Cases'!$M$2:$M$500,"Fail") -> 0 | C71: =IFERROR(B71/$B$48,0) -> 0
A72: Not Run (zamandan asılı) | B72: =COUNTIF('API_Test Cases'!$M$2:$M$500,"Not Run") -> 0 | C72: =IFERROR(B72/$B$48,0) -> 0
A74: Avtomatlaşdırma
A75: Göstərici | B75: Say | C75: Faiz
A76: Gauge (kurs framework-ü) — Automated | B76: =COUNTIF('API_Test Cases'!$N$2:$N$500,"Automated") -> 123 | C76: =IFERROR(B76/$B$48,0) -> 0.73214286
A77: Gauge — Manual | B77: =COUNTIF('API_Test Cases'!$N$2:$N$500,"Manual") -> 45 | C77: =IFERROR(B77/$B$48,0) -> 0.26785714
A78: RestAssured + JUnit 5 — əhatə olunan TC | B78: =COUNTIF('API_Test Cases'!$T$2:$T$500,"Yes*") -> 130 | C78: =IFERROR(B78/$B$48,0) -> 0.77380952
A80: Avtomat run nəticələri (08.10.2026)
A81: Run | B81: Nəticə
A82: CallMan Collection Runner (manual) | B82: 165/165 PASS
A83: Gauge API regression | B83: 123/123 PASS (4 run; 1 run-da server 500 — BUG_API_004; 13.10: 123/123)
A84: RestAssured + JUnit 5 | B84: 166/166 PASS (3 ardıcıl run, son: 13.10.2026)
A85: Allure report | B85: 166 test, 100%

Sheet Grooming Questions
A1: GQ ID | B1: Modul | C1: Sual (PO / BA / Dev üçün) | D1: Niyə vacibdir (risk) | E1: Əlaqəli TC | F1: Qəbul edilmiş fərziyyə (cavab gələnədək) | G1: Cavab (saytda təsdiqlənmiş) | H1: Status
A2: GQ_UI_01 | B2: Axtarış | C2: Boş sorğu ilə "Axtar" basıldıqda nə baş verməlidir: heç nə, xəbərdarlıq, yoxsa bütün məhsullar? | D2: Gözlənilən nəticə müəyyən olmadan TC PASS/FAIL ola bilməz | E2: TC_SRCH_NEG_004 | F2: Axtarış icra olunmur, səhifə dəyişmir | G2: Boş sorğuda "Axtar" heç bir reaksiya vermir | H2: Answered
A3: GQ_UI_02 | B3: Qiymət filtri | C3: Min > Max olduqda sistem dəyərləri yerini dəyişməlidir, xəta göstərməlidir, yoxsa filtri bloklamalıdır? | D3: Decision Table halı müəyyən deyil | E3: TC_PLP_NEG_004 | F3: Xəta vermədən idarə edilir (500 yoxdur) | G3: Yanlış dəyər daxil edilən kimi sahə avtomatik sıfırlanır | H3: Answered
A4: GQ_UI_03 | B4: Qiymət filtri | C4: Qiymət filtrinin minimum və maksimum icazə verilən dəyərləri nədir? Mənfi və onluq dəyərlər qəbul edilirmi? | D4: BVA sərhədləri məlum deyil | E4: TC_PLP_BVA_005 | F4: Alt sərhəd 0, mənfi qəbul edilmir | G4: Mənfi və hərf daxil edildikdə sahə avtomatik sıfırlanır | H4: Answered
A5: GQ_UI_04 | B5: Seçilmişlər | C5: Guest istifadəçi məhsulu seçilmişlərə əlavə edə bilərmi (lokal saxlama), yoxsa login tələb olunur? | D5: Guest vs Login davranışı fərqli ola bilər | E5: TC_FAV_POS_001, TC_FAV_POS_003 | F5: Login tələb olunur | G5: Guest login olmadan seçilmişlərə əlavə edə bilir (brauzerdə saxlanılır) | H5: Answered
A6: GQ_UI_05 | B6: Səbət | C6: Miqdar 1 olduqda "−" düyməsi deaktiv olur, yoxsa məhsulu silmə təklifi çıxır? | D6: BVA min sərhədində assertion buna görə dəqiqləşir | E6: TC_CART_BVA_004 | F6: Miqdar 1-dən aşağı düşmür | G6: Miqdar 1 olduqda "−" düyməsi deaktivdir | H6: Answered
A7: GQ_UI_06 | B7: Səbət | C7: Bir məhsul üçün maksimum miqdar limiti stok sayı ilə, yoxsa sabit limitlə müəyyən olunur? Limitdə hansı mesaj göstərilir? | D7: BVA max sərhədi məlum deyil | E7: TC_CART_BVA_005 | F7: Limit = stok sayı | G7: Stokda 1 ədəd qaldıqda "+" və "−" işləmir | H7: Answered
A8: GQ_UI_07 | B8: Səbət (Login) | C8: Guest səbəti login olduqda hesabın mövcud səbəti ilə birləşir, yoxsa onu əvəz edir? | D8: Səbət itkisi birbaşa satış itkisidir | E8: TC_CART_POS_010 | F8: Birləşir (merge) | H8: Open
A9: GQ_UI_08 | B9: Autentifikasiya | C9: Operator kodu validasiyası client tərəfdə, yoxsa server tərəfdə aparılır? Etibarlı kodların tam siyahısı hansıdır? | D9: Yanlış nömrəyə SMS göndərilməsi xərc və təhlükəsizlik riskidir | E9: TC_AUTH_NEG_007 | F9: Etibarlı kodlar: 10, 50, 51, 55, 60, 70, 77, 99 | G9: Sahə +994-dən sonra max 9 rəqəm qəbul edir; "Kodu göndər" həmişə aktivdir, validasiya klikdə işləyir: yanlış nömrədə "Telefon nömrəsi yanlışdır" | H9: Answered
A10: GQ_UI_09 | B10: Autentifikasiya | C10: OTP kodunun etibarlılıq müddəti, yenidən göndərmə taymeri və yanlış cəhd limiti nədir? Limit aşıldıqda hesab bloklanırmı? | D10: State Transition testi üçün keçid qaydaları lazımdır | E10: TC_AUTH_NEG_011, TC_AUTH_NEG_019, TC_AUTH_BVA_025, TC_AUTH_NEG_026 | F10: Kod taymer bitdikdən sonra etibarsızdır | G10: OTP 6 rəqəmli, taymer 2:59; 2 yanlış cəhd icazəli, 3-cüdə həmin nömrə 15 dəqiqə bloklanır (başqa nömrəyə təsir etmir) | H10: Answered
A11: GQ_UI_10 | B11: PDP / Taksit | C11: Taksit aylıq ödənişi necə yuvarlaqlaşdırılır (yuxarı / riyazi)? Fərq son ayın ödənişinə əlavə olunurmu? | D11: Pul hesablamasında 0.01 ₼ fərq FAIL deməkdir | E11: TC_PDP_POS_004 | F11: Riyazi yuvarlaqlaşdırma, 2 onluq | H11: Open
A12: GQ_UI_11 | B12: Checkout | C12: Pulsuz çatdırılma həddi (50 ₼) bütün şəhərlər və çatdırılma üsulları üçün eynidirmi? Endirimdən əvvəlki, yoxsa sonrakı məbləğə tətbiq olunur? | D12: BVA dəyərləri buna görə seçilir | E12: TC_CHK_BVA_003, TC_CHK_BVA_004 | F12: Bakı, kuryer, endirimdən sonrakı məbləğ | H12: Open
A13: GQ_UI_12 | B13: Avtomatlaşdırma | C13: Login axınlarını avtomatlaşdırmaq üçün test mühiti və ya OTP bypass (sabit test kodu) təqdim oluna bilərmi? | D13: Cavab müsbət olsa, "Yes (Manual)" TC-lər avtomatlaşdırıla bilər | E13: Bütün [Login] TC-lər | F13: Yoxdur — login axınları manual qalır | H13: Open
A14: GQ_UI_13 | B14: Şəhər seçimi | C14: Login istifadəçinin seçdiyi şəhər hesabda saxlanılır, yoxsa yalnız brauzerdə? | D14: Cihazlar arası fərqli çatdırılma şərtləri göstərilə bilər | E14: TC_CITY_POS_004 | F14: Hesabda saxlanılır | G14: Müşahidə: logout-dan sonra "Şəhərinizi seçin" pəncərəsi avtomatik açılır (Bakı seçili) | H14: Open
A15: GQ_UI_14 | B15: Dil | C15: Dil seçimi hesab səviyyəsində saxlanılırmı (SMS/bildirişlərin dili)? | D15: Bildirişlərin yanlış dildə gəlməsi | E15: TC_LANG_POS_005, TC_LANG_POS_006 | F15: Yalnız brauzerdə saxlanılır | H15: Open
A16: GQ_UI_15 | B16: Autentifikasiya | C16: Nömrə yerli formatda (0 ilə) daxil edildikdə 0 avtomatik atılmalıdırmı? | D16: İstifadəçilərin çoxu nömrəni 0 ilə yazır — login uğursuzluğu | E16: TC_AUTH_EDGE_015 | F16: 0 atılır | H16: Open
A17: GQ_UI_16 | B17: Qeydiyyat / Profil | C17: Ad sahəsinin qaydaları: min/max uzunluq, icazə verilən simvollar (rəqəm, tire, boşluq, kiril)? | D17: BVA və EP dəyərləri buna görə seçilir | E17: TC_REG_NEG_002, TC_REG_BVA_003/004, TC_PRF_NEG_004 | F17: Min 2, max 50, yalnız hərf, boşluq və tire | H17: Open
A18: GQ_UI_17 | B18: Profil | C18: Profildə e-poçt sahəsi varmı, mütləqdirmi? Telefon nömrəsi necə dəyişdirilir? | D18: Hesab təhlükəsizliyi | E18: TC_PRF_NEG_005, TC_PRF_POS_006 | F18: E-poçt ixtiyaridir; telefon yalnız OTP ilə dəyişir | G18: E-Mail sahəsi var; telefon "Əlaqə nömrəsi" kimi ayrıca göstərilir | H18: Answered
A19: GQ_UI_18 | B19: Səbət (Login) | C19: Logout-dan sonra hesabın səbəti guest səbəti kimi brauzerdə qalırmı? | D19: Paylaşılan kompüterdə məxfilik riski | E19: TC_CART_POS_016 | F19: Qalmır | H19: Open
A20: GQ_UI_19 | B20: PDP / Rəy | C20: Rəyi kim yaza bilər: istənilən login istifadəçi, yoxsa yalnız məhsulu almış alıcı? | D20: Saxta rəy riski | E20: TC_PDP_NEG_012, TC_PDP_NEG_014 | F20: Yalnız almış alıcı | G20: Rəy yalnız çatdırılmış məhsullar üçün yazıla bilər ("Rəy yazmaq" tabı: "Çatdırılmış məhsul yoxdur") | H20: Answered
A21: GQ_UI_20 | B21: Axtarış | C21: Axtarış üçün minimum simvol sayı varmı? | D21: Server yükü və UX | E21: TC_SRCH_EDGE_012 | F21: Minimum yoxdur | H21: Open
A22: GQ_UI_21 | B22: Seçilmişlər | C22: Guest seçilmişləri login olduqda hesabın seçilmişləri ilə birləşir, yoxsa itirilir? | D22: Guest artıq seçilmişlərdən istifadə edə bildiyi üçün login zamanı data itkisi riski | E22: TC_FAV_POS_009 | F22: Birləşir | G22: Guest seçilmişləri login-dən sonra hesabda qalır | H22: Answered
A23: GQ_UI_22 | B23: Sıralama | C23: "Yüksək reytinq" və "Yeniliklər" hansı meyarla sıralayır (reytinq + rəy sayı? əlavə olunma tarixi?) | D23: Meyar bilinmədən sərt assertion yazmaq mümkün deyil | E23: TC_PLP_POS_026, TC_PLP_POS_027 | F23: Reytinq azalan; tarix azalan | H23: Open
A24: GQ_UI_23 | B24: Sıralama | C24: Kateqoriya açıldıqda default sıralama hansıdır? | D24: İstifadəçinin ilk gördüyü siyahı | E24: TC_PLP_POS_028 | F24: Populyar | H24: Open
A25: GQ_UI_24 | B25: Autentifikasiya | C25: Əvvəl istifadə olunmuş nömrə ilə eyni brauzerdə OTP-siz giriş qəsdən edilmiş "etibarlı cihaz" funksiyasıdırmı? Logout bu statusu ləğv etməlidirmi? Status nə qədər müddət etibarlıdır? | D25: Logout-dan sonra OTP-siz giriş ortaq kompüterdə hesabın ələ keçirilməsinə imkan verir (yalnız nömrə ilə giriş) | E25: TC_AUTH_POS_028, TC_AUTH_SEC_029…032 | F25: Etibarlı cihaz funksiyasıdır, amma logout onu ləğv etməlidir | G25: Network analizi: OTP-ni Single ID (SSO) sessiyası atlayır; logout SSO sessiyasını bitirmir (singleid_auth OTP-siz token qaytarır). Başqa nömrə üçün OTP soruşulur | H25: Open
A26: GQ_UI_25 | B26: Ana səhifə | C26: Sol paneldə "Bütün kateqoriyalar" siyahını yerində genişləndirir, yoxsa /categories səhifəsini açır? | D26: Gözlənilən nəticə müəyyən olmadan TC PASS/FAIL ola bilməz | E26: TC_HOME_POS_010 | F26: Siyahını genişləndirir | G26: Siyahı yerində genişlənir (URL dəyişmir, overlay açılır) | H26: Answered
A27: GQ_UI_26 | B27: Ana səhifə | C27: "Birmarket-də satın" və "915" seçicisi nəyi göstərir/açır? | D27: Keçidin düzgünlüyü | E27: TC_HOME_POS_014, TC_HOME_POS_015 | F27: Satıcı səhifəsi; əlaqə məlumatları | G27: "Birmarket-də satın" → business.umico.az; "915" → iş saatları (hər gün 09:00–00:00) və tel: link | H27: Answered
A28: GQ_UI_27 | B28: Bir Bonus | C28: Bonus hansı məbləğə hesablanır: bonusla ödənilən hissə çıxılırmı? Yuvarlaqlaşdırma qaydası nədir? "Bonus növü" filtrində hansı seçimlər var? | D28: Pul ekvivalenti olan bonusların səhv hesablanması | E28: TC_BON_POS_003, TC_TRX_POS_008 | F28: (məbləğ − xərclənən bonus) × faiz, riyazi yuvarlaqlaşdırma | G28: Ekrandakı data formula ilə uyğun gəlir | H28: Open
A29: GQ_UI_28 | B29: Profil | C29: FİN kodun qaydaları: dəqiq 7 simvol? Yalnız böyük hərf və rəqəm? Kiçik hərf avtomatik böyüdülürmü? | D29: BVA/EP dəyərləri buna görə seçilir | E29: TC_PRF_BVA_008…TC_PRF_NEG_011 | F29: 7 simvol, latın böyük hərf + rəqəm | H29: Open
A30: GQ_UI_29 | B30: Profil | C30: Doğum tarixi üçün minimum yaş (məs. 18) və maksimum geriyə həddi varmı? | D30: BVA sərhədləri | E30: TC_PRF_BVA_014 | F30: Gələcək tarix seçilmir; yaş limiti yoxdur | G30: Tarix yalnız təqvimdən seçilir | H30: Open
A31: GQ_UI_30 | B31: Ünvanlar | C31: Çatdırılma ərazisindən kənar ünvan əlavə etmək mümkündürmü (yalnız sifariş zamanı bloklanır)? | D31: Səhv ünvana sifariş riski | E31: TC_ADR_NEG_007 | F31: Əlavə etmək mümkün deyil | H31: Open
A32: GQ_UI_31 | B32: Ünvanlar | C32: "Ünvan adı" üçün maksimum uzunluq və icazə verilən simvollar nədir? | D32: BVA | E32: TC_ADR_BVA_009 | F32: Max 50 simvol | H32: Open
A33: GQ_UI_32 | B33: Profil | C33: Profil şəkli üçün icazə verilən formatlar və maksimum fayl ölçüsü nədir? | D33: Böyük/yanlış faylla sistemin yüklənməsi | E33: TC_PRF_NEG_017 | F33: JPG/PNG, max 5 MB | H33: Open
A34: GQ_UI_33 | B34: Profil | C34: Ad və Soyad məcburidirmi? | D34: Validasiya TC-ləri | E34: TC_PRF_NEG_003 | F34: Ad məcburi, Soyad ixtiyari | H34: Open
A35: GQ_UI_34 | B35: Ünvanlar | C35: Saxlanmış ünvan redaktə və silinə bilərmi? Əsas ünvan silinərsə nə olur? | D35: Ünvan idarəetməsi | E35: TC_ADR_POS_013 | F35: Silinə bilər | H35: Open
A36: GQ_UI_35 | B36: Ana səhifə | C36: "Ləğv et" seçildikdən sonra bildiriş təklifi nə vaxt yenidən göstərilir (heç vaxt / X gün sonra / hər sessiyada)? | D36: Təkrarlanan pop-up istifadəçini narahat edir | E36: TC_HOME_POS_018 | F36: Ən azı həmin sessiyada təkrar göstərilmir | H36: Open

Sheet Assumptions & Risks
A1: Fərziyyələr
A2: ID | B2: Fərziyyə | C2: Təsir
A3: A-01 | B3: Public sayt üçün rəsmi tələb sənədi yoxdur; gözlənilən nəticələr saytın hazırkı davranışı, saytdakı rəsmi məlumat səhifələri (Çatdırılma və ödəmə, FAQ) və e-commerce best practice əsasında müəyyən edilib | C3: Qeyri-müəyyən hallar Grooming Questions-da qeyd olunub
A4: A-02 | B4: UI mesajlarının dəqiq mətnləri saytdan təsdiqlənib Expected Result-a yazılır (boş səbət, nəticəsiz axtarış, silmə təsdiqi, "Səbətdə" vəziyyəti artıq təsdiqlənib) | C4: Mətn dəyişərsə TC yenilənir
A5: A-03 | B5: Pulsuz çatdırılma həddi ana səhifədəki məlumata əsasən 50 ₼ qəbul edilib | C5: BVA dəyərləri 49.xx / 50.xx seçilib
A6: A-04 | B6: Login yalnız telefon nömrəsi + SMS OTP (BirID) ilə həyata keçirilir, şifrə ilə login yoxdur | C6: Login axınları manual qalır
A7: A-05 | B7: Bütün testlər Production-da aparılır; sifariş heç vaxt təsdiqlənmir | C7: Checkout yalnız təsdiq addımına qədər yoxlanılır
A8: A-06 | B8: Kabinet URL-ləri təsdiqlənib: /account/profile, /account/orders, /account/notifications. Checkout URL-i hələ qeyd olunmayıb | C8: TC_ACC_NEG_001/002/004 bu URL-lərlə avtomatlaşdırılır
A9: A-07 | B9: Login versiyası yalnız davranışı Guest-dən fərqlənən funksionallıqlar üçün yazılıb (header, səbət, seçilmişlər, checkout, kabinet). Davranışı eyni olan funksiyalar (kataloq, filtr) üçün login dublikatı yazılmayıb | C9: Mənasız dublikat TC-lərin qarşısı alınır
A10: A-08 | B10: UI avtomatlaşdırma guest vəziyyətində icra olunur; login tələb edən ssenarilər SMS OTP səbəbilə manual test olunur | C10: Avtomat regression yalnız guest funksionallığını əhatə edir
A11: A-09 | B11: "Səbətə əlavə et" asılı 8 TC (PDP_POS_010, CART_*, CHK_POS_001) Manual regression-dadır | C11: Avtomat regression-da yalnız deterministik nəticə verən testlər saxlanılır
A13: Risklər
A14: ID | B14: Risk | C14: Təsir səviyyəsi | D14: Azaltma tədbiri
A15: R-01 | B15: Prod-da qiymət, stok və məhsul siyahısı daim dəyişir | C15: Yüksək | D15: Assertion-lar invariantlara əsaslanır, hardcode data yoxdur (Automation Strategy, bölmə 3)
A16: R-02 | B16: Saytın anti-bot qorunması avtomatlaşdırılmış brauzeri bloklaya bilər (captcha / rate limit) | C16: Orta | D16: Testlər arasında aqressiv sorğu yoxdur, regression kiçik və fokuslu saxlanılır; bloklanma halında bug yox, Blocked statusu verilir
A17: R-03 | B17: SMS OTP səbəbilə login axınları avtomatlaşdırıla bilmir | C17: Orta | D17: Manual regression (Yes (Manual)) + GQ_UI_12 ilə test mühiti/bypass tələbi
A18: R-04 | B18: UI/locator dəyişiklikləri (redesign) avtomat testləri sındıra bilər | C18: Orta | D18: Stabil locator-lar (id, data-atributlar, mətn) və Page Object pattern (verilmiş arxitekturaya uyğun)
A19: R-05 | B19: Marketinq bannerləri və aksiyalar tez-tez dəyişir | C19: Aşağı | D19: Banner testləri manual saxlanılıb
A20: R-06 | B20: 3 yanlış OTP cəhdi nömrəni 15 dəqiqə bloklayır (təsdiqlənib) | C20: Orta | D20: Limit testləri (TC_AUTH_NEG_019, TC_AUTH_BVA_025, TC_AUTH_NEG_026) ayrıca test nömrəsi ilə, digər login testlərindən sonra icra olunur
A21: R-07 | B21: Production-da qonaq səbətinə əlavə ardıcıl run-larda qeyri-deterministikdir (təsdiqləndi: eyni kod bir run-da PASS, digərində FAIL) | C21: Orta | D21: Səbətə əlavə asılı testlər avtomatdan çıxarılıb, Manual regression-a keçirilib; boş səbət testi (CART_POS_011) avtomatda qalır
A22: R-08 | B22: "Şəhərinizi seçin" pəncərəsi təmiz sessiyada avtomatik açılır və klikləri bloklayır | C22: Orta | D22: "Şeher penceresi açılarsa bağla" concept-i: pəncərə çıxarsa X ilə bağlanır, çıxmazsa test davam edir
A23: R-09 | B23: Səhifə tam hidrasiya olunmamış klik itə bilər (flaky) | C23: Orta | D23: Səhifə yüklənməsi və element vəziyyəti gözlənilir (explicit wait); hard sleep minimuma endirilib
A24: R-10 | B24: Təmiz sessiyada "Brauzerinizdə bildirişlər almaq istəyirsinizmi?" pəncərəsi çıxa bilər və sol yuxarı hissəni örtür (manual icrada müşahidə olundu, avtomat run-larda çıxmadı) | C24: Aşağı | D24: "Şeher penceresi açılarsa bağla" concept-inə əlavə addım: pəncərə görünərsə "Ləğv et" basılır, görünməzsə test davam edir
A25: R-11 | B25: API: server vaxtaşırı etibarlı sorğulara 500 "Network connection lost" qaytarır (08.10.2026 ~14:52–14:55 arası 23 ssenari bu səbəbdən düşdü; həmin sorğular əvvəl və sonra uğurla keçdi) | C25: Orta | D25: Nəticə assertion-a yox, mühitə bağlıdırsa run təkrarlanır; hadisə BUG_API_004 kimi sənədləşdirildi. Framework-də 500 üçün retry açılmadı ki, real problem gizlənməsin
... A28: R-14 | B28: UI: 228 TC-nin hamısını bir sprint ərzində manual icra etmək mümkün deyil | C28: Aşağı | D28: Risk əsaslı icra: bütün avtomat regression (43) hər run-da, manual-dan yalnız P1 (17) icra olundu. P2–P4 manual TC-lər (146) "Not Run" statusundadır və növbəti regression dövrünə planlaşdırılıb

Sheet Bug Reports
A1: Bug ID | B1: Title | C1: Module | D1: Severity | E1: Priority | F1: Environment | G1: Preconditions | H1: Steps to Reproduce | I1: Actual Result | J1: Expected Result | K1: Related TC | L1: Attachment | M1: Status
A2: BUG_001 | B2: Logout Single ID (SSO) sessiyasını bitirmir — eyni brauzerdə təkrar girişdə OTP soruşulmadan login olunur | C2: Autentifikasiya → Logout / SSO sessiyası | D2: Major | E2: P1 - Critical | F2: Production: https://birmarket.az/ | Windows 11 | Google Chrome (son stabil versiya) | 07.10.2026 | G2: 1) Test nömrəsi ilə bu brauzerdə əvvəllər OTP ilə login olunub 2) İstifadəçi "Şəxsi hesabım" → "Çıxış" ilə logout edib, header-də "Qeydiyyat | Giriş" görünür 3) DevTools → Network açıqdır ("Keep log" aktiv) | H2: 1) "Qeydiyyat | Giriş" linkinə klik et 2) "Telefon nömrəsi" sahəsinə həmin nömrəni daxil et 3) "Kodu göndər" düyməsinə klik et 4) Network-də "singleid_auth" sorğusunun Payload və Response-una bax | I2: OTP ekranı açılmır, SMS göndərilmir, istifadəçi birbaşa login olur. Network: "singleid_auth" (Payload: code, code_verifier, redirect_uri=https://birmarket.az/sso_auth, state) Response-da access_token (expires_in: 1800), refresh_token (refresh_expires_in: 7776000 — 90 gün), "auth_scenario": "sign_in" qaytarır. Yəni logout-dan sonra SSO sessiyası aktiv qalır və avtorizasiya kodu OTP-siz verilir. Qeyd: başqa nömrə ilə girişdə OTP soruşulur Əlavə yoxlama (07.10.2026): Chrome Incognito və Microsoft Edge-də eyni nömrə ilə OTP tələb olundu (TC_AUTH_SEC_029, TC_AUTH_SEC_030 — PASS). Yəni OTP yalnız əvvəllər login olunmuş eyni brauzerdə keçilir; logout həmin brauzerin "etibarlı" statusunu silmir. Yalnız nömrə ilə girişə imkan yoxdur → Severity: Major (Critical deyil). | J2: "Çıxış" həm Birmarket tokenlərini, həm də Single ID (SSO) sessiyasını bitirməlidir (end-session / refresh_token ləğvi). Təkrar girişdə OTP ekranı açılmalı və SMS kod tələb olunmalıdır. Risk: ortaq kompüterdə növbəti şəxs nömrəni yazaraq əvvəlki istifadəçinin hesabına daxil ola bilər | K2: TC_AUTH_POS_028, GQ_UI_24 | L2: Ekran videosu + Network ekran şəkilləri (tokenlər, session_state, ext_id gizlədilməlidir) | M2: New
A3: BUG_002 | B3: Ünvan validasiya mesajı formada olmayan "təsdiqləmək" düyməsinə istinad edir və türkcə söz ("tıklayın") ehtiva edir | C3: Mənim ünvanlarım → Ünvan validasiyası | D3: Minor | E3: P3 - Medium | F3: Production: https://birmarket.az/account/addresses | Windows 11 | Google Chrome (son stabil versiya) | 07.10.2026 | G3: 1) İstifadəçi login olub 2) "Mənim ünvanlarım" səhifəsi açıqdır | H3: 1) "Ünvan adı" sahəsinə "Ev" daxil et 2) "Ünvan və evin nömrəsi" sahəsinə "fbvfdfg" daxil et 3) "Ok" düyməsinə klik et 4) Sahənin altındakı mesajı oxu | I3: Mesaj göstərilir: "Ünvan dəqiq deyil. Ünvan düzgündürsə, "təsdiqləmək" düyməsini tıklayın və ya ünvanı xəritədə seçin." Formada "təsdiqləmək" adlı düymə yoxdur (mövcud link: "Seçilmiş ünvan ilə davam etmək"); "tıklayın" türkcə sözdür | J3: Mesaj formada mövcud olan elementə istinad etməlidir (məs. "Seçilmiş ünvan ilə davam etmək" linkinə klikləyin) və düzgün Azərbaycan dilində olmalıdır ("klikləyin" / "basın") | K3: TC_ADR_NEG_005 | L3: Ekran şəkli (mövcuddur) | M3: New
A4: BUG_003 | B4: "Mənim ID kartım" səhifəsində bonus kartı blokunda sınıq şəkil ikonu göstərilir | C4: Bir Bonus → ID kart | D4: Minor | E4: P4 - Low | F4: Production: https://birmarket.az/account/id-card | Windows 11 | Google Chrome (son stabil versiya) | 07.10.2026 | G4: 1) İstifadəçi login olub | H4: 1) "Şəxsi hesabım" → "Mənim ID kartım"-a klik et 2) Bonus kartı blokunun aşağı hissəsinə bax | I4: Kart nömrəsinin altında yüklənməyən şəkil (sınıq şəkil ikonu) göstərilir | J4: Bütün şəkillər düzgün yüklənməli; şəkil yoxdursa element ümumiyyətlə göstərilməməlidir | K4: TC_BON_UI_004 | L4: Ekran şəkli (mövcuddur — şəxsi məlumatlar gizlədilməlidir) | M4: New
A5: BUG_API_001 | B5: POST /cards başqa istifadəçinin hesabı üçün 403 qaytarır — ümumi "başqasının resursu → 404" qaydasına zidddir (resursun mövcudluğu açıqlanır) | C5: API → GRAD-201 POST /cards | D5: Minor | E5: P3 - Medium | F5: API: https://api.anarabbas.com | Callman Desktop | 08.10.2026 | G5: user1 token alınıb; acc_003 user2-yə aiddir | H5: 1) POST /auth/login (user1@test.com / User1234) 2) POST /cards Body: {"accountId":"acc_003","initialAmount":100} | I5: 403 {"code":"FORBIDDEN"} — sistem acc_003 hesabının mövcud olduğunu təsdiqləmiş olur. Digər bütün endpoint-lərdə (GET /cards/{id}, DELETE /beneficiaries/{id}, POST /cards/{id}/block) başqasının resursu 404 qaytarır | J5: Backlog-un ümumi qaydasına görə başqa istifadəçinin resursu 404 qaytarmalıdır (403 yox) — mövcudluq gizlədilməlidir. Qeyd: GRAD-201 AC-5 403 gözləyir → tələblərdə ziddiyyət; PO ilə dəqiqləşdirilməlidir (GQ_API_01) | K5: TC_API_CARD_014, GQ_API_01 | L5: Callman: request + response | M5: New
A6: BUG_API_002 | B6: Auth xəta cavablarında (POST /auth/login və müddəti bitmiş token) "code" sahəsi yoxdur — API-nin vahid xəta formatına uyğun deyil | C6: API → POST /auth/login; token yoxlaması (401) | D6: Trivial | E6: P4 - Low | F6: API: https://api.anarabbas.com | Callman Desktop | 08.10.2026 | G6: — | H6: 1) POST /auth/login Body: {"email":"user1@test.com","password":"Wrong999"} | I6: 1) Login: 401 {"error":"Email və ya şifrə yanlışdır"} — "code" yoxdur. 2) 24 saatdan köhnə token ilə GET /beneficiaries (10.10.2026): 401 {"error":"Token etibarsızdır və ya müddəti bitib"} — "code" yoxdur | J6: Backlog qaydası: biznes xətaları {"error","code"} formatındadır və assert code-a yazılmalıdır. Auth xətaları da sabit code qaytarmalıdır (məs. "INVALID_CREDENTIALS", "TOKEN_EXPIRED") | K6: TC_API_AUTH_002, TC_API_SEC_004, GQ_API_13 | L6: Callman: response | M6: New
A7: BUG_API_003 | B7: GET /me/accounts: müddəti bitmiş kart (card_002, 08/2026) "active" statusu ilə qaytarılır | C7: API → GET /me/accounts (backlog scope-undan kənar, kəşfiyyat zamanı tapılıb) | D7: Minor | E7: P3 - Medium | F7: API: https://api.anarabbas.com | Callman Desktop | 08.10.2026 | G7: user1 token; cari tarix 08.10.2026 | H7: 1) POST /auth/login (user1) 2) GET /me/accounts | I7: data[0].cards: {"id":"card_002","expiryMonth":8,"expiryYear":2026,"status":"active"} — kartın müddəti 2 ay əvvəl bitib | J7: Müddəti bitmiş kart "expired" (və ya qeyri-aktiv) statusunda olmalıdır və ödənişdə istifadə edilə bilməməlidir | K7: TC_API_CARD_021 (SETUP) | L7: Callman: response | M7: New
A8: BUG_API_004 | B8: API vaxtaşırı etibarlı sorğulara 500 "Network connection lost" qaytarır | C8: API → bütün endpoint-lər (POST /beneficiaries, POST /cards, GET /billers və s.) | D8: Major | E8: P2 - High | F8: API: https://api.anarabbas.com | Gauge+RestAssured | 08.10.2026 14:52–14:55 | G8: Etibarlı token; düzgün body | H8: 1) Tam API regression run-u işlət (mvn test "-Dgauge.specs.dir=specs/api-testing/final-project") 2) Logda 500 cavablarını izlə | I8: 123 ssenaridən 23-ü düşdü: server 500 {"error":"Server xətası","detail":"Network connection lost."} qaytardı; bəzi sorğular 10–13 san çəkdi. Eyni sorğular bir neçə saniyə əvvəl/sonra 201/200 ilə keçdi. Təkrar run (15:21) — 123/123 PASS | J8: Etibarlı sorğular sabit şəkildə gözlənilən status (200/201/4xx) qaytarmalıdır; daxili bağlantı xətaları müştəriyə 500 kimi sızmamalı, lazım olsa 503 + Retry-After qaytarılmalıdır | K8: Bütün API regression (intermittent) | L8: Gauge HTML report + terminal log | M8: New

Sheet API_Test Plan
A1: API Test Plan — Final Project Backlog (api.anarabbas.com)
A3: Məqsəd | B3: Final project backlog-undakı 10 task-ın (3 epic, 37 SP) acceptance criteria-ya uyğunluğunu yoxlamaq, bug-ları aşkar etmək və regression ssenarilərini avtomatlaşdırmaq.
A4: Test obyekti | B4: Base URL: https://api.anarabbas.com — EPIC-1 Saxlanmış alıcılar (GRAD-101/102/103), EPIC-2 Virtual kartlar (GRAD-201/202/203/204), EPIC-3 Kommunal ödənişlər (GRAD-301/302/303) + POST /auth/login.
A5: Scope — daxil | B5: Funksional (pozitiv/neqativ), validasiya (EP, BVA), biznes qaydaları (komissiya, limitlər, idempotency), state transition (kart statusu), təhlükəsizlik (401, IDOR → 404, PAN/CVV sızmaması), contract (JSON Schema), yoxlama ardıcıllığı.
A6: Scope — xaric | B6: Performans/yük testi (yalnız rate limit bir dəfə manual), UI, DB səviyyəsində yoxlama, backlog-da təsvir olunmayan endpoint-lər (GET /me/accounts yalnız test datası üçün).
A7: Test texnikaları | B7: Equivalence partitioning, Boundary value analysis (fullName, IBAN, nickname, initialAmount, amount, Idempotency-Key, limit/page, gündəlik/tranzaksiya limiti), Decision table (yoxlama ardıcıllığı, filtr birləşmələri), State transition (GRAD-203/204 — 9 xanalı keçid cədvəli), Error guessing (tip qarışıqlığı, normallaşdırma, IDOR). Decision table-lar ayrıca: API_Decision Table sheet-i (GRAD-302, GRAD-201). Hər TC-nin texnikası API_Test Cases → "Test texnikası" sütunundadır.
A8: Mühit və test data | B8: 3 test user (admin, user1, user2). Sandbox token-ə bağlıdır: hər yeni login boş mühit açır, data 24 saat yaşayır. Avtomat testlərdə hər ssenaridən əvvəl yeni login edilir (təmiz sandbox) — testlər müstəqildir, limitlər (10 alıcı, 3 kart) və receiptNo deterministikdir. Test datası testin özündə yaradılır (alıcı, kart, ödəniş) — hardcode id yoxdur. IDOR testləri üçün user2 token-i ayrıca alınır.
A9: Manual icra | B9: CallMan: collection (11 qovluq = 11 ssenari) + environment (baseUrl, token, user2Token, cardId, benId, uuid). Token login sorğusunun test skriptində environment-ə yazılır, assertion-lar hər sorğuda (status + code + body). Collection Runner ilə icra.
A10: Avtomatlaşdırma | B10: İki səviyyə: (1) RestAssured + JUnit 5 + Allure layihəsi (final-project-api-restassured): request/response POJO-lar (pul sahələri BigDecimal), base request spec (ApiSpec), token setup (BaseTest @BeforeEach), API client class-ları, data-driven BVA (@ParameterizedTest + @CsvSource), state transition cədvəli, 6 JSON Schema, Allure (@Epic/@Feature/@Story/@Severity, hər request/response hesabatda) — 166 test icrası, 130 TC. (2) Kursun Gauge arxitekturası (RestAssured əsaslı step-lər) — 123 ssenari. Kriteriya: P1/P2 + deterministik nəticə → avtomat; P3/P4 və zamandan asılı testlər → manual (CallMan). Assert-lər mətnə yox, code-a yazılır.
A11: Entry kriteriyaları | B11: Backlog statusu "Ready for QA"; test mühiti və test user-lər əlçatandır; grooming sualları üzrə fərziyyələr qeyd olunub.
A12: Exit kriteriyaları | B12: Bütün P1 TC-lər icra olunub; P1/P2 avtomat regression ardıcıl 3 run-da stabil (flaky yoxdur); bütün AC-lər ən azı 1 TC ilə əhatə olunub (API_Traceability); tapılan bug-lar Bug Reports sheet-ində sənədləşdirilib.
A13: Risklər | B13: 1) spentToday Bakı vaxtı 00:00-da sıfırlanır — limit testləri gecə yarısına yaxın flaky ola bilər. 2) Sandbox limitləri (10 alıcı, 3 kart) test sırasından asılılıq yarada bilər → test özü datanı yaradır və təmizləyir. 3) Backlog-da ziddiyyət (403 vs 404) — GQ_API_01. 4) Rate limit (600/10 san) — paralel run-da nəzərə alınmalıdır.
A14: Təhvil veriləcəklər | B14: Test plan (bu sheet), API test case-lər + traceability + decision table, CallMan collection + environment (export), bug report-lar, RestAssured layihəsi (GitHub), Allure report (single-file HTML), təqdimat.

Sheet API_Test Scenarios
A1: Scenario ID | B1: Endpoint / Resource | C1: Ssenari | D1: Priority | E1: TC sayı | F1: Avtomat TC
A2: SC_API_01 | B2: POST /auth/login + bütün endpoint-lər | C2: Autentifikasiya, token və ümumi qaydalar: 401 (tokensiz / saxta / prefikssiz / vaxtı bitmiş token), sandbox izolyasiyası, rate limit, həssas məlumatın (PAN/CVV) sızmaması | D2: P1 - Critical | E2: =COUNTIF('API_Test Cases'!$K:$K,A2) -> 9 | F2: =COUNTIFS('API_Test Cases'!$K:$K,A2,'API_Test Cases'!$N:$N,"Automated") -> 7
A3: SC_API_02 | B3: POST /beneficiaries (GRAD-101) | C3: Yeni alıcı əlavə etmək: uğurlu yaradılma, IBAN normallaşdırması, fullName/IBAN/nickname validasiyası (EP + BVA), dublikat IBAN və ləqəb, öz hesabı, 10 alıcı limiti, yoxlama ardıcıllığı | D3: P1 - Critical | E3: =COUNTIF('API_Test Cases'!$K:$K,A3) -> 30 | F3: =COUNTIFS('API_Test Cases'!$K:$K,A3,'API_Test Cases'!$N:$N,"Automated") -> 24
A4: SC_API_03 | B4: GET /beneficiaries (GRAD-102) | C4: Alıcılar siyahısı: default sıralama, fullName/createdAt sıralaması (Azərbaycan əlifbası), valyuta filtri, I/İ/ı fərqi olmadan axtarış, ləqəbə görə axtarış, q BVA, boş nəticə, AND məntiqi | D4: P2 - High | E4: =COUNTIF('API_Test Cases'!$K:$K,A4) -> 19 | F4: =COUNTIFS('API_Test Cases'!$K:$K,A4,'API_Test Cases'!$N:$N,"Automated") -> 9
A5: SC_API_04 | B5: DELETE /beneficiaries/{id} (GRAD-103) | C5: Alıcını silmək: 204, yarat-sil-oxu, təkrar silmə, başqasının alıcısı (IDOR → 404), silinmədən sonra IBAN və limit yerinin azad olması | D5: P2 - High | E5: =COUNTIF('API_Test Cases'!$K:$K,A5) -> 7 | F5: =COUNTIFS('API_Test Cases'!$K:$K,A5,'API_Test Cases'!$N:$N,"Automated") -> 4
A6: SC_API_05 | B6: POST /cards (GRAD-201) | C6: Virtual kart buraxmaq: uğurlu buraxılış və standart limitlər, maskedPan/expiry formatı, initialAmount BVA və tip validasiyası, başqasının hesabı, balans çatışmazlığı, 3 kart limiti (ACTIVE/FROZEN sayılır, BLOCKED sayılmır) | D6: P1 - Critical | E6: =COUNTIF('API_Test Cases'!$K:$K,A6) -> 21 | F6: =COUNTIFS('API_Test Cases'!$K:$K,A6,'API_Test Cases'!$N:$N,"Automated") -> 17
A7: SC_API_06 | B7: GET /cards/{id} (GRAD-202) | C7: Kart məlumatı: POST ilə uyğunluq, ödənişdən sonra availableBalance/spentToday yenilənməsi, başqasının kartı (404) | D7: P2 - High | E7: =COUNTIF('API_Test Cases'!$K:$K,A7) -> 4 | F7: =COUNTIFS('API_Test Cases'!$K:$K,A7,'API_Test Cases'!$N:$N,"Automated") -> 3
A8: SC_API_07 | B8: POST /cards/{id}/block (GRAD-203) | C8: Kartı bloklamaq / dondurmaq: state transition cədvəlinin 9 xanası, reason validasiyası, INVALID_JSON, yoxlama ardıcıllığı, FROZEN/BLOCKED kartla ödənişin rədd edilməsi | D8: P1 - Critical | E8: =COUNTIF('API_Test Cases'!$K:$K,A8) -> 18 | F8: =COUNTIFS('API_Test Cases'!$K:$K,A8,'API_Test Cases'!$N:$N,"Automated") -> 12
A9: SC_API_08 | B9: POST /cards/{id}/unblock (GRAD-204) | C9: Dondurulmuş kartı açmaq: FROZEN → ACTIVE, ACTIVE və BLOCKED kartlar üçün 409, açılmış kartla ödəniş, dondur-aç-dondur dövrü | D9: P2 - High | E9: =COUNTIF('API_Test Cases'!$K:$K,A9) -> 7 | F9: =COUNTIFS('API_Test Cases'!$K:$K,A9,'API_Test Cases'!$N:$N,"Automated") -> 5
A10: SC_API_09 | B10: GET /billers (GRAD-301) | C10: Təchizatçı kataloqu: 6 təchizatçı, kataloq datası və komissiya qaydaları, kateqoriya filtri, etibarsız kateqoriya, contract | D10: P2 - High | E10: =COUNTIF('API_Test Cases'!$K:$K,A10) -> 9 | F10: =COUNTIFS('API_Test Cases'!$K:$K,A10,'API_Test Cases'!$N:$N,"Automated") -> 6
A11: SC_API_10 | B11: POST /bill-payments (GRAD-302) | C11: Kommunal ödəniş: komissiya hesablanması (faiz/sabit, min/max, yuvarlaqlaşdırma), balans və spentToday, receiptNo, idempotency (replay / conflict / açar BVA), abunəçi formatı, məbləğ aralığı, tranzaksiya və gündəlik limit, balans çatışmazlığı (total üzrə), kart statusu və valyutası | D11: P1 - Critical | E11: =COUNTIF('API_Test Cases'!$K:$K,A11) -> 30 | F11: =COUNTIFS('API_Test Cases'!$K:$K,A11,'API_Test Cases'!$N:$N,"Automated") -> 25
A12: SC_API_11 | B12: GET /bill-payments (GRAD-303) | C12: Ödəniş tarixçəsi: default sıralama, səhifələmə (page/limit BVA, boş səhifə), tarix filtri (inclusive, etibarsız tarix, from > to), təchizatçı və kart filtri, filtrdən sonrakı total | D12: P2 - High | E12: =COUNTIF('API_Test Cases'!$K:$K,A12) -> 14 | F12: =COUNTIFS('API_Test Cases'!$K:$K,A12,'API_Test Cases'!$N:$N,"Automated") -> 11
A13: Cəmi | E13: =SUM(E2:E12) -> 168 | F13: =SUM(F2:F12) -> 123

Sheet API_Test Cases
A1: Test Case ID | B1: Test Case Title | C1: Endpoint | D1: Method | E1: Priority | F1: Test Type | G1: Preconditions | H1: Request (Headers / Params / Body) | I1: Expected Status Code | J1: Expected Response (Body / Headers) | K1: Scenario ID | L1: Manual/Automation əsaslandırması | M1: Status | N1: Automation | O1: Regression | P1: Test texnikası | Q1: Acceptance Criteria (Traceability) | R1: Actual Result | S1: Execution Date | T1: RestAssured (JUnit 5 + Allure)
A2: TC_API_AUTH_001 | B2: Etibarlı user1 məlumatları ilə login → token qaytarılır | C2: /auth/login | D2: POST | E2: P1 - Critical | F2: Pozitiv | G2: Test user mövcuddur | H2: Content-Type: application/json Body: {"email":"user1@test.com","password":"User1234"} | I2: 200 | J2: token: boş deyil (notNull) user.email = "user1@test.com" Cavabda password sahəsi YOXDUR | K2: SC_API_01 | L2: Deterministik nəticə, yalnız API ilə yoxlanılır, hər relizdə təkrarlanmalıdır → avtomat | M2: Pass | N2: Automated | O2: Yes | P2: EP | Q2: Ümumi: Token al | R2: Callman icrası: status 200; gözlənilən body/code ilə üst-üstə düşür (bütün assertion-lar PASS). PASS. | S2: 08.10.2026 | T2: Yes — AuthSecurityTest
A3: TC_API_AUTH_002 | B3: Yanlış şifrə ilə login rədd edilir və hansı sahənin səhv olduğu açıqlanmır | C3: /auth/login | D3: POST | E3: P1 - Critical | F3: Auth | G3: Test user mövcuddur | H3: Body: {"email":"user1@test.com","password":"Wrong999"} | I3: 401 | J3: token sahəsi yoxdur Xəta mesajı "şifrə səhvdir" kimi konkret sahəni açıqlamır (user enumeration riski) | K3: SC_API_01 | L3: Deterministik nəticə, yalnız API ilə yoxlanılır, hər relizdə təkrarlanmalıdır → avtomat | M3: Pass | N3: Automated | O3: Yes | P3: EP / Error guessing | Q3: Ümumi: 401 | R3: 401 qaytarıldı, token yoxdur. Cavab: {"error":"Email və ya şifrə yanlışdır"} — hansı sahənin səhv olduğu açıqlanmır. Müşahidə: login xətasında digər endpoint-lərdən fərqli olaraq "code" sahəsi yoxdur (BUG_API_002). PASS. | S3: 08.10.2026 | T3: Yes — AuthSecurityTest
A4: TC_API_SEC_001 | B4: Token olmadan qorunan endpoint-lər 401 qaytarır (data-driven, 10 endpoint) | C4: Bütün qorunan endpoint-lər | D4: GET | E4: P1 - Critical | F4: Auth | G4: — | H4: Authorization header YOXDUR Cədvəl: GET /beneficiaries, POST /beneficiaries, DELETE /beneficiaries/{id}, POST /cards, GET /cards/{id}, POST /cards/{id}/block, POST /cards/{id}/unblock, GET /billers, POST /bill-payments, GET /bill-payments | I4: 401 | J4: Hər endpoint üçün status 401; cavabda data qaytarılmır | K4: SC_API_01 | L4: Hər endpoint üçün eyni qayda → bir data-driven avtomat test ilə tam əhatə | M4: Pass | N4: Automated | O4: Yes | P4: EP / Decision table | Q4: Ümumi: Token yoxdur → 401 | R4: Callman icrası: status 401; gözlənilən body/code ilə üst-üstə düşür (bütün assertion-lar PASS). PASS. | S4: 08.10.2026 | T4: Yes — AuthSecurityTest
A5: TC_API_SEC_002 | B5: Saxta (uydurma) token ilə sorğu 401 qaytarır | C5: /beneficiaries | D5: GET | E5: P1 - Critical | F5: Auth | G5: — | H5: Authorization: Bearer abc.invalid.token | I5: 401 | J5: Cavabda alıcı datası yoxdur | K5: SC_API_01 | L5: Deterministik nəticə, yalnız API ilə yoxlanılır, hər relizdə təkrarlanmalıdır → avtomat | M5: Pass | N5: Automated | O5: Yes | P5: EP | Q5: Ümumi: Token saxtadır → 401 | R5: Callman icrası: status 401; gözlənilən body/code ilə üst-üstə düşür (bütün assertion-lar PASS). PASS. | S5: 08.10.2026 | T5: Yes — AuthSecurityTest
A6: TC_API_SEC_003 | B6: "Bearer" prefiksi olmadan göndərilən token 401 qaytarır | C6: /beneficiaries | D6: GET | E6: P2 - High | F6: Auth | G6: Etibarlı token alınıb | H6: Authorization: {{token}} (Bearer sözü YOXDUR) | I6: 401 | J6: Sorğu rədd edilir | K6: SC_API_01 | L6: Deterministik nəticə, yalnız API ilə yoxlanılır, hər relizdə təkrarlanmalıdır → avtomat | M6: Pass | N6: Automated | O6: Yes | P6: Error guessing | Q6: Ümumi: 401 | R6: Callman icrası: status 401; gözlənilən body/code ilə üst-üstə düşür (bütün assertion-lar PASS). PASS. | S6: 08.10.2026 | T6: Yes — AuthSecurityTest
A7: TC_API_SEC_004 | B7: Müddəti bitmiş (24 saatdan köhnə) token 401 qaytarır | C7: /beneficiaries | D7: GET | E7: P3 - Medium | F7: Auth | G7: 24 saat əvvəl alınmış token | H7: Authorization: Bearer {{expiredToken}} | I7: 401 | J7: Sorğu rədd edilir | K7: SC_API_01 | L7: 24 saat gözləmə tələb edir — avtomat run-da praktik deyil → manual | M7: Pass | N7: Manual | O7: No | P7: EP | Q7: Ümumi: Müddəti bitib → 401 | R7: Callman: 09.10.2026 23:43-də alınmış token ilə 10.10.2026 23:56-da (24 saat 13 dəq sonra) GET /beneficiaries → 401 {"error":"Token etibarsızdır və ya müddəti bitib"}. Data qaytarılmadı. Qeyd: cavabda "code" sahəsi yoxdur — BUG_API_002 ilə eyni müşahidə. | S7: 10.10.2026 | T7: No (manual / Gauge)
A8: TC_API_SEC_005 | B8: Yeni login yeni, boş sandbox açır (data izolyasiyası) | C8: /beneficiaries | D8: GET | E8: P2 - High | F8: Pozitiv | G8: Token A ilə 1 alıcı yaradılıb; sonra eyni user ilə yeni login → Token B | H8: Authorization: Bearer {{tokenB}} | I8: 200 | J8: total = 0, items = [] (Token A-nın datası Token B-də görünmür) | K8: SC_API_01 | L8: Deterministik nəticə, yalnız API ilə yoxlanılır, hər relizdə təkrarlanmalıdır → avtomat | M8: Pass | N8: Automated | O8: Yes | P8: Error guessing | Q8: Sandbox qaydası | R8: Token A ilə alıcı yaradıldıqdan sonra yeni login (Token B): GET /beneficiaries → total 0, items []. Sandbox izolyasiyası işləyir. PASS. | S8: 08.10.2026 | T8: Yes — AuthSecurityTest
A9: TC_API_SEC_006 | B9: Sorğu limiti aşıldıqda 429 RATE_LIMITED və Retry-After qaytarılır | C9: /billers | D9: GET | E9: P4 - Low | F9: Neqativ | G9: Etibarlı token | H9: 10 saniyə ərzində 601+ sorğu (CallMan Runner, iteration 601, delay 0) | I9: 429 | J9: code = "RATE_LIMITED" Header Retry-After: 10 | K9: SC_API_01 | L9: Yük xarakterli test, regresiyada sandbox-u bloklayır → yalnız manual, bir dəfə | M9: Pass | N9: Manual | O9: No | P9: BVA | Q9: Ümumi: 600 sorğu / 10 san → 429 | R9: PowerShell (HttpClient, paralel): 1 token ilə GET /billers × 700 → 608 × 200, 92 × 429. 429 cavabı: {"error":"Bu sessiya üçün sorğu limiti aşıldı. 10 saniyə gözləyin.","code":"RATE_LIMITED","retryAfter":10}; header Retry-After: 10 (CORS-da expose olunub). 600-dən artıq 200 (608) — sorğuların bir hissəsi növbəti 10 san pəncərəyə düşüb, qüsur deyil. Limit sessiyaya (token-ə) bağlıdır. | S9: 09.10.2026 | T9: No (manual / Gauge)
A10: TC_API_SEC_007 | B10: Kart cavabında tam kart nömrəsi (PAN) və CVV qaytarılmır | C10: /cards | D10: POST | E10: P1 - Critical | F10: Auth | G10: user1 token | H10: Authorization: Bearer {{token}} Content-Type: application/json Body: {"accountId":"acc_002","initialAmount":10} | I10: 201 | J10: maskedPan maskalıdır ("4169 73** **** NNNN") Cavabda pan, cardNumber, cvv, cvc sahələri YOXDUR | K10: SC_API_01 | L10: Təhlükəsizlik yoxlaması, hər relizdə qorunmalıdır → avtomat | M10: Pass | N10: Automated | O10: Yes | P10: Error guessing | Q10: GRAD-201 AC-2 / Təhlükəsizlik | R10: CARD_001 cavabında maskedPan maskalıdır; pan, cardNumber, cvv, cvc sahələri yoxdur. PASS. | S10: 08.10.2026 | T10: Yes — CardTest.Create
A11: TC_API_BEN_001 | B11: Bütün sahələrlə etibarlı alıcı yaradılır (201, Location header) | C11: /beneficiaries | D11: POST | E11: P1 - Critical | F11: Pozitiv | G11: Token: user1@test.com / User1234 (POST /auth/login, bütün testlər eyni sandbox token-i ilə); alıcı siyahısı boş | H11: Authorization: Bearer {{token}} Content-Type: application/json Body: {"fullName":"Nigar Əliyeva","iban":"AZ77AIIB40060019440123456789","currency":"AZN","nickname":"Anam"} | I11: 201 | J11: id: "ben_" + 8 simvol (regex ^ben_[a-z0-9]{8}$) fullName = "Nigar Əliyeva", iban = "AZ77AIIB40060019440123456789", currency = "AZN", nickname = "Anam" createdAt: ISO-8601, boş deyil Header Location = /beneficiaries/{id} | K11: SC_API_02 | L11: Deterministik nəticə, yalnız API ilə yoxlanılır, hər relizdə təkrarlanmalıdır → avtomat | M11: Pass | N11: Automated | O11: Yes | P11: EP | Q11: GRAD-101 AC-1 | R11: Callman icrası: status 201; gözlənilən body/code ilə üst-üstə düşür (bütün assertion-lar PASS). PASS. | S11: 08.10.2026 | T11: Yes — BeneficiaryTest.Create
A12: TC_API_BEN_002 | B12: Alıcı cavabı JSON Schema-ya uyğundur | C12: /beneficiaries | D12: POST | E12: P2 - High | F12: Schema / Contract | G12: Token: user1@test.com / User1234 (POST /auth/login, bütün testlər eyni sandbox token-i ilə) | H12: Authorization: Bearer {{token}} Content-Type: application/json Body: {"fullName":"Rauf Məmmədov","iban":"AZ12NABZ00000000000000000001","currency":"USD"} | I12: 201 | J12: Cavab beneficiary-schema.json-a uyğundur: id, fullName, iban, ibanMasked, currency (string); nickname (string|null); createdAt (string) | K12: SC_API_02 | L12: Struktur (contract) yoxlaması — API dəyişəndə ilk sınan yer → avtomat | M12: Pass | N12: Automated | O12: Yes | P12: Contract | Q12: GRAD-101 AC-1 | R12: Callman icrası: status 201; gözlənilən body/code ilə üst-üstə düşür (bütün assertion-lar PASS). PASS. | S12: 08.10.2026 | T12: Yes — BeneficiaryTest.Create
... A169: TC_API_HIS_014 | B169: Tarixçə cavabı JSON Schema-ya uyğundur | C169: /bill-payments | D169: GET | E169: P2 - High | F169: Schema / Contract | G169: Token: user1@test.com / User1234 (POST /auth/login, bütün testlər eyni sandbox token-i ilə); sandbox-da 18 ödəniş (12 azercell, 6 citynet), hamısı bu gün | H169: Authorization: Bearer {{token}} Query: (yoxdur) | I169: 200 | J169: payment-history-schema.json: page, limit, total, totalPages (integer); items[] (payment) | K169: SC_API_11 | L169: Contract → avtomat | M169: Pass | N169: Automated | O169: Yes | P169: Contract | Q169: GRAD-303 AC-1 | R169: Callman icrası: status 200; gözlənilən body/code ilə üst-üstə düşür (bütün assertion-lar PASS). PASS. | S169: 08.10.2026 | T169: Yes — PaymentHistoryTest

Sheet API_Decision Table
A1: API Decision Table — yoxlama qaydaları və nəticələr
A2: Y = şərt ödənilir, N = ödənilmir, – = nəticəyə təsir etmir (yoxlama əvvəlki addımda dayanır). Qaydalar API-nin yoxlama ardıcıllığı ilə düzülüb (collapsed decision table). Hər qayda ən azı bir test case ilə əhatə olunub.
A4: 1) GRAD-302 POST /bill-payments — ödənişin qəbulu
A5: Şərt / Nəticə | B5: R1 | C5: R2 | D5: R3 | E5: R4 | F5: R5 | G5: R6 | H5: R7 | I5: R8 | J5: R9 | K5: R10 | L5: R11 | M5: R12
A6: C1. Sorğu validdir (məcburi sahələr, tiplər, 2 onluq, Idempotency-Key 8–64) | B6: Y | C6: N | D6: Y | E6: Y | F6: Y | G6: Y | H6: Y | I6: Y | J6: Y | K6: Y | L6: Y | M6: Y
A7: C2. Kart mövcuddur və istifadəçiyə məxsusdur | B7: Y | C7: – | D7: N | E7: – | F7: Y | G7: Y | H7: Y | I7: Y | J7: Y | K7: Y | L7: Y | M7: Y
A8: C3. Təchizatçı mövcuddur | B8: Y | C8: – | D8: – | E8: N | F8: Y | G8: Y | H8: Y | I8: Y | J8: Y | K8: Y | L8: Y | M8: Y
A9: C4. Kart ACTIVE-dir | B9: Y | C9: – | D9: – | E9: – | F9: N | G9: Y | H9: Y | I9: Y | J9: Y | K9: Y | L9: Y | M9: Y
A10: C5. Kart valyutası AZN-dir | B10: Y | C10: – | D10: – | E10: – | F10: – | G10: N | H10: Y | I10: Y | J10: Y | K10: Y | L10: Y | M10: Y
A11: C6. Abunəçi nömrəsi təchizatçının formatına uyğundur | B11: Y | C11: – | D11: – | E11: – | F11: – | G11: – | H11: N | I11: Y | J11: Y | K11: Y | L11: Y | M11: N
A12: C7. Məbləğ təchizatçının min–max aralığındadır | B12: Y | C12: – | D12: – | E12: – | F12: – | G12: – | H12: – | I12: N | J12: Y | K12: Y | L12: Y | M12: N
A13: C8. total ≤ 300 (tək əməliyyat limiti) | B13: Y | C13: – | D13: – | E13: – | F13: – | G13: – | H13: – | I13: – | J13: N | K13: Y | L13: Y | M13: –
A14: C9. spentToday + total ≤ 500 (gündəlik limit) | B14: Y | C14: – | D14: – | E14: – | F14: – | G14: – | H14: – | I14: – | J14: – | K14: N | L14: Y | M14: –
A15: C10. Kart balansı ≥ total | B15: Y | C15: – | D15: – | E15: – | F15: – | G15: – | H15: – | I15: – | J15: – | K15: – | L15: N | M15: –
A16: Status | B16: 201 | C16: 400 | D16: 404 | E16: 404 | F16: 422 | G16: 422 | H16: 422 | I16: 422 | J16: 422 | K16: 422 | L16: 422 | M16: 422
... A19: Test case-lər | B19: PAY_001, PAY_011, PAY_014–017 | C19: PAY_007, PAY_008, PAY_024, PAY_025, PAY_028 | D19: PAY_027 | E19: PAY_026 | F19: BLK_017, BLK_018 | G19: PAY_023 | H19: PAY_010, PAY_012 | I19: PAY_013 | J19: PAY_018 | K19: PAY_019, PAY_020 | L19: PAY_021, PAY_022 | M19: PAY_029
A21: 2) GRAD-201 POST /cards — kartın buraxılması
A22: Şərt / Nəticə | B22: R1 | C22: R2 | D22: R3 | E22: R4 | F22: R5
A23: C1. Body validdir (accountId var, initialAmount ədəd, 2 onluq, 1.00–1000.00) | B23: Y | C23: N | D23: Y | E23: Y | F23: Y
A24: C2. Hesab istifadəçiyə məxsusdur | B24: Y | C24: – | D24: N | E24: Y | F24: Y
A25: C3. ACTIVE + FROZEN kart sayı < 3 (BLOCKED sayılmır) | B25: Y | C25: – | D25: – | E25: N | F25: –
A26: C4. Hesab balansı ≥ initialAmount | B26: Y | C26: – | D26: – | E26: – | F26: N
A27: Status | B27: 201 | C27: 400 | D27: 403 | E27: 422 | F27: 422
A28: code | B28: — (ACTIVE kart) | C28: VALIDATION_ERROR | D28: FORBIDDEN (GQ_API_01) | E28: CARD_LIMIT_REACHED | F28: INSUFFICIENT_FUNDS
A29: Test case-lər | B29: CARD_001, CARD_006, CARD_007, CARD_017, CARD_020 | C29: CARD_005, CARD_008–011, CARD_013 | D29: CARD_014 | E29: CARD_018, CARD_019 | F29: CARD_016
A31: Qeyd: R12 (PAY_029) yoxlama ardıcıllığını təsdiqləyir — həm abunəçi formatı, həm məbləğ səhv olduqda API əvvəlcə INVALID_SUBSCRIBER qaytarır. Digər şərtlərin bir-birinə nisbətən ardıcıllığı backlog-da göstərilməyib; ona görə hər qaydada yalnız bir şərt pozulur.

Sheet API_Coverage
A1: Endpoint | B1: Method | C1: Task | D1: Pozitiv | E1: Neqativ | F1: BVA | G1: State transition | H1: Schema / Contract | I1: Auth | J1: Cəmi TC | K1: Automated | L1: Coverage % (avtomat)
A2: /auth/login | B2: POST | C2: GRAD — Auth | D2: =COUNTIFS('API_Test Cases'!$C:$C,$A2,'API_Test Cases'!$D:$D,$B2,'API_Test Cases'!$F:$F,"Pozitiv") -> 1 | E2: =COUNTIFS('API_Test Cases'!$C:$C,$A2,'API_Test Cases'!$D:$D,$B2,'API_Test Cases'!$F:$F,"Neqativ") -> 0 | F2: =COUNTIFS('API_Test Cases'!$C:$C,$A2,'API_Test Cases'!$D:$D,$B2,'API_Test Cases'!$F:$F,"BVA") -> 0 | G2: =COUNTIFS('API_Test Cases'!$C:$C,$A2,'API_Test Cases'!$D:$D,$B2,'API_Test Cases'!$F:$F,"State transition") -> 0 | H2: =COUNTIFS('API_Test Cases'!$C:$C,$A2,'API_Test Cases'!$D:$D,$B2,'API_Test Cases'!$F:$F,"Schema / Contract") -> 0 | I2: =COUNTIFS('API_Test Cases'!$C:$C,$A2,'API_Test Cases'!$D:$D,$B2,'API_Test Cases'!$F:$F,"Auth") -> 1 | J2: =SUM(D2:I2) -> 2 | K2: =COUNTIFS('API_Test Cases'!$C:$C,$A2,'API_Test Cases'!$D:$D,$B2,'API_Test Cases'!$N:$N,"Automated") -> 2 | L2: =IF(J2=0,0,K2/J2) -> 1
A3: Bütün qorunan endpoint-lər | B3: GET | C3: Ümumi qaydalar | D3: =COUNTIFS('API_Test Cases'!$C:$C,$A3,'API_Test Cases'!$D:$D,$B3,'API_Test Cases'!$F:$F,"Pozitiv") -> 0 | E3: =COUNTIFS('API_Test Cases'!$C:$C,$A3,'API_Test Cases'!$D:$D,$B3,'API_Test Cases'!$F:$F,"Neqativ") -> 0 | F3: =COUNTIFS('API_Test Cases'!$C:$C,$A3,'API_Test Cases'!$D:$D,$B3,'API_Test Cases'!$F:$F,"BVA") -> 0 | G3: =COUNTIFS('API_Test Cases'!$C:$C,$A3,'API_Test Cases'!$D:$D,$B3,'API_Test Cases'!$F:$F,"State transition") -> 0 | H3: =COUNTIFS('API_Test Cases'!$C:$C,$A3,'API_Test Cases'!$D:$D,$B3,'API_Test Cases'!$F:$F,"Schema / Contract") -> 0 | I3: =COUNTIFS('API_Test Cases'!$C:$C,$A3,'API_Test Cases'!$D:$D,$B3,'API_Test Cases'!$F:$F,"Auth") -> 1 | J3: =SUM(D3:I3) -> 1 | K3: =COUNTIFS('API_Test Cases'!$C:$C,$A3,'API_Test Cases'!$D:$D,$B3,'API_Test Cases'!$N:$N,"Automated") -> 1 | L3: =IF(J3=0,0,K3/J3) -> 1
A4: /beneficiaries | B4: POST | C4: GRAD-101 | D4: =COUNTIFS('API_Test Cases'!$C:$C,$A4,'API_Test Cases'!$D:$D,$B4,'API_Test Cases'!$F:$F,"Pozitiv") -> 4 | E4: =COUNTIFS('API_Test Cases'!$C:$C,$A4,'API_Test Cases'!$D:$D,$B4,'API_Test Cases'!$F:$F,"Neqativ") -> 14 | F4: =COUNTIFS('API_Test Cases'!$C:$C,$A4,'API_Test Cases'!$D:$D,$B4,'API_Test Cases'!$F:$F,"BVA") -> 11 | G4: =COUNTIFS('API_Test Cases'!$C:$C,$A4,'API_Test Cases'!$D:$D,$B4,'API_Test Cases'!$F:$F,"State transition") -> 0 | H4: =COUNTIFS('API_Test Cases'!$C:$C,$A4,'API_Test Cases'!$D:$D,$B4,'API_Test Cases'!$F:$F,"Schema / Contract") -> 1 | I4: =COUNTIFS('API_Test Cases'!$C:$C,$A4,'API_Test Cases'!$D:$D,$B4,'API_Test Cases'!$F:$F,"Auth") -> 0 | J4: =SUM(D4:I4) -> 30 | K4: =COUNTIFS('API_Test Cases'!$C:$C,$A4,'API_Test Cases'!$D:$D,$B4,'API_Test Cases'!$N:$N,"Automated") -> 24 | L4: =IF(J4=0,0,K4/J4) -> 0.8
A5: /beneficiaries | B5: GET | C5: GRAD-102 | D5: =COUNTIFS('API_Test Cases'!$C:$C,$A5,'API_Test Cases'!$D:$D,$B5,'API_Test Cases'!$F:$F,"Pozitiv") -> 14 | E5: =COUNTIFS('API_Test Cases'!$C:$C,$A5,'API_Test Cases'!$D:$D,$B5,'API_Test Cases'!$F:$F,"Neqativ") -> 3 | F5: =COUNTIFS('API_Test Cases'!$C:$C,$A5,'API_Test Cases'!$D:$D,$B5,'API_Test Cases'!$F:$F,"BVA") -> 2 | G5: =COUNTIFS('API_Test Cases'!$C:$C,$A5,'API_Test Cases'!$D:$D,$B5,'API_Test Cases'!$F:$F,"State transition") -> 0 | H5: =COUNTIFS('API_Test Cases'!$C:$C,$A5,'API_Test Cases'!$D:$D,$B5,'API_Test Cases'!$F:$F,"Schema / Contract") -> 1 | I5: =COUNTIFS('API_Test Cases'!$C:$C,$A5,'API_Test Cases'!$D:$D,$B5,'API_Test Cases'!$F:$F,"Auth") -> 3 | J5: =SUM(D5:I5) -> 23 | K5: =COUNTIFS('API_Test Cases'!$C:$C,$A5,'API_Test Cases'!$D:$D,$B5,'API_Test Cases'!$N:$N,"Automated") -> 12 | L5: =IF(J5=0,0,K5/J5) -> 0.52173913
A6: /beneficiaries/{id} | B6: DELETE | C6: GRAD-103 | D6: =COUNTIFS('API_Test Cases'!$C:$C,$A6,'API_Test Cases'!$D:$D,$B6,'API_Test Cases'!$F:$F,"Pozitiv") -> 3 | E6: =COUNTIFS('API_Test Cases'!$C:$C,$A6,'API_Test Cases'!$D:$D,$B6,'API_Test Cases'!$F:$F,"Neqativ") -> 2 | F6: =COUNTIFS('API_Test Cases'!$C:$C,$A6,'API_Test Cases'!$D:$D,$B6,'API_Test Cases'!$F:$F,"BVA") -> 1 | G6: =COUNTIFS('API_Test Cases'!$C:$C,$A6,'API_Test Cases'!$D:$D,$B6,'API_Test Cases'!$F:$F,"State transition") -> 0 | H6: =COUNTIFS('API_Test Cases'!$C:$C,$A6,'API_Test Cases'!$D:$D,$B6,'API_Test Cases'!$F:$F,"Schema / Contract") -> 0 | I6: =COUNTIFS('API_Test Cases'!$C:$C,$A6,'API_Test Cases'!$D:$D,$B6,'API_Test Cases'!$F:$F,"Auth") -> 1 | J6: =SUM(D6:I6) -> 7 | K6: =COUNTIFS('API_Test Cases'!$C:$C,$A6,'API_Test Cases'!$D:$D,$B6,'API_Test Cases'!$N:$N,"Automated") -> 4 | L6: =IF(J6=0,0,K6/J6) -> 0.57142857
A7: /cards | B7: POST | C7: GRAD-201 | D7: =COUNTIFS('API_Test Cases'!$C:$C,$A7,'API_Test Cases'!$D:$D,$B7,'API_Test Cases'!$F:$F,"Pozitiv") -> 4 | E7: =COUNTIFS('API_Test Cases'!$C:$C,$A7,'API_Test Cases'!$D:$D,$B7,'API_Test Cases'!$F:$F,"Neqativ") -> 5 | F7: =COUNTIFS('API_Test Cases'!$C:$C,$A7,'API_Test Cases'!$D:$D,$B7,'API_Test Cases'!$F:$F,"BVA") -> 8 | G7: =COUNTIFS('API_Test Cases'!$C:$C,$A7,'API_Test Cases'!$D:$D,$B7,'API_Test Cases'!$F:$F,"State transition") -> 2 | H7: =COUNTIFS('API_Test Cases'!$C:$C,$A7,'API_Test Cases'!$D:$D,$B7,'API_Test Cases'!$F:$F,"Schema / Contract") -> 1 | I7: =COUNTIFS('API_Test Cases'!$C:$C,$A7,'API_Test Cases'!$D:$D,$B7,'API_Test Cases'!$F:$F,"Auth") -> 2 | J7: =SUM(D7:I7) -> 22 | K7: =COUNTIFS('API_Test Cases'!$C:$C,$A7,'API_Test Cases'!$D:$D,$B7,'API_Test Cases'!$N:$N,"Automated") -> 18 | L7: =IF(J7=0,0,K7/J7) -> 0.81818182
A8: /cards/{id} | B8: GET | C8: GRAD-202 | D8: =COUNTIFS('API_Test Cases'!$C:$C,$A8,'API_Test Cases'!$D:$D,$B8,'API_Test Cases'!$F:$F,"Pozitiv") -> 2 | E8: =COUNTIFS('API_Test Cases'!$C:$C,$A8,'API_Test Cases'!$D:$D,$B8,'API_Test Cases'!$F:$F,"Neqativ") -> 1 | F8: =COUNTIFS('API_Test Cases'!$C:$C,$A8,'API_Test Cases'!$D:$D,$B8,'API_Test Cases'!$F:$F,"BVA") -> 0 | G8: =COUNTIFS('API_Test Cases'!$C:$C,$A8,'API_Test Cases'!$D:$D,$B8,'API_Test Cases'!$F:$F,"State transition") -> 0 | H8: =COUNTIFS('API_Test Cases'!$C:$C,$A8,'API_Test Cases'!$D:$D,$B8,'API_Test Cases'!$F:$F,"Schema / Contract") -> 0 | I8: =COUNTIFS('API_Test Cases'!$C:$C,$A8,'API_Test Cases'!$D:$D,$B8,'API_Test Cases'!$F:$F,"Auth") -> 1 | J8: =SUM(D8:I8) -> 4 | K8: =COUNTIFS('API_Test Cases'!$C:$C,$A8,'API_Test Cases'!$D:$D,$B8,'API_Test Cases'!$N:$N,"Automated") -> 3 | L8: =IF(J8=0,0,K8/J8) -> 0.75
A9: /cards/{id}/block | B9: POST | C9: GRAD-203 | D9: =COUNTIFS('API_Test Cases'!$C:$C,$A9,'API_Test Cases'!$D:$D,$B9,'API_Test Cases'!$F:$F,"Pozitiv") -> 0 | E9: =COUNTIFS('API_Test Cases'!$C:$C,$A9,'API_Test Cases'!$D:$D,$B9,'API_Test Cases'!$F:$F,"Neqativ") -> 6 | F9: =COUNTIFS('API_Test Cases'!$C:$C,$A9,'API_Test Cases'!$D:$D,$B9,'API_Test Cases'!$F:$F,"BVA") -> 0 | G9: =COUNTIFS('API_Test Cases'!$C:$C,$A9,'API_Test Cases'!$D:$D,$B9,'API_Test Cases'!$F:$F,"State transition") -> 11 | H9: =COUNTIFS('API_Test Cases'!$C:$C,$A9,'API_Test Cases'!$D:$D,$B9,'API_Test Cases'!$F:$F,"Schema / Contract") -> 0 | I9: =COUNTIFS('API_Test Cases'!$C:$C,$A9,'API_Test Cases'!$D:$D,$B9,'API_Test Cases'!$F:$F,"Auth") -> 1 | J9: =SUM(D9:I9) -> 18 | K9: =COUNTIFS('API_Test Cases'!$C:$C,$A9,'API_Test Cases'!$D:$D,$B9,'API_Test Cases'!$N:$N,"Automated") -> 12 | L9: =IF(J9=0,0,K9/J9) -> 0.66666667
A10: /cards/{id}/unblock | B10: POST | C10: GRAD-204 | D10: =COUNTIFS('API_Test Cases'!$C:$C,$A10,'API_Test Cases'!$D:$D,$B10,'API_Test Cases'!$F:$F,"Pozitiv") -> 1 | E10: =COUNTIFS('API_Test Cases'!$C:$C,$A10,'API_Test Cases'!$D:$D,$B10,'API_Test Cases'!$F:$F,"Neqativ") -> 1 | F10: =COUNTIFS('API_Test Cases'!$C:$C,$A10,'API_Test Cases'!$D:$D,$B10,'API_Test Cases'!$F:$F,"BVA") -> 0 | G10: =COUNTIFS('API_Test Cases'!$C:$C,$A10,'API_Test Cases'!$D:$D,$B10,'API_Test Cases'!$F:$F,"State transition") -> 5 | H10: =COUNTIFS('API_Test Cases'!$C:$C,$A10,'API_Test Cases'!$D:$D,$B10,'API_Test Cases'!$F:$F,"Schema / Contract") -> 0 | I10: =COUNTIFS('API_Test Cases'!$C:$C,$A10,'API_Test Cases'!$D:$D,$B10,'API_Test Cases'!$F:$F,"Auth") -> 0 | J10: =SUM(D10:I10) -> 7 | K10: =COUNTIFS('API_Test Cases'!$C:$C,$A10,'API_Test Cases'!$D:$D,$B10,'API_Test Cases'!$N:$N,"Automated") -> 5 | L10: =IF(J10=0,0,K10/J10) -> 0.71428571
A11: /billers | B11: GET | C11: GRAD-301 | D11: =COUNTIFS('API_Test Cases'!$C:$C,$A11,'API_Test Cases'!$D:$D,$B11,'API_Test Cases'!$F:$F,"Pozitiv") -> 6 | E11: =COUNTIFS('API_Test Cases'!$C:$C,$A11,'API_Test Cases'!$D:$D,$B11,'API_Test Cases'!$F:$F,"Neqativ") -> 3 | F11: =COUNTIFS('API_Test Cases'!$C:$C,$A11,'API_Test Cases'!$D:$D,$B11,'API_Test Cases'!$F:$F,"BVA") -> 0 | G11: =COUNTIFS('API_Test Cases'!$C:$C,$A11,'API_Test Cases'!$D:$D,$B11,'API_Test Cases'!$F:$F,"State transition") -> 0 | H11: =COUNTIFS('API_Test Cases'!$C:$C,$A11,'API_Test Cases'!$D:$D,$B11,'API_Test Cases'!$F:$F,"Schema / Contract") -> 1 | I11: =COUNTIFS('API_Test Cases'!$C:$C,$A11,'API_Test Cases'!$D:$D,$B11,'API_Test Cases'!$F:$F,"Auth") -> 0 | J11: =SUM(D11:I11) -> 10 | K11: =COUNTIFS('API_Test Cases'!$C:$C,$A11,'API_Test Cases'!$D:$D,$B11,'API_Test Cases'!$N:$N,"Automated") -> 6 | L11: =IF(J11=0,0,K11/J11) -> 0.6
A12: /bill-payments | B12: POST | C12: GRAD-302 | D12: =COUNTIFS('API_Test Cases'!$C:$C,$A12,'API_Test Cases'!$D:$D,$B12,'API_Test Cases'!$F:$F,"Pozitiv") -> 9 | E12: =COUNTIFS('API_Test Cases'!$C:$C,$A12,'API_Test Cases'!$D:$D,$B12,'API_Test Cases'!$F:$F,"Neqativ") -> 10 | F12: =COUNTIFS('API_Test Cases'!$C:$C,$A12,'API_Test Cases'!$D:$D,$B12,'API_Test Cases'!$F:$F,"BVA") -> 9 | G12: =COUNTIFS('API_Test Cases'!$C:$C,$A12,'API_Test Cases'!$D:$D,$B12,'API_Test Cases'!$F:$F,"State transition") -> 0 | H12: =COUNTIFS('API_Test Cases'!$C:$C,$A12,'API_Test Cases'!$D:$D,$B12,'API_Test Cases'!$F:$F,"Schema / Contract") -> 1 | I12: =COUNTIFS('API_Test Cases'!$C:$C,$A12,'API_Test Cases'!$D:$D,$B12,'API_Test Cases'!$F:$F,"Auth") -> 1 | J12: =SUM(D12:I12) -> 30 | K12: =COUNTIFS('API_Test Cases'!$C:$C,$A12,'API_Test Cases'!$D:$D,$B12,'API_Test Cases'!$N:$N,"Automated") -> 25 | L12: =IF(J12=0,0,K12/J12) -> 0.83333333
A13: /bill-payments | B13: GET | C13: GRAD-303 | D13: =COUNTIFS('API_Test Cases'!$C:$C,$A13,'API_Test Cases'!$D:$D,$B13,'API_Test Cases'!$F:$F,"Pozitiv") -> 6 | E13: =COUNTIFS('API_Test Cases'!$C:$C,$A13,'API_Test Cases'!$D:$D,$B13,'API_Test Cases'!$F:$F,"Neqativ") -> 4 | F13: =COUNTIFS('API_Test Cases'!$C:$C,$A13,'API_Test Cases'!$D:$D,$B13,'API_Test Cases'!$F:$F,"BVA") -> 3 | G13: =COUNTIFS('API_Test Cases'!$C:$C,$A13,'API_Test Cases'!$D:$D,$B13,'API_Test Cases'!$F:$F,"State transition") -> 0 | H13: =COUNTIFS('API_Test Cases'!$C:$C,$A13,'API_Test Cases'!$D:$D,$B13,'API_Test Cases'!$F:$F,"Schema / Contract") -> 1 | I13: =COUNTIFS('API_Test Cases'!$C:$C,$A13,'API_Test Cases'!$D:$D,$B13,'API_Test Cases'!$F:$F,"Auth") -> 0 | J13: =SUM(D13:I13) -> 14 | K13: =COUNTIFS('API_Test Cases'!$C:$C,$A13,'API_Test Cases'!$D:$D,$B13,'API_Test Cases'!$N:$N,"Automated") -> 11 | L13: =IF(J13=0,0,K13/J13) -> 0.78571429
A14: Cəmi | D14: =SUM(D2:D13) -> 50 | E14: =SUM(E2:E13) -> 49 | F14: =SUM(F2:F13) -> 34 | G14: =SUM(G2:G13) -> 18 | H14: =SUM(H2:H13) -> 6 | I14: =SUM(I2:I13) -> 11 | J14: =SUM(J2:J13) -> 168 | K14: =SUM(K2:K13) -> 123 | L14: =IF(J14=0,0,K14/J14) -> 0.73214286
A16: Qeyd: bir neçə endpoint-ə toxunan ssenarilər (məs. bloklanmış kartla ödəniş) əsas yoxlanılan endpoint-ə görə sayılır. Cəmi TC sayı API_Test Cases sheet-indəki sətir sayı ilə üst-üstə düşməlidir.

Sheet API_Traceability
A1: Requirement (Task / AC) | B1: Acceptance criteria (qısa) | C1: Scenario ID | D1: Test Case ID-lər | E1: Avtomat TC sayı | F1: Status | G1: RestAssured test class
A2: GRAD-101 AC-1 | B2: Etibarlı sorğu → 201, id/iban/ibanMasked/currency/nickname/createdAt, Location header | C2: SC_API_02 | D2: TC_API_BEN_001, TC_API_BEN_002 | E2: 2 | F2: Əhatə olunub | G2: BeneficiaryTest.Create
A3: GRAD-101 AC-2 | B3: Boşluqlu/kiçik hərfli IBAN normallaşdırılır | C3: SC_API_02 | D3: TC_API_BEN_003, TC_API_BEN_025 | E3: 2 | F3: Əhatə olunub | G3: BeneficiaryTest.Create
A4: GRAD-101 AC-3 | B4: nickname yoxdursa null | C4: SC_API_02 | D4: TC_API_BEN_004 | E4: 1 | F4: Əhatə olunub | G4: BeneficiaryTest.Create
A5: GRAD-101 AC-4 | B5: Bir neçə səhv sahə → hər biri details-də | C5: SC_API_02 | D5: TC_API_BEN_005 | E5: 1 | F5: Əhatə olunub | G5: BeneficiaryTest.Create
A6: GRAD-101 AC-5 | B6: fullName 1/51 rədd, 2/50 qəbul | C6: SC_API_02 | D6: TC_API_BEN_006, TC_API_BEN_007, TC_API_BEN_008, TC_API_BEN_009, TC_API_BEN_010 | E6: 4 | F6: Əhatə olunub | G6: BeneficiaryTest.Create
A7: GRAD-101 AC-6 | B7: fullName "---" / "Ali2" rədd | C7: SC_API_02 | D7: TC_API_BEN_011, TC_API_BEN_012 | E7: 2 | F7: Əhatə olunub | G7: BeneficiaryTest.Create
A8: GRAD-101 AC-7 | B8: Dublikat IBAN → 409 BENEFICIARY_EXISTS | C8: SC_API_02 | D8: TC_API_BEN_024, TC_API_BEND_006 | E8: 1 | F8: Əhatə olunub | G8: BeneficiaryTest.Create
A9: GRAD-101 AC-8 | B9: Ləqəb case-insensitive → 409 NICKNAME_TAKEN | C9: SC_API_02 | D9: TC_API_BEN_026 | E9: 1 | F9: Əhatə olunub | G9: BeneficiaryTest.Create
A10: GRAD-101 AC-9 | B10: Öz IBAN-ı → 422 OWN_ACCOUNT | C10: SC_API_02 | D10: TC_API_BEN_027 | E10: 1 | F10: Əhatə olunub | G10: BeneficiaryTest.Create
A11: GRAD-101 AC-10 | B11: 11-ci alıcı → 422 LIMIT_REACHED | C11: SC_API_02 | D11: TC_API_BEN_029, TC_API_BEN_030, TC_API_BEND_007 | E11: 2 | F11: Əhatə olunub | G11: BeneficiaryTest.Create
A12: GRAD-102 AC-1 | B12: Parametrsiz: total = items.length, ən yeni birinci | C12: SC_API_03 | D12: TC_API_BENL_001, TC_API_BENL_002 | E12: 2 | F12: Əhatə olunub | G12: BeneficiaryTest.ListBeneficiaries
A13: GRAD-102 AC-2 | B13: sort=fullName asc — Azərbaycan əlifbası | C13: SC_API_03 | D13: TC_API_BENL_003, TC_API_BENL_004 | E13: 1 | F13: Əhatə olunub | G13: BeneficiaryTest.ListBeneficiaries
... A71: Əlavə (backlog qaydaları) | B71: Ümumi qaydalar: 401, sandbox izolyasiyası, rate limit, 404 (başqasının resursu), pul sahəsinin tipi, yoxlama ardıcıllığı, Qeydlər bölmələri | C71: SC_API_01 + hamısı | D71: TC_API_AUTH_001, TC_API_AUTH_002, TC_API_SEC_001, TC_API_SEC_002, TC_API_SEC_003, TC_API_SEC_004, TC_API_SEC_005, TC_API_SEC_006, TC_API_BEN_013, TC_API_BEN_014, TC_API_BEN_015, TC_API_BEN_016, TC_API_BEN_017, TC_API_BEN_018, TC_API_BEN_019, TC_API_BEN_020, TC_API_BEN_021, TC_API_BEN_022, TC_API_BEN_023, TC_API_BEN_028, TC_API_BENL_005, TC_API_BENL_015, TC_API_BENL_016, TC_API_BENL_017, TC_API_BENL_018, TC_API_BEND_005, TC_API_CARD_004, TC_API_CARD_011, TC_API_CARD_012, TC_API_CARD_013, TC_API_CARD_015, TC_API_CARD_021, TC_API_CARDG_004, TC_API_BLK_003, TC_API_BLK_005, TC_API_BLK_012, TC_API_BLK_013, TC_API_BLK_014, TC_API_BLK_015, TC_API_BLK_016, TC_API_UNB_006, TC_API_UNB_007, TC_API_BIL_002, TC_API_BIL_003, TC_API_BIL_005, TC_API_BIL_006, TC_API_BIL_008, TC_API_PAY_008, TC_API_PAY_009, TC_API_PAY_011, TC_API_PAY_012, TC_API_PAY_015, TC_API_PAY_017, TC_API_PAY_020, TC_API_PAY_022, TC_API_PAY_025, TC_API_PAY_026, TC_API_PAY_027, TC_API_PAY_028, TC_API_PAY_029, TC_API_PAY_030, TC_API_HIS_007, TC_API_HIS_011, TC_API_HIS_012 | E71: 30 | F71: Əhatə olunub | G71: AuthSecurityTest, BeneficiaryTest.Create, BillPaymentTest, BillerTest, CardStateTransitionTest, CardTest.Create, CardTest.Get, PaymentHistoryTest

Sheet API_Grooming Questions
A1: GQ ID | B1: Endpoint | C1: Sual | D1: Niyə vacibdir (risk) | E1: Əlaqəli TC | F1: Qəbul edilmiş fərziyyə | G1: Status
A2: GQ_API_01 | B2: POST /cards | C2: Ümumi qayda "başqa istifadəçinin resursu → 404 (403 yox)" deyir, GRAD-201 AC-5 isə başqasının hesabı (acc_003) üçün 403 FORBIDDEN gözləyir. Hansı doğrudur? | D2: 403 resursun mövcudluğunu açıqlayır — ümumi təhlükəsizlik qaydası ilə ziddiyyət | E2: TC_API_CARD_014 | F2: Təsdiqləndi (icra): API başqasının hesabı üçün 403 FORBIDDEN qaytarır — ümumi qayda ilə ziddiyyət qalır, BUG_API_001 | G2: Cavablandı
A3: GQ_API_02 | B3: POST /beneficiaries | C3: AC-10-da LIMIT_REACHED cavabında "limit": 10 göstərilib, amma sahənin cavabdakı yeri (kök səviyyə və ya details) təyin olunmayıb. | D3: Assert yolu səhv yazılarsa test yanlış düşər | E3: TC_API_BEN_030 | F3: Təsdiqləndi: "limit": 10 kök səviyyədədir | G3: Cavablandı
A4: GQ_API_03 | B4: POST /beneficiaries | C4: IBAN yalnız format (AZ + 2 rəqəm + 4 hərf + 20 simvol) üzrə yoxlanılır, yoxsa mod-97 nəzarət rəqəmi də yoxlanılır? | D4: Nəzarət rəqəmi yoxlanılırsa test datası (uydurma IBAN-lar) rədd ediləcək | E4: TC_API_BEN_002…030 | F4: Təsdiqləndi: uydurma (nəzarət rəqəmsiz) IBAN-lar qəbul olunur — yalnız format yoxlanılır | G4: Cavablandı
A5: GQ_API_04 | B5: POST /beneficiaries | C5: fullName trim-dən sonra saxlanılırmı? " Nigar " göndərildikdə cavabda trim olunmuş dəyər qaytarılırmı? | D5: Dublikat və axtarış davranışına təsir edir | E5: TC_API_BEN_010 | F5: Uzunluq trim-dən sonra hesablanır; saxlanılan dəyər də trim olunur | G5: Açıq
A6: GQ_API_05 | B6: GET /beneficiaries | C6: q boş string (q=) göndərildikdə nə olur: 400 (min 2) və ya parametr nəzərə alınmır? | D6: Boş axtarış sahəsi UI-da tez-tez göndərilir | E6: — | F6: q= → 400 VALIDATION_ERROR (min 2 qaydası) | G6: Açıq
A7: GQ_API_06 | B7: GET /beneficiaries | C7: sort=fullName zamanı Azərbaycan əlifbası (C < Ç, E < Ə, I < İ) dəqiq necə tətbiq olunur? Böyük-kiçik hərf sıralamaya təsir edirmi? | D7: Sıralama assert-ləri əlifba qaydasından asılıdır | E7: TC_API_BENL_003, 004 | F7: Təsdiqləndi: Azərbaycan əlifbası tətbiq olunur (C<Ç<E<Ə) | G7: Cavablandı
A8: GQ_API_07 | B8: Bütün enum sahələr | C8: Enum dəyərləri (currency, reason, category) kiçik hərflə göndərildikdə rədd edilir, yoxsa normallaşdırılır? IBAN üçün normallaşdırma var, digərləri üçün qeyd yoxdur. | D8: Davranış qeyri-müəyyəndir | E8: TC_API_BLK_013, TC_API_BIL_008 | F8: Təsdiqləndi: kiçik hərfli enum dəyərləri (temporary, mobile) 400 ilə rədd edilir | G8: Cavablandı
A9: GQ_API_08 | B9: POST /cards/{id}/block | C9: Bloklama/dondurma kartın availableBalance-ına təsir edirmi? BLOCKED kartdakı vəsait nə olur (qaytarılır?) | D9: Pul itkisi riski — biznes qaydası təsvir olunmayıb | E9: TC_API_BLK_002 | F9: Balans dəyişmir; vəsaitin taleyi bu sprintin scope-undan kənardır | G9: Açıq
A10: GQ_API_09 | B10: POST /bill-payments | C10: spentToday Bakı vaxtı 00:00-da sıfırlanır. Gündəlik limit testləri gecə yarısına yaxın icra olunarsa nəticə dəyişir. Test mühitində vaxtı idarə etmək imkanı varmı? | D10: Flaky test riski | E10: TC_API_PAY_019, 020, 030 | F10: Limit testləri 23:30–00:30 (GMT+4) arasında icra edilmir | G10: Açıq
A11: GQ_API_10 | B11: POST /bill-payments | C11: Idempotency replay (AC-4) zamanı cavab body-si 1-ci cavabla tam eynidirmi (balanceAfter daxil), yoxsa cari balans qaytarılır? | D11: Replay assert-i hansı sahələrə yazılmalıdır | E11: TC_API_PAY_005 | F11: Body 1-ci cavabla eynidir (balanceAfter dəyişmir) | G11: Açıq
A12: GQ_API_11 | B12: POST /bill-payments | C12: Idempotency-Key istifadəçiyə/token-ə bağlıdırmı? Eyni açarı başqa user göndərsə nə olur? | D12: Açarların toqquşması başqa istifadəçinin ödənişini "replay" edə bilər | E12: — | F12: Açar token (sandbox) daxilində unikaldır | G12: Açıq
... A15: GQ_API_14 | B15: GET /bill-payments | C15: from/to filtri Bakı vaxtı ilə işləyir, cavabdakı createdAt isə UTC (Z) formatındadır. 00:00–04:00 (GMT+4) arasında edilən ödəniş hansı günə düşür? | D15: Tarix sərhədi testlərində çaşqınlıq | E15: TC_API_HIS_009 | F15: Filtr Bakı vaxtına görə tətbiq olunur, createdAt UTC-də qaytarılır | G15: Açıq
